{"info": {"city": "Kolkata", "dates": [{"month": 12, "day": 24, "year": 2009}], "match_type": "ODI", "toss": {"decision": "bat", "winner": "Sri Lanka"}, "venue": "Eden Gardens", "teams": ["India", "Sri Lanka"], "umpires": ["M Erasmus", "SS Hazare"], "player_of_match": ["G Gambhir"], "outcome": {"winner": "India", "by": {"wickets": 7}}, "overs": 50}, "innings": [{"1st innings": {"deliveries": [{"0.1": {"batsman": "WU Tharanga", "bowler": "Z Khan", "runs": {"batsman": 0, "total": 0, "extras": 0}, "non_striker": "TM Dilshan"}}, {"0.2": {"batsman": "WU Tharanga", "bowler": "Z Khan", "runs": {"batsman": 0, "total": 0, "extras": 0}, "non_striker": "TM Dilshan"}}, {"0.3": {"batsman": "WU Tharanga", "bowler": "Z Khan", "runs": {"batsman": 1, "total": 1, "extras": 0}, "non_striker": "TM Dilshan"}}, {"0.4": {"batsman": "TM Dilshan", "bowler": "Z Khan", "runs": {"batsman": 0, "total": 0, "extras": 0}, "non_striker": "WU Tharanga"}}, {"0.5": {"batsman": "TM Dilshan", "bowler": "Z Khan", "runs": {"batsman": 0, "total": 0, "extras": 0}, "non_striker": "WU Tharanga"}}, {"0.6": {"batsman": "TM Dilshan", "bowler": "Z Khan", "runs": {"batsman": 0, "total": 0, "extras": 0}, "non_striker": "WU Tharanga"}}, {"1.1": {"batsman": "WU Tharanga", "bowler": "A Nehra", "runs": {"batsman": 0, "total": 0, "extras": 0}, "non_striker": "TM Dilshan"}}, {"1.2": {"batsman": "WU Tharanga", "bowler": "A Nehra", "runs": {"batsman": 0, "total": 0, "extras": 0}, "non_striker": "TM Dilshan"}}, {"1.3": {"batsman": "WU Tharanga", "bowler": "A Nehra", "runs": {"batsman": 0, "total": 0, "extras": 0}, "non_striker": "TM Dilshan"}}, {"1.4": {"batsman": "WU Tharanga", "bowler": "A Nehra", "runs": {"batsman": 0, "total": 0, "extras": 0}, "non_striker": "TM Dilshan"}}, {"1.5": {"batsman": "WU Tharanga", "bowler": "A Nehra", "runs": {"batsman": 0, "total": 0, "extras": 0}, "non_striker": "TM Dilshan"}}, {"1.6": {"batsman": "WU Tharanga", "bowler": "A Nehra", "runs": {"batsman": 0, "total": 0, "extras": 0}, "non_striker": "TM Dilshan"}}, {"2.1": {"batsman": "TM Dilshan", "bowler": "Z Khan", "runs": {"batsman": 1, "total": 1, "extras": 0}, "non_striker": "WU Tharanga"}}, {"2.2": {"batsman": "WU Tharanga", "bowler": "Z Khan", "runs": {"batsman": 1, "total": 1, "extras": 0}, "non_striker": "TM Dilshan"}}, {"2.3": {"batsman": "TM Dilshan", "bowler": "Z Khan", "runs": {"batsman": 1, "total": 1, "extras": 0}, "non_striker": "WU Tharanga"}}, {"2.4": {"batsman": "WU Tharanga", "bowler": "Z Khan", "runs": {"batsman": 0, "total": 0, "extras": 0}, "non_striker": "TM Dilshan"}}, {"2.5": {"batsman": "WU Tharanga", "bowler": "Z Khan", "runs": {"batsman": 0, "total": 0, "extras": 0}, "non_striker": "TM Dilshan"}}, {"2.6": {"batsman": "WU Tharanga", "bowler": "Z Khan", "runs": {"batsman": 0, "total": 0, "extras": 0}, "non_striker": "TM Dilshan"}}, {"3.1": {"batsman": "TM Dilshan", "bowler": "A Nehra", "runs": {"batsman": 0, "total": 0, "extras": 0}, "non_striker": "WU Tharanga"}}, {"3.2": {"batsman": "TM Dilshan", "bowler": "A Nehra", "runs": {"batsman": 0, "total": 0, "extras": 0}, "non_striker": "WU Tharanga"}}, {"3.3": {"batsman": "TM Dilshan", "bowler": "A Nehra", "runs": {"batsman": 1, "total": 1, "extras": 0}, "non_striker": "WU Tharanga"}}, {"3.4": {"batsman": "WU Tharanga", "bowler": "A Nehra", "runs": {"batsman": 1, "total": 1, "extras": 0}, "non_striker": "TM Dilshan"}}, {"3.5": {"batsman": "TM Dilshan", "bowler": "A Nehra", "runs": {"batsman": 0, "total": 1, "extras": 1}, "extras": {"wides": 1}, "non_striker": "WU Tharanga"}}, {"3.6": {"batsman": "TM Dilshan", "bowler": "A Nehra", "runs": {"batsman": 0, "total": 1, "extras": 1}, "extras": {"legbyes": 1}, "non_striker": "WU Tharanga"}}, {"3.7": {"batsman": "WU Tharanga", "bowler": "A Nehra", "runs": {"batsman": 0, "total": 0, "extras": 0}, "non_striker": "TM Dilshan"}}, {"4.1": {"batsman": "TM Dilshan", "bowler": "Z Khan", "runs": {"batsman": 0, "total": 0, "extras": 0}, "non_striker": "WU Tharanga"}}, {"4.2": {"batsman": "TM Dilshan", "bowler": "Z Khan", "runs": {"batsman": 0, "total": 0, "extras": 0}, "non_striker": "WU Tharanga"}}, {"4.3": {"batsman": "TM Dilshan", "bowler": "Z Khan", "runs": {"batsman": 1, "total": 1, "extras": 0}, "non_striker": "WU Tharanga"}}, {"4.4": {"batsman": "WU Tharanga", "bowler": "Z Khan", "runs": {"batsman": 0, "total": 0, "extras": 0}, "non_striker": "TM Dilshan"}}, {"4.5": {"batsman": "WU Tharanga", "bowler": "Z Khan", "runs": {"batsman": 0, "total": 0, "extras": 0}, "non_striker": "TM Dilshan"}}, {"4.6": {"batsman": "WU Tharanga", "bowler": "Z Khan", "runs": {"batsman": 0, "total": 0, "extras": 0}, "non_striker": "TM Dilshan"}}, {"5.1": {"batsman": "TM Dilshan", "bowler": "A Nehra", "runs": {"batsman": 4, "total": 4, "extras": 0}, "non_striker": "WU Tharanga"}}, {"5.2": {"batsman": "TM Dilshan", "bowler": "A Nehra", "runs": {"batsman": 0, "total": 1, "extras": 1}, "extras": {"legbyes": 1}, "non_striker": "WU Tharanga"}}, {"5.3": {"batsman": "WU Tharanga", "bowler": "A Nehra", "runs": {"batsman": 0, "total": 0, "extras": 0}, "non_striker": "TM Dilshan"}}, {"5.4": {"batsman": "WU Tharanga", "bowler": "A Nehra", "runs": {"batsman": 4, "total": 4, "extras": 0}, "non_striker": "TM Dilshan"}}, {"5.5": {"batsman": "WU Tharanga", "bowler": "A Nehra", "runs": {"batsman": 0, "total": 0, "extras": 0}, "non_striker": "TM Dilshan"}}, {"5.6": {"batsman": "WU Tharanga", "bowler": "A Nehra", "runs": {"batsman": 4, "total": 4, "extras": 0}, "non_striker": "TM Dilshan"}}, {"6.1": {"batsman": "TM Dilshan", "bowler": "Z Khan", "runs": {"batsman": 0, "total": 0, "extras": 0}, "non_striker": "WU Tharanga"}}, {"6.2": {"batsman": "TM Dilshan", "bowler": "Z Khan", "runs": {"batsman": 1, "total": 1, "extras": 0}, "non_striker": "WU Tharanga"}}, {"6.3": {"batsman": "WU Tharanga", "bowler": "Z Khan", "runs": {"batsman": 0, "total": 0, "extras": 0}, "non_striker": "TM Dilshan"}}, {"6.4": {"batsman": "WU Tharanga", "bowler": "Z Khan", "runs": {"batsman": 1, "total": 1, "extras": 0}, "non_striker": "TM Dilshan"}}, {"6.5": {"batsman": "TM Dilshan", "bowler": "Z Khan", "runs": {"batsman": 0, "total": 0, "extras": 0}, "non_striker": "WU Tharanga"}}, {"6.6": {"batsman": "TM Dilshan", "bowler": "Z Khan", "runs": {"batsman": 0, "total": 0, "extras": 0}, "non_striker": "WU Tharanga"}}, {"7.1": {"batsman": "WU Tharanga", "bowler": "A Nehra", "runs": {"batsman": 0, "total": 0, "extras": 0}, "non_striker": "TM Dilshan"}}, {"7.2": {"batsman": "WU Tharanga", "bowler": "A Nehra", "runs": {"batsman": 0, "total": 0, "extras": 0}, "non_striker": "TM Dilshan"}}, {"7.3": {"batsman": "WU Tharanga", "bowler": "A Nehra", "runs": {"batsman": 6, "total": 6, "extras": 0}, "non_striker": "TM Dilshan"}}, {"7.4": {"batsman": "WU Tharanga", "bowler": "A Nehra", "runs": {"batsman": 0, "total": 0, "extras": 0}, "non_striker": "TM Dilshan"}}, {"7.5": {"batsman": "WU Tharanga", "bowler": "A Nehra", "runs": {"batsman": 1, "total": 1, "extras": 0}, "non_striker": "TM Dilshan"}}, {"7.6": {"batsman": "TM Dilshan", "bowler": "A Nehra", "runs": {"batsman": 0, "total": 0, "extras": 0}, "non_striker": "WU Tharanga", "wicket": {"fielders": ["V Kohli"], "kind": "caught", "player_out": "TM Dilshan"}}}, {"8.1": {"batsman": "WU Tharanga", "bowler": "Z Khan", "runs": {"batsman": 0, "total": 0, "extras": 0}, "non_striker": "ST Jayasuriya"}}, {"8.2": {"batsman": "WU Tharanga", "bowler": "Z Khan", "runs": {"batsman": 0, "total": 0, "extras": 0}, "non_striker": "ST Jayasuriya"}}, {"8.3": {"batsman": "WU Tharanga", "bowler": "Z Khan", "runs": {"batsman": 4, "total": 4, "extras": 0}, "non_striker": "ST Jayasuriya"}}, {"8.4": {"batsman": "WU Tharanga", "bowler": "Z Khan", "runs": {"batsman": 0, "total": 0, "extras": 0}, "non_striker": "ST Jayasuriya"}}, {"8.5": {"batsman": "WU Tharanga", "bowler": "Z Khan", "runs": {"batsman": 0, "total": 0, "extras": 0}, "non_striker": "ST Jayasuriya"}}, {"8.6": {"batsman": "WU Tharanga", "bowler": "Z Khan", "runs": {"batsman": 0, "total": 0, "extras": 0}, "non_striker": "ST Jayasuriya"}}, {"9.1": {"batsman": "ST Jayasuriya", "bowler": "A Nehra", "runs": {"batsman": 4, "total": 4, "extras": 0}, "non_striker": "WU Tharanga"}}, {"9.2": {"batsman": "ST Jayasuriya", "bowler": "A Nehra", "runs": {"batsman": 0, "total": 0, "extras": 0}, "non_striker": "WU Tharanga"}}, {"9.3": {"batsman": "ST Jayasuriya", "bowler": "A Nehra", "runs": {"batsman": 4, "total": 4, "extras": 0}, "non_striker": "WU Tharanga"}}, {"9.4": {"batsman": "ST Jayasuriya", "bowler": "A Nehra", "runs": {"batsman": 0, "total": 0, "extras": 0}, "non_striker": "WU Tharanga"}}, {"9.5": {"batsman": "ST Jayasuriya", "bowler": "A Nehra", "runs": {"batsman": 1, "total": 1, "extras": 0}, "non_striker": "WU Tharanga"}}, {"9.6": {"batsman": "WU Tharanga", "bowler": "A Nehra", "runs": {"batsman": 1, "total": 1, "extras": 0}, "non_striker": "ST Jayasuriya"}}, {"10.1": {"batsman": "WU Tharanga", "bowler": "Z Khan", "runs": {"batsman": 1, "total": 1, "extras": 0}, "non_striker": "ST Jayasuriya"}}, {"10.2": {"batsman": "ST Jayasuriya", "bowler": "Z Khan", "runs": {"batsman": 0, "total": 0, "extras": 0}, "non_striker": "WU Tharanga"}}, {"10.3": {"batsman": "ST Jayasuriya", "bowler": "Z Khan", "runs": {"batsman": 2, "total": 2, "extras": 0}, "non_striker": "WU Tharanga"}}, {"10.4": {"batsman": "ST Jayasuriya", "bowler": "Z Khan", "runs": {"batsman": 0, "total": 0, "extras": 0}, "non_striker": "WU Tharanga"}}, {"10.5": {"batsman": "ST Jayasuriya", "bowler": "Z Khan", "runs": {"batsman": 0, "total": 0, "extras": 0}, "non_striker": "WU Tharanga"}}, {"10.6": {"batsman": "ST Jayasuriya", "bowler": "Z Khan", "runs": {"batsman": 0, "total": 0, "extras": 0}, "non_striker": "WU Tharanga"}}, {"11.1": {"batsman": "WU Tharanga", "bowler": "I Sharma", "runs": {"batsman": 4, "total": 4, "extras": 0}, "non_striker": "ST Jayasuriya"}}, {"11.2": {"batsman": "WU Tharanga", "bowler": "I Sharma", "runs": {"batsman": 0, "total": 0, "extras": 0}, "non_striker": "ST Jayasuriya"}}, {"11.3": {"batsman": "WU Tharanga", "bowler": "I Sharma", "runs": {"batsman": 4, "total": 4, "extras": 0}, "non_striker": "ST Jayasuriya"}}, {"11.4": {"batsman": "WU Tharanga", "bowler": "I Sharma", "runs": {"batsman": 4, "total": 4, "extras": 0}, "non_striker": "ST Jayasuriya"}}, {"11.5": {"batsman": "WU Tharanga", "bowler": "I Sharma", "runs": {"batsman": 4, "total": 4, "extras": 0}, "non_striker": "ST Jayasuriya"}}, {"11.6": {"batsman": "WU Tharanga", "bowler": "I Sharma", "runs": {"batsman": 4, "total": 4, "extras": 0}, "non_striker": "ST Jayasuriya"}}, {"12.1": {"batsman": "ST Jayasuriya", "bowler": "Z Khan", "runs": {"batsman": 4, "total": 4, "extras": 0}, "non_striker": "WU Tharanga"}}, {"12.2": {"batsman": "ST Jayasuriya", "bowler": "Z Khan", "runs": {"batsman": 0, "total": 0, "extras": 0}, "non_striker": "WU Tharanga"}}, {"12.3": {"batsman": "ST Jayasuriya", "bowler": "Z Khan", "runs": {"batsman": 0, "total": 0, "extras": 0}, "non_striker": "WU Tharanga"}}, {"12.4": {"batsman": "ST Jayasuriya", "bowler": "Z Khan", "runs": {"batsman": 0, "total": 0, "extras": 0}, "non_striker": "WU Tharanga"}}, {"12.5": {"batsman": "ST Jayasuriya", "bowler": "Z Khan", "runs": {"batsman": 0, "total": 0, "extras": 0}, "non_striker": "WU Tharanga", "wicket": {"fielders": ["SR Tendulkar"], "kind": "caught", "player_out": "ST Jayasuriya"}}}, {"12.6": {"batsman": "KC Sangakkara", "bowler": "Z Khan", "runs": {"batsman": 0, "total": 0, "extras": 0}, "non_striker": "WU Tharanga"}}, {"13.1": {"batsman": "WU Tharanga", "bowler": "I Sharma", "runs": {"batsman": 1, "total": 1, "extras": 0}, "non_striker": "KC Sangakkara"}}, {"13.2": {"batsman": "KC Sangakkara", "bowler": "I Sharma", "runs": {"batsman": 0, "total": 0, "extras": 0}, "non_striker": "WU Tharanga"}}, {"13.3": {"batsman": "KC Sangakkara", "bowler": "I Sharma", "runs": {"batsman": 0, "total": 0, "extras": 0}, "non_striker": "WU Tharanga"}}, {"13.4": {"batsman": "KC Sangakkara", "bowler": "I Sharma", "runs": {"batsman": 0, "total": 0, "extras": 0}, "non_striker": "WU Tharanga"}}, {"13.5": {"batsman": "KC Sangakkara", "bowler": "I Sharma", "runs": {"batsman": 1, "total": 1, "extras": 0}, "non_striker": "WU Tharanga"}}, {"13.6": {"batsman": "WU Tharanga", "bowler": "I Sharma", "runs": {"batsman": 4, "total": 4, "extras": 0}, "non_striker": "KC Sangakkara"}}, {"14.1": {"batsman": "KC Sangakkara", "bowler": "A Nehra", "runs": {"batsman": 4, "total": 4, "extras": 0}, "non_striker": "WU Tharanga"}}, {"14.2": {"batsman": "KC Sangakkara", "bowler": "A Nehra", "runs": {"batsman": 0, "total": 0, "extras": 0}, "non_striker": "WU Tharanga"}}, {"14.3": {"batsman": "KC Sangakkara", "bowler": "A Nehra", "runs": {"batsman": 1, "total": 1, "extras": 0}, "non_striker": "WU Tharanga"}}, {"14.4": {"batsman": "WU Tharanga", "bowler": "A Nehra", "runs": {"batsman": 2, "total": 2, "extras": 0}, "non_striker": "KC Sangakkara"}}, {"14.5": {"batsman": "WU Tharanga", "bowler": "A Nehra", "runs": {"batsman": 4, "total": 4, "extras": 0}, "non_striker": "KC Sangakkara"}}, {"14.6": {"batsman": "WU Tharanga", "bowler": "A Nehra", "runs": {"batsman": 0, "total": 1, "extras": 1}, "extras": {"wides": 1}, "non_striker": "KC Sangakkara"}}, {"14.7": {"batsman": "WU Tharanga", "bowler": "A Nehra", "runs": {"batsman": 0, "total": 1, "extras": 1}, "extras": {"wides": 1}, "non_striker": "KC Sangakkara"}}, {"14.8": {"batsman": "WU Tharanga", "bowler": "A Nehra", "runs": {"batsman": 0, "total": 0, "extras": 0}, "non_striker": "KC Sangakkara"}}, {"15.1": {"batsman": "KC Sangakkara", "bowler": "I Sharma", "runs": {"batsman": 0, "total": 0, "extras": 0}, "non_striker": "WU Tharanga"}}, {"15.2": {"batsman": "KC Sangakkara", "bowler": "I Sharma", "runs": {"batsman": 0, "total": 0, "extras": 0}, "non_striker": "WU Tharanga"}}, {"15.3": {"batsman": "KC Sangakkara", "bowler": "I Sharma", "runs": {"batsman": 0, "total": 0, "extras": 0}, "non_striker": "WU Tharanga"}}, {"15.4": {"batsman": "KC Sangakkara", "bowler": "I Sharma", "runs": {"batsman": 0, "total": 0, "extras": 0}, "non_striker": "WU Tharanga"}}, {"15.5": {"batsman": "KC Sangakkara", "bowler": "I Sharma", "runs": {"batsman": 1, "total": 1, "extras": 0}, "non_striker": "WU Tharanga"}}, {"15.6": {"batsman": "WU Tharanga", "bowler": "I Sharma", "runs": {"batsman": 0, "total": 1, "extras": 1}, "extras": {"wides": 1}, "non_striker": "KC Sangakkara"}}, {"15.7": {"batsman": "WU Tharanga", "bowler": "I Sharma", "runs": {"batsman": 0, "total": 0, "extras": 0}, "non_striker": "KC Sangakkara"}}, {"16.1": {"batsman": "KC Sangakkara", "bowler": "Harbhajan Singh", "runs": {"batsman": 0, "total": 0, "extras": 0}, "non_striker": "WU Tharanga"}}, {"16.2": {"batsman": "KC Sangakkara", "bowler": "Harbhajan Singh", "runs": {"batsman": 1, "total": 1, "extras": 0}, "non_striker": "WU Tharanga"}}, {"16.3": {"batsman": "WU Tharanga", "bowler": "Harbhajan Singh", "runs": {"batsman": 1, "total": 1, "extras": 0}, "non_striker": "KC Sangakkara"}}, {"16.4": {"batsman": "KC Sangakkara", "bowler": "Harbhajan Singh", "runs": {"batsman": 1, "total": 1, "extras": 0}, "non_striker": "WU Tharanga"}}, {"16.5": {"batsman": "WU Tharanga", "bowler": "Harbhajan Singh", "runs": {"batsman": 2, "total": 2, "extras": 0}, "non_striker": "KC Sangakkara"}}, {"16.6": {"batsman": "WU Tharanga", "bowler": "Harbhajan Singh", "runs": {"batsman": 1, "total": 1, "extras": 0}, "non_striker": "KC Sangakkara"}}, {"17.1": {"batsman": "WU Tharanga", "bowler": "I Sharma", "runs": {"batsman": 0, "total": 0, "extras": 0}, "non_striker": "KC Sangakkara"}}, {"17.2": {"batsman": "WU Tharanga", "bowler": "I Sharma", "runs": {"batsman": 1, "total": 1, "extras": 0}, "non_striker": "KC Sangakkara"}}, {"17.3": {"batsman": "KC Sangakkara", "bowler": "I Sharma", "runs": {"batsman": 2, "total": 2, "extras": 0}, "non_striker": "WU Tharanga"}}, {"17.4": {"batsman": "KC Sangakkara", "bowler": "I Sharma", "runs": {"batsman": 0, "total": 0, "extras": 0}, "non_striker": "WU Tharanga"}}, {"17.5": {"batsman": "KC Sangakkara", "bowler": "I Sharma", "runs": {"batsman": 1, "total": 1, "extras": 0}, "non_striker": "WU Tharanga"}}, {"17.6": {"batsman": "WU Tharanga", "bowler": "I Sharma", "runs": {"batsman": 0, "total": 0, "extras": 0}, "non_striker": "KC Sangakkara"}}, {"18.1": {"batsman": "KC Sangakkara", "bowler": "Harbhajan Singh", "runs": {"batsman": 0, "total": 0, "extras": 0}, "non_striker": "WU Tharanga"}}, {"18.2": {"batsman": "KC Sangakkara", "bowler": "Harbhajan Singh", "runs": {"batsman": 0, "total": 0, "extras": 0}, "non_striker": "WU Tharanga"}}, {"18.3": {"batsman": "KC Sangakkara", "bowler": "Harbhajan Singh", "runs": {"batsman": 0, "total": 0, "extras": 0}, "non_striker": "WU Tharanga"}}, {"18.4": {"batsman": "KC Sangakkara", "bowler": "Harbhajan Singh", "runs": {"batsman": 0, "total": 0, "extras": 0}, "non_striker": "WU Tharanga"}}, {"18.5": {"batsman": "KC Sangakkara", "bowler": "Harbhajan Singh", "runs": {"batsman": 0, "total": 0, "extras": 0}, "non_striker": "WU Tharanga"}}, {"18.6": {"batsman": "KC Sangakkara", "bowler": "Harbhajan Singh", "runs": {"batsman": 1, "total": 1, "extras": 0}, "non_striker": "WU Tharanga"}}, {"19.1": {"batsman": "KC Sangakkara", "bowler": "I Sharma", "runs": {"batsman": 1, "total": 1, "extras": 0}, "non_striker": "WU Tharanga"}}, {"19.2": {"batsman": "WU Tharanga", "bowler": "I Sharma", "runs": {"batsman": 1, "total": 1, "extras": 0}, "non_striker": "KC Sangakkara"}}, {"19.3": {"batsman": "KC Sangakkara", "bowler": "I Sharma", "runs": {"batsman": 1, "total": 1, "extras": 0}, "non_striker": "WU Tharanga"}}, {"19.4": {"batsman": "WU Tharanga", "bowler": "I Sharma", "runs": {"batsman": 4, "total": 4, "extras": 0}, "non_striker": "KC Sangakkara"}}, {"19.5": {"batsman": "WU Tharanga", "bowler": "I Sharma", "runs": {"batsman": 4, "total": 4, "extras": 0}, "non_striker": "KC Sangakkara"}}, {"19.6": {"batsman": "WU Tharanga", "bowler": "I Sharma", "runs": {"batsman": 1, "total": 1, "extras": 0}, "non_striker": "KC Sangakkara"}}, {"20.1": {"batsman": "WU Tharanga", "bowler": "Harbhajan Singh", "runs": {"batsman": 0, "total": 0, "extras": 0}, "non_striker": "KC Sangakkara"}}, {"20.2": {"batsman": "WU Tharanga", "bowler": "Harbhajan Singh", "runs": {"batsman": 1, "total": 1, "extras": 0}, "non_striker": "KC Sangakkara"}}, {"20.3": {"batsman": "KC Sangakkara", "bowler": "Harbhajan Singh", "runs": {"batsman": 1, "total": 1, "extras": 0}, "non_striker": "WU Tharanga"}}, {"20.4": {"batsman": "WU Tharanga", "bowler": "Harbhajan Singh", "runs": {"batsman": 0, "total": 0, "extras": 0}, "non_striker": "KC Sangakkara"}}, {"20.5": {"batsman": "WU Tharanga", "bowler": "Harbhajan Singh", "runs": {"batsman": 0, "total": 0, "extras": 0}, "non_striker": "KC Sangakkara"}}, {"20.6": {"batsman": "WU Tharanga", "bowler": "Harbhajan Singh", "runs": {"batsman": 1, "total": 1, "extras": 0}, "non_striker": "KC Sangakkara"}}, {"21.1": {"batsman": "WU Tharanga", "bowler": "RA Jadeja", "runs": {"batsman": 0, "total": 0, "extras": 0}, "non_striker": "KC Sangakkara"}}, {"21.2": {"batsman": "WU Tharanga", "bowler": "RA Jadeja", "runs": {"batsman": 0, "total": 0, "extras": 0}, "non_striker": "KC Sangakkara"}}, {"21.3": {"batsman": "WU Tharanga", "bowler": "RA Jadeja", "runs": {"batsman": 0, "total": 0, "extras": 0}, "non_striker": "KC Sangakkara"}}, {"21.4": {"batsman": "WU Tharanga", "bowler": "RA Jadeja", "runs": {"batsman": 0, "total": 0, "extras": 0}, "non_striker": "KC Sangakkara"}}, {"21.5": {"batsman": "WU Tharanga", "bowler": "RA Jadeja", "runs": {"batsman": 0, "total": 0, "extras": 0}, "non_striker": "KC Sangakkara"}}, {"21.6": {"batsman": "WU Tharanga", "bowler": "RA Jadeja", "runs": {"batsman": 0, "total": 0, "extras": 0}, "non_striker": "KC Sangakkara"}}, {"22.1": {"batsman": "KC Sangakkara", "bowler": "Harbhajan Singh", "runs": {"batsman": 0, "total": 0, "extras": 0}, "non_striker": "WU Tharanga"}}, {"22.2": {"batsman": "KC Sangakkara", "bowler": "Harbhajan Singh", "runs": {"batsman": 1, "total": 1, "extras": 0}, "non_striker": "WU Tharanga"}}, {"22.3": {"batsman": "WU Tharanga", "bowler": "Harbhajan Singh", "runs": {"batsman": 1, "total": 1, "extras": 0}, "non_striker": "KC Sangakkara"}}, {"22.4": {"batsman": "KC Sangakkara", "bowler": "Harbhajan Singh", "runs": {"batsman": 0, "total": 0, "extras": 0}, "non_striker": "WU Tharanga"}}, {"22.5": {"batsman": "KC Sangakkara", "bowler": "Harbhajan Singh", "runs": {"batsman": 2, "total": 2, "extras": 0}, "non_striker": "WU Tharanga"}}, {"22.6": {"batsman": "KC Sangakkara", "bowler": "Harbhajan Singh", "runs": {"batsman": 0, "total": 0, "extras": 0}, "non_striker": "WU Tharanga"}}, {"23.1": {"batsman": "WU Tharanga", "bowler": "RA Jadeja", "runs": {"batsman": 0, "total": 0, "extras": 0}, "non_striker": "KC Sangakkara"}}, {"23.2": {"batsman": "WU Tharanga", "bowler": "RA Jadeja", "runs": {"batsman": 2, "total": 2, "extras": 0}, "non_striker": "KC Sangakkara"}}, {"23.3": {"batsman": "WU Tharanga", "bowler": "RA Jadeja", "runs": {"batsman": 0, "total": 0, "extras": 0}, "non_striker": "KC Sangakkara"}}, {"23.4": {"batsman": "WU Tharanga", "bowler": "RA Jadeja", "runs": {"batsman": 1, "total": 1, "extras": 0}, "non_striker": "KC Sangakkara"}}, {"23.5": {"batsman": "KC Sangakkara", "bowler": "RA Jadeja", "runs": {"batsman": 1, "total": 1, "extras": 0}, "non_striker": "WU Tharanga"}}, {"23.6": {"batsman": "WU Tharanga", "bowler": "RA Jadeja", "runs": {"batsman": 0, "total": 0, "extras": 0}, "non_striker": "KC Sangakkara"}}, {"24.1": {"batsman": "KC Sangakkara", "bowler": "Harbhajan Singh", "runs": {"batsman": 0, "total": 0, "extras": 0}, "non_striker": "WU Tharanga"}}, {"24.2": {"batsman": "KC Sangakkara", "bowler": "Harbhajan Singh", "runs": {"batsman": 1, "total": 1, "extras": 0}, "non_striker": "WU Tharanga"}}, {"24.3": {"batsman": "WU Tharanga", "bowler": "Harbhajan Singh", "runs": {"batsman": 0, "total": 0, "extras": 0}, "non_striker": "KC Sangakkara"}}, {"24.4": {"batsman": "WU Tharanga", "bowler": "Harbhajan Singh", "runs": {"batsman": 1, "total": 1, "extras": 0}, "non_striker": "KC Sangakkara"}}, {"24.5": {"batsman": "KC Sangakkara", "bowler": "Harbhajan Singh", "runs": {"batsman": 0, "total": 0, "extras": 0}, "non_striker": "WU Tharanga"}}, {"24.6": {"batsman": "KC Sangakkara", "bowler": "Harbhajan Singh", "runs": {"batsman": 0, "total": 0, "extras": 0}, "non_striker": "WU Tharanga"}}, {"25.1": {"batsman": "WU Tharanga", "bowler": "RA Jadeja", "runs": {"batsman": 4, "total": 4, "extras": 0}, "non_striker": "KC Sangakkara"}}, {"25.2": {"batsman": "WU Tharanga", "bowler": "RA Jadeja", "runs": {"batsman": 1, "total": 1, "extras": 0}, "non_striker": "KC Sangakkara"}}, {"25.3": {"batsman": "KC Sangakkara", "bowler": "RA Jadeja", "runs": {"batsman": 0, "total": 0, "extras": 0}, "non_striker": "WU Tharanga"}}, {"25.4": {"batsman": "KC Sangakkara", "bowler": "RA Jadeja", "runs": {"batsman": 1, "total": 1, "extras": 0}, "non_striker": "WU Tharanga"}}, {"25.5": {"batsman": "WU Tharanga", "bowler": "RA Jadeja", "runs": {"batsman": 0, "total": 0, "extras": 0}, "non_striker": "KC Sangakkara"}}, {"25.6": {"batsman": "WU Tharanga", "bowler": "RA Jadeja", "runs": {"batsman": 1, "total": 1, "extras": 0}, "non_striker": "KC Sangakkara"}}, {"26.1": {"batsman": "WU Tharanga", "bowler": "Harbhajan Singh", "runs": {"batsman": 1, "total": 1, "extras": 0}, "non_striker": "KC Sangakkara"}}, {"26.2": {"batsman": "KC Sangakkara", "bowler": "Harbhajan Singh", "runs": {"batsman": 1, "total": 1, "extras": 0}, "non_striker": "WU Tharanga"}}, {"26.3": {"batsman": "WU Tharanga", "bowler": "Harbhajan Singh", "runs": {"batsman": 0, "total": 0, "extras": 0}, "non_striker": "KC Sangakkara"}}, {"26.4": {"batsman": "WU Tharanga", "bowler": "Harbhajan Singh", "runs": {"batsman": 1, "total": 1, "extras": 0}, "non_striker": "KC Sangakkara"}}, {"26.5": {"batsman": "KC Sangakkara", "bowler": "Harbhajan Singh", "runs": {"batsman": 0, "total": 0, "extras": 0}, "non_striker": "WU Tharanga"}}, {"26.6": {"batsman": "KC Sangakkara", "bowler": "Harbhajan Singh", "runs": {"batsman": 1, "total": 1, "extras": 0}, "non_striker": "WU Tharanga"}}, {"27.1": {"batsman": "KC Sangakkara", "bowler": "RA Jadeja", "runs": {"batsman": 1, "total": 1, "extras": 0}, "non_striker": "WU Tharanga"}}, {"27.2": {"batsman": "WU Tharanga", "bowler": "RA Jadeja", "runs": {"batsman": 0, "total": 0, "extras": 0}, "non_striker": "KC Sangakkara"}}, {"27.3": {"batsman": "WU Tharanga", "bowler": "RA Jadeja", "runs": {"batsman": 1, "total": 1, "extras": 0}, "non_striker": "KC Sangakkara"}}, {"27.4": {"batsman": "KC Sangakkara", "bowler": "RA Jadeja", "runs": {"batsman": 0, "total": 0, "extras": 0}, "non_striker": "WU Tharanga"}}, {"27.5": {"batsman": "KC Sangakkara", "bowler": "RA Jadeja", "runs": {"batsman": 1, "total": 1, "extras": 0}, "non_striker": "WU Tharanga"}}, {"27.6": {"batsman": "WU Tharanga", "bowler": "RA Jadeja", "runs": {"batsman": 1, "total": 1, "extras": 0}, "non_striker": "KC Sangakkara"}}, {"28.1": {"batsman": "WU Tharanga", "bowler": "V Sehwag", "runs": {"batsman": 0, "total": 0, "extras": 0}, "non_striker": "KC Sangakkara"}}, {"28.2": {"batsman": "WU Tharanga", "bowler": "V Sehwag", "runs": {"batsman": 4, "total": 4, "extras": 0}, "non_striker": "KC Sangakkara"}}, {"28.3": {"batsman": "WU Tharanga", "bowler": "V Sehwag", "runs": {"batsman": 1, "total": 1, "extras": 0}, "non_striker": "KC Sangakkara"}}, {"28.4": {"batsman": "KC Sangakkara", "bowler": "V Sehwag", "runs": {"batsman": 1, "total": 1, "extras": 0}, "non_striker": "WU Tharanga"}}, {"28.5": {"batsman": "WU Tharanga", "bowler": "V Sehwag", "runs": {"batsman": 1, "total": 1, "extras": 0}, "non_striker": "KC Sangakkara"}}, {"28.6": {"batsman": "KC Sangakkara", "bowler": "V Sehwag", "runs": {"batsman": 1, "total": 1, "extras": 0}, "non_striker": "WU Tharanga"}}, {"29.1": {"batsman": "KC Sangakkara", "bowler": "RA Jadeja", "runs": {"batsman": 0, "total": 0, "extras": 0}, "non_striker": "WU Tharanga"}}, {"29.2": {"batsman": "KC Sangakkara", "bowler": "RA Jadeja", "runs": {"batsman": 1, "total": 1, "extras": 0}, "non_striker": "WU Tharanga"}}, {"29.3": {"batsman": "WU Tharanga", "bowler": "RA Jadeja", "runs": {"batsman": 1, "total": 1, "extras": 0}, "non_striker": "KC Sangakkara"}}, {"29.4": {"batsman": "KC Sangakkara", "bowler": "RA Jadeja", "runs": {"batsman": 2, "total": 2, "extras": 0}, "non_striker": "WU Tharanga"}}, {"29.5": {"batsman": "KC Sangakkara", "bowler": "RA Jadeja", "runs": {"batsman": 4, "total": 4, "extras": 0}, "non_striker": "WU Tharanga"}}, {"29.6": {"batsman": "KC Sangakkara", "bowler": "RA Jadeja", "runs": {"batsman": 1, "total": 1, "extras": 0}, "non_striker": "WU Tharanga"}}, {"30.1": {"batsman": "KC Sangakkara", "bowler": "V Sehwag", "runs": {"batsman": 0, "total": 0, "extras": 0}, "non_striker": "WU Tharanga"}}, {"30.2": {"batsman": "KC Sangakkara", "bowler": "V Sehwag", "runs": {"batsman": 1, "total": 1, "extras": 0}, "non_striker": "WU Tharanga"}}, {"30.3": {"batsman": "WU Tharanga", "bowler": "V Sehwag", "runs": {"batsman": 1, "total": 1, "extras": 0}, "non_striker": "KC Sangakkara"}}, {"30.4": {"batsman": "KC Sangakkara", "bowler": "V Sehwag", "runs": {"batsman": 1, "total": 1, "extras": 0}, "non_striker": "WU Tharanga"}}, {"30.5": {"batsman": "WU Tharanga", "bowler": "V Sehwag", "runs": {"batsman": 0, "total": 0, "extras": 0}, "non_striker": "KC Sangakkara"}}, {"30.6": {"batsman": "WU Tharanga", "bowler": "V Sehwag", "runs": {"batsman": 0, "total": 0, "extras": 0}, "non_striker": "KC Sangakkara"}}, {"31.1": {"batsman": "KC Sangakkara", "bowler": "I Sharma", "runs": {"batsman": 4, "total": 4, "extras": 0}, "non_striker": "WU Tharanga"}}, {"31.2": {"batsman": "KC Sangakkara", "bowler": "I Sharma", "runs": {"batsman": 4, "total": 4, "extras": 0}, "non_striker": "WU Tharanga"}}, {"31.3": {"batsman": "KC Sangakkara", "bowler": "I Sharma", "runs": {"batsman": 1, "total": 1, "extras": 0}, "non_striker": "WU Tharanga"}}, {"31.4": {"batsman": "WU Tharanga", "bowler": "I Sharma", "runs": {"batsman": 1, "total": 1, "extras": 0}, "non_striker": "KC Sangakkara"}}, {"31.5": {"batsman": "KC Sangakkara", "bowler": "I Sharma", "runs": {"batsman": 0, "total": 0, "extras": 0}, "non_striker": "WU Tharanga"}}, {"31.6": {"batsman": "KC Sangakkara", "bowler": "I Sharma", "runs": {"batsman": 1, "total": 1, "extras": 0}, "non_striker": "WU Tharanga"}}, {"32.1": {"batsman": "KC Sangakkara", "bowler": "V Sehwag", "runs": {"batsman": 1, "total": 1, "extras": 0}, "non_striker": "WU Tharanga"}}, {"32.2": {"batsman": "WU Tharanga", "bowler": "V Sehwag", "runs": {"batsman": 0, "total": 0, "extras": 0}, "non_striker": "KC Sangakkara"}}, {"32.3": {"batsman": "WU Tharanga", "bowler": "V Sehwag", "runs": {"batsman": 1, "total": 1, "extras": 0}, "non_striker": "KC Sangakkara"}}, {"32.4": {"batsman": "KC Sangakkara", "bowler": "V Sehwag", "runs": {"batsman": 0, "total": 0, "extras": 0}, "non_striker": "WU Tharanga"}}, {"32.5": {"batsman": "KC Sangakkara", "bowler": "V Sehwag", "runs": {"batsman": 2, "total": 2, "extras": 0}, "non_striker": "WU Tharanga"}}, {"32.6": {"batsman": "KC Sangakkara", "bowler": "V Sehwag", "runs": {"batsman": 0, "total": 0, "extras": 0}, "non_striker": "WU Tharanga"}}, {"33.1": {"batsman": "WU Tharanga", "bowler": "SK Raina", "runs": {"batsman": 1, "total": 1, "extras": 0}, "non_striker": "KC Sangakkara"}}, {"33.2": {"batsman": "KC Sangakkara", "bowler": "SK Raina", "runs": {"batsman": 0, "total": 1, "extras": 1}, "extras": {"wides": 1}, "non_striker": "WU Tharanga"}}, {"33.3": {"batsman": "KC Sangakkara", "bowler": "SK Raina", "runs": {"batsman": 1, "total": 1, "extras": 0}, "non_striker": "WU Tharanga"}}, {"33.4": {"batsman": "WU Tharanga", "bowler": "SK Raina", "runs": {"batsman": 0, "total": 0, "extras": 0}, "non_striker": "KC Sangakkara"}}, {"33.5": {"batsman": "WU Tharanga", "bowler": "SK Raina", "runs": {"batsman": 1, "total": 1, "extras": 0}, "non_striker": "KC Sangakkara"}}, {"33.6": {"batsman": "KC Sangakkara", "bowler": "SK Raina", "runs": {"batsman": 1, "total": 1, "extras": 0}, "non_striker": "WU Tharanga"}}, {"33.7": {"batsman": "WU Tharanga", "bowler": "SK Raina", "runs": {"batsman": 1, "total": 1, "extras": 0}, "non_striker": "KC Sangakkara"}}, {"34.1": {"batsman": "WU Tharanga", "bowler": "Harbhajan Singh", "runs": {"batsman": 1, "total": 1, "extras": 0}, "non_striker": "KC Sangakkara"}}, {"34.2": {"batsman": "KC Sangakkara", "bowler": "Harbhajan Singh", "runs": {"batsman": 1, "total": 1, "extras": 0}, "non_striker": "WU Tharanga"}}, {"34.3": {"batsman": "WU Tharanga", "bowler": "Harbhajan Singh", "runs": {"batsman": 0, "total": 0, "extras": 0}, "non_striker": "KC Sangakkara"}}, {"34.4": {"batsman": "WU Tharanga", "bowler": "Harbhajan Singh", "runs": {"batsman": 1, "total": 1, "extras": 0}, "non_striker": "KC Sangakkara"}}, {"34.5": {"batsman": "KC Sangakkara", "bowler": "Harbhajan Singh", "runs": {"batsman": 1, "total": 1, "extras": 0}, "non_striker": "WU Tharanga"}}, {"34.6": {"batsman": "WU Tharanga", "bowler": "Harbhajan Singh", "runs": {"batsman": 1, "total": 1, "extras": 0}, "non_striker": "KC Sangakkara"}}, {"35.1": {"batsman": "WU Tharanga", "bowler": "SK Raina", "runs": {"batsman": 0, "total": 0, "extras": 0}, "non_striker": "KC Sangakkara"}}, {"35.2": {"batsman": "WU Tharanga", "bowler": "SK Raina", "runs": {"batsman": 0, "total": 0, "extras": 0}, "non_striker": "KC Sangakkara"}}, {"35.3": {"batsman": "WU Tharanga", "bowler": "SK Raina", "runs": {"batsman": 0, "total": 0, "extras": 0}, "non_striker": "KC Sangakkara"}}, {"35.4": {"batsman": "WU Tharanga", "bowler": "SK Raina", "runs": {"batsman": 1, "total": 1, "extras": 0}, "non_striker": "KC Sangakkara"}}, {"35.5": {"batsman": "KC Sangakkara", "bowler": "SK Raina", "runs": {"batsman": 1, "total": 1, "extras": 0}, "non_striker": "WU Tharanga"}}, {"35.6": {"batsman": "WU Tharanga", "bowler": "SK Raina", "runs": {"batsman": 1, "total": 1, "extras": 0}, "non_striker": "KC Sangakkara"}}, {"36.1": {"batsman": "WU Tharanga", "bowler": "Harbhajan Singh", "runs": {"batsman": 1, "total": 1, "extras": 0}, "non_striker": "KC Sangakkara"}}, {"36.2": {"batsman": "KC Sangakkara", "bowler": "Harbhajan Singh", "runs": {"batsman": 4, "total": 4, "extras": 0}, "non_striker": "WU Tharanga"}}, {"36.3": {"batsman": "KC Sangakkara", "bowler": "Harbhajan Singh", "runs": {"batsman": 0, "total": 0, "extras": 0}, "non_striker": "WU Tharanga", "wicket": {"fielders": ["KD Karthik"], "kind": "stumped", "player_out": "KC Sangakkara"}}}, {"36.4": {"batsman": "DPMD Jayawardene", "bowler": "Harbhajan Singh", "runs": {"batsman": 4, "total": 4, "extras": 0}, "non_striker": "WU Tharanga"}}, {"36.5": {"batsman": "DPMD Jayawardene", "bowler": "Harbhajan Singh", "runs": {"batsman": 0, "total": 0, "extras": 0}, "non_striker": "WU Tharanga"}}, {"36.6": {"batsman": "DPMD Jayawardene", "bowler": "Harbhajan Singh", "runs": {"batsman": 1, "total": 1, "extras": 0}, "non_striker": "WU Tharanga"}}, {"37.1": {"batsman": "DPMD Jayawardene", "bowler": "RA Jadeja", "runs": {"batsman": 0, "total": 0, "extras": 0}, "non_striker": "WU Tharanga"}}, {"37.2": {"batsman": "DPMD Jayawardene", "bowler": "RA Jadeja", "runs": {"batsman": 0, "total": 0, "extras": 0}, "non_striker": "WU Tharanga"}}, {"37.3": {"batsman": "DPMD Jayawardene", "bowler": "RA Jadeja", "runs": {"batsman": 1, "total": 1, "extras": 0}, "non_striker": "WU Tharanga"}}, {"37.4": {"batsman": "WU Tharanga", "bowler": "RA Jadeja", "runs": {"batsman": 0, "total": 0, "extras": 0}, "non_striker": "DPMD Jayawardene"}}, {"37.5": {"batsman": "WU Tharanga", "bowler": "RA Jadeja", "runs": {"batsman": 0, "total": 1, "extras": 1}, "extras": {"legbyes": 1}, "non_striker": "DPMD Jayawardene"}}, {"37.6": {"batsman": "DPMD Jayawardene", "bowler": "RA Jadeja", "runs": {"batsman": 0, "total": 0, "extras": 0}, "non_striker": "WU Tharanga"}}, {"38.1": {"batsman": "WU Tharanga", "bowler": "Harbhajan Singh", "runs": {"batsman": 1, "total": 1, "extras": 0}, "non_striker": "DPMD Jayawardene"}}, {"38.2": {"batsman": "DPMD Jayawardene", "bowler": "Harbhajan Singh", "runs": {"batsman": 0, "total": 0, "extras": 0}, "non_striker": "WU Tharanga"}}, {"38.3": {"batsman": "DPMD Jayawardene", "bowler": "Harbhajan Singh", "runs": {"batsman": 1, "total": 1, "extras": 0}, "non_striker": "WU Tharanga"}}, {"38.4": {"batsman": "WU Tharanga", "bowler": "Harbhajan Singh", "runs": {"batsman": 0, "total": 0, "extras": 0}, "non_striker": "DPMD Jayawardene"}}, {"38.5": {"batsman": "WU Tharanga", "bowler": "Harbhajan Singh", "runs": {"batsman": 2, "total": 2, "extras": 0}, "non_striker": "DPMD Jayawardene"}}, {"38.6": {"batsman": "WU Tharanga", "bowler": "Harbhajan Singh", "runs": {"batsman": 0, "total": 5, "extras": 5}, "extras": {"wides": 5}, "non_striker": "DPMD Jayawardene"}}, {"38.7": {"batsman": "WU Tharanga", "bowler": "Harbhajan Singh", "runs": {"batsman": 0, "total": 0, "extras": 0}, "non_striker": "DPMD Jayawardene"}}, {"39.1": {"batsman": "DPMD Jayawardene", "bowler": "RA Jadeja", "runs": {"batsman": 1, "total": 1, "extras": 0}, "non_striker": "WU Tharanga"}}, {"39.2": {"batsman": "WU Tharanga", "bowler": "RA Jadeja", "runs": {"batsman": 1, "total": 1, "extras": 0}, "non_striker": "DPMD Jayawardene"}}, {"39.3": {"batsman": "DPMD Jayawardene", "bowler": "RA Jadeja", "runs": {"batsman": 0, "total": 0, "extras": 0}, "non_striker": "WU Tharanga"}}, {"39.4": {"batsman": "DPMD Jayawardene", "bowler": "RA Jadeja", "runs": {"batsman": 0, "total": 0, "extras": 0}, "non_striker": "WU Tharanga"}}, {"39.5": {"batsman": "DPMD Jayawardene", "bowler": "RA Jadeja", "runs": {"batsman": 1, "total": 1, "extras": 0}, "non_striker": "WU Tharanga"}}, {"39.6": {"batsman": "WU Tharanga", "bowler": "RA Jadeja", "runs": {"batsman": 0, "total": 0, "extras": 0}, "non_striker": "DPMD Jayawardene"}}, {"40.1": {"batsman": "DPMD Jayawardene", "bowler": "Harbhajan Singh", "runs": {"batsman": 0, "total": 0, "extras": 0}, "non_striker": "WU Tharanga"}}, {"40.2": {"batsman": "DPMD Jayawardene", "bowler": "Harbhajan Singh", "runs": {"batsman": 0, "total": 0, "extras": 0}, "non_striker": "WU Tharanga"}}, {"40.3": {"batsman": "DPMD Jayawardene", "bowler": "Harbhajan Singh", "runs": {"batsman": 4, "total": 4, "extras": 0}, "non_striker": "WU Tharanga"}}, {"40.4": {"batsman": "DPMD Jayawardene", "bowler": "Harbhajan Singh", "runs": {"batsman": 4, "total": 4, "extras": 0}, "non_striker": "WU Tharanga"}}, {"40.5": {"batsman": "DPMD Jayawardene", "bowler": "Harbhajan Singh", "runs": {"batsman": 1, "total": 1, "extras": 0}, "non_striker": "WU Tharanga"}}, {"40.6": {"batsman": "WU Tharanga", "bowler": "Harbhajan Singh", "runs": {"batsman": 0, "total": 0, "extras": 0}, "non_striker": "DPMD Jayawardene"}}, {"41.1": {"batsman": "DPMD Jayawardene", "bowler": "RA Jadeja", "runs": {"batsman": 1, "total": 1, "extras": 0}, "non_striker": "WU Tharanga"}}, {"41.2": {"batsman": "WU Tharanga", "bowler": "RA Jadeja", "runs": {"batsman": 0, "total": 0, "extras": 0}, "non_striker": "DPMD Jayawardene"}}, {"41.3": {"batsman": "WU Tharanga", "bowler": "RA Jadeja", "runs": {"batsman": 6, "total": 6, "extras": 0}, "non_striker": "DPMD Jayawardene"}}, {"41.4": {"batsman": "WU Tharanga", "bowler": "RA Jadeja", "runs": {"batsman": 0, "total": 0, "extras": 0}, "non_striker": "DPMD Jayawardene"}}, {"41.5": {"batsman": "WU Tharanga", "bowler": "RA Jadeja", "runs": {"batsman": 0, "total": 0, "extras": 0}, "non_striker": "DPMD Jayawardene"}}, {"41.6": {"batsman": "WU Tharanga", "bowler": "RA Jadeja", "runs": {"batsman": 1, "total": 1, "extras": 0}, "non_striker": "DPMD Jayawardene"}}, {"42.1": {"batsman": "WU Tharanga", "bowler": "Z Khan", "runs": {"batsman": 0, "total": 0, "extras": 0}, "non_striker": "DPMD Jayawardene", "wicket": {"kind": "bowled", "player_out": "WU Tharanga"}}}, {"42.2": {"batsman": "NLTC Perera", "bowler": "Z Khan", "runs": {"batsman": 0, "total": 0, "extras": 0}, "non_striker": "DPMD Jayawardene"}}, {"42.3": {"batsman": "NLTC Perera", "bowler": "Z Khan", "runs": {"batsman": 2, "total": 2, "extras": 0}, "non_striker": "DPMD Jayawardene"}}, {"42.4": {"batsman": "NLTC Perera", "bowler": "Z Khan", "runs": {"batsman": 4, "total": 4, "extras": 0}, "non_striker": "DPMD Jayawardene"}}, {"42.5": {"batsman": "NLTC Perera", "bowler": "Z Khan", "runs": {"batsman": 1, "total": 1, "extras": 0}, "non_striker": "DPMD Jayawardene"}}, {"42.6": {"batsman": "DPMD Jayawardene", "bowler": "Z Khan", "runs": {"batsman": 0, "total": 0, "extras": 0}, "non_striker": "NLTC Perera"}}, {"43.1": {"batsman": "NLTC Perera", "bowler": "RA Jadeja", "runs": {"batsman": 4, "total": 4, "extras": 0}, "non_striker": "DPMD Jayawardene"}}, {"43.2": {"batsman": "NLTC Perera", "bowler": "RA Jadeja", "runs": {"batsman": 1, "total": 1, "extras": 0}, "non_striker": "DPMD Jayawardene"}}, {"43.3": {"batsman": "DPMD Jayawardene", "bowler": "RA Jadeja", "runs": {"batsman": 1, "total": 1, "extras": 0}, "non_striker": "NLTC Perera"}}, {"43.4": {"batsman": "NLTC Perera", "bowler": "RA Jadeja", "runs": {"batsman": 4, "total": 4, "extras": 0}, "non_striker": "DPMD Jayawardene"}}, {"43.5": {"batsman": "NLTC Perera", "bowler": "RA Jadeja", "runs": {"batsman": 1, "total": 1, "extras": 0}, "non_striker": "DPMD Jayawardene"}}, {"43.6": {"batsman": "DPMD Jayawardene", "bowler": "RA Jadeja", "runs": {"batsman": 4, "total": 4, "extras": 0}, "non_striker": "NLTC Perera"}}, {"44.1": {"batsman": "NLTC Perera", "bowler": "Z Khan", "runs": {"batsman": 0, "total": 0, "extras": 0}, "non_striker": "DPMD Jayawardene"}}, {"44.2": {"batsman": "NLTC Perera", "bowler": "Z Khan", "runs": {"batsman": 6, "total": 6, "extras": 0}, "non_striker": "DPMD Jayawardene"}}, {"44.3": {"batsman": "NLTC Perera", "bowler": "Z Khan", "runs": {"batsman": 3, "total": 3, "extras": 0}, "non_striker": "DPMD Jayawardene"}}, {"44.4": {"batsman": "DPMD Jayawardene", "bowler": "Z Khan", "runs": {"batsman": 1, "total": 1, "extras": 0}, "non_striker": "NLTC Perera"}}, {"44.5": {"batsman": "NLTC Perera", "bowler": "Z Khan", "runs": {"batsman": 4, "total": 4, "extras": 0}, "non_striker": "DPMD Jayawardene"}}, {"44.6": {"batsman": "NLTC Perera", "bowler": "Z Khan", "runs": {"batsman": 1, "total": 1, "extras": 0}, "non_striker": "DPMD Jayawardene"}}, {"45.1": {"batsman": "NLTC Perera", "bowler": "A Nehra", "runs": {"batsman": 0, "total": 0, "extras": 0}, "non_striker": "DPMD Jayawardene", "wicket": {"fielders": ["RA Jadeja"], "kind": "caught", "player_out": "NLTC Perera"}}}, {"45.2": {"batsman": "DPMD Jayawardene", "bowler": "A Nehra", "runs": {"batsman": 1, "total": 1, "extras": 0}, "non_striker": "SHT Kandamby"}}, {"45.3": {"batsman": "SHT Kandamby", "bowler": "A Nehra", "runs": {"batsman": 0, "total": 0, "extras": 0}, "non_striker": "DPMD Jayawardene"}}, {"45.4": {"batsman": "SHT Kandamby", "bowler": "A Nehra", "runs": {"batsman": 2, "total": 2, "extras": 0}, "non_striker": "DPMD Jayawardene"}}, {"45.5": {"batsman": "SHT Kandamby", "bowler": "A Nehra", "runs": {"batsman": 0, "total": 0, "extras": 0}, "non_striker": "DPMD Jayawardene"}}, {"45.6": {"batsman": "SHT Kandamby", "bowler": "A Nehra", "runs": {"batsman": 4, "total": 4, "extras": 0}, "non_striker": "DPMD Jayawardene"}}, {"46.1": {"batsman": "DPMD Jayawardene", "bowler": "Z Khan", "runs": {"batsman": 4, "total": 4, "extras": 0}, "non_striker": "SHT Kandamby"}}, {"46.2": {"batsman": "DPMD Jayawardene", "bowler": "Z Khan", "runs": {"batsman": 1, "total": 1, "extras": 0}, "non_striker": "SHT Kandamby"}}, {"46.3": {"batsman": "SHT Kandamby", "bowler": "Z Khan", "runs": {"batsman": 1, "total": 1, "extras": 0}, "non_striker": "DPMD Jayawardene"}}, {"46.4": {"batsman": "DPMD Jayawardene", "bowler": "Z Khan", "runs": {"batsman": 1, "total": 1, "extras": 0}, "non_striker": "SHT Kandamby"}}, {"46.5": {"batsman": "SHT Kandamby", "bowler": "Z Khan", "runs": {"batsman": 1, "total": 1, "extras": 0}, "non_striker": "DPMD Jayawardene"}}, {"46.6": {"batsman": "DPMD Jayawardene", "bowler": "Z Khan", "runs": {"batsman": 1, "total": 1, "extras": 0}, "non_striker": "SHT Kandamby"}}, {"47.1": {"batsman": "DPMD Jayawardene", "bowler": "A Nehra", "runs": {"batsman": 0, "total": 0, "extras": 0}, "non_striker": "SHT Kandamby"}}, {"47.2": {"batsman": "DPMD Jayawardene", "bowler": "A Nehra", "runs": {"batsman": 0, "total": 0, "extras": 0}, "non_striker": "SHT Kandamby", "wicket": {"fielders": ["A Nehra"], "kind": "run out", "player_out": "DPMD Jayawardene"}}}, {"47.3": {"batsman": "SHT Kandamby", "bowler": "A Nehra", "runs": {"batsman": 4, "total": 4, "extras": 0}, "non_striker": "TT Samaraweera"}}, {"47.4": {"batsman": "SHT Kandamby", "bowler": "A Nehra", "runs": {"batsman": 0, "total": 0, "extras": 0}, "non_striker": "TT Samaraweera"}}, {"47.5": {"batsman": "SHT Kandamby", "bowler": "A Nehra", "runs": {"batsman": 0, "total": 0, "extras": 0}, "non_striker": "TT Samaraweera"}}, {"47.6": {"batsman": "SHT Kandamby", "bowler": "A Nehra", "runs": {"batsman": 1, "total": 1, "extras": 0}, "non_striker": "TT Samaraweera"}}, {"48.1": {"batsman": "SHT Kandamby", "bowler": "I Sharma", "runs": {"batsman": 4, "total": 4, "extras": 0}, "non_striker": "TT Samaraweera"}}, {"48.2": {"batsman": "SHT Kandamby", "bowler": "I Sharma", "runs": {"batsman": 1, "total": 1, "extras": 0}, "non_striker": "TT Samaraweera"}}, {"48.3": {"batsman": "TT Samaraweera", "bowler": "I Sharma", "runs": {"batsman": 2, "total": 2, "extras": 0}, "non_striker": "SHT Kandamby"}}, {"48.4": {"batsman": "TT Samaraweera", "bowler": "I Sharma", "runs": {"batsman": 1, "total": 1, "extras": 0}, "non_striker": "SHT Kandamby"}}, {"48.5": {"batsman": "SHT Kandamby", "bowler": "I Sharma", "runs": {"batsman": 0, "total": 0, "extras": 0}, "non_striker": "TT Samaraweera"}}, {"48.6": {"batsman": "SHT Kandamby", "bowler": "I Sharma", "runs": {"batsman": 4, "total": 4, "extras": 0}, "non_striker": "TT Samaraweera"}}, {"49.1": {"batsman": "TT Samaraweera", "bowler": "A Nehra", "runs": {"batsman": 2, "total": 2, "extras": 0}, "non_striker": "SHT Kandamby"}}, {"49.2": {"batsman": "TT Samaraweera", "bowler": "A Nehra", "runs": {"batsman": 1, "total": 1, "extras": 0}, "non_striker": "SHT Kandamby"}}, {"49.3": {"batsman": "SHT Kandamby", "bowler": "A Nehra", "runs": {"batsman": 1, "total": 1, "extras": 0}, "non_striker": "TT Samaraweera"}}, {"49.4": {"batsman": "TT Samaraweera", "bowler": "A Nehra", "runs": {"batsman": 4, "total": 4, "extras": 0}, "non_striker": "SHT Kandamby"}}, {"49.5": {"batsman": "TT Samaraweera", "bowler": "A Nehra", "runs": {"batsman": 2, "total": 2, "extras": 0}, "non_striker": "SHT Kandamby"}}, {"49.6": {"batsman": "TT Samaraweera", "bowler": "A Nehra", "runs": {"batsman": 1, "total": 1, "extras": 0}, "non_striker": "SHT Kandamby"}}], "team": "Sri Lanka"}}, {"2nd innings": {"deliveries": [{"0.1": {"batsman": "V Sehwag", "bowler": "NLTC Perera", "runs": {"batsman": 4, "total": 4, "extras": 0}, "non_striker": "SR Tendulkar"}}, {"0.2": {"batsman": "V Sehwag", "bowler": "NLTC Perera", "runs": {"batsman": 0, "total": 0, "extras": 0}, "non_striker": "SR Tendulkar"}}, {"0.3": {"batsman": "V Sehwag", "bowler": "NLTC Perera", "runs": {"batsman": 1, "total": 1, "extras": 0}, "non_striker": "SR Tendulkar"}}, {"0.4": {"batsman": "SR Tendulkar", "bowler": "NLTC Perera", "runs": {"batsman": 0, "total": 2, "extras": 2}, "extras": {"wides": 2}, "non_striker": "V Sehwag"}}, {"0.5": {"batsman": "V Sehwag", "bowler": "NLTC Perera", "runs": {"batsman": 0, "total": 0, "extras": 0}, "non_striker": "SR Tendulkar"}}, {"0.6": {"batsman": "V Sehwag", "bowler": "NLTC Perera", "runs": {"batsman": 4, "total": 4, "extras": 0}, "non_striker": "SR Tendulkar"}}, {"0.7": {"batsman": "V Sehwag", "bowler": "NLTC Perera", "runs": {"batsman": 1, "total": 1, "extras": 0}, "non_striker": "SR Tendulkar"}}, {"1.1": {"batsman": "V Sehwag", "bowler": "RAS Lakmal", "runs": {"batsman": 0, "total": 0, "extras": 0}, "non_striker": "SR Tendulkar"}}, {"1.2": {"batsman": "V Sehwag", "bowler": "RAS Lakmal", "runs": {"batsman": 0, "total": 0, "extras": 0}, "non_striker": "SR Tendulkar"}}, {"1.3": {"batsman": "V Sehwag", "bowler": "RAS Lakmal", "runs": {"batsman": 0, "total": 1, "extras": 1}, "extras": {"wides": 1}, "non_striker": "SR Tendulkar"}}, {"1.4": {"batsman": "V Sehwag", "bowler": "RAS Lakmal", "runs": {"batsman": 0, "total": 0, "extras": 0}, "non_striker": "SR Tendulkar"}}, {"1.5": {"batsman": "V Sehwag", "bowler": "RAS Lakmal", "runs": {"batsman": 0, "total": 0, "extras": 0}, "non_striker": "SR Tendulkar", "wicket": {"fielders": ["TM Dilshan"], "kind": "caught", "player_out": "V Sehwag"}}}, {"1.6": {"batsman": "G Gambhir", "bowler": "RAS Lakmal", "runs": {"batsman": 0, "total": 1, "extras": 1}, "extras": {"noballs": 1}, "non_striker": "SR Tendulkar"}}, {"1.7": {"batsman": "G Gambhir", "bowler": "RAS Lakmal", "runs": {"batsman": 0, "total": 0, "extras": 0}, "non_striker": "SR Tendulkar"}}, {"1.8": {"batsman": "G Gambhir", "bowler": "RAS Lakmal", "runs": {"batsman": 0, "total": 0, "extras": 0}, "non_striker": "SR Tendulkar"}}, {"2.1": {"batsman": "SR Tendulkar", "bowler": "NLTC Perera", "runs": {"batsman": 4, "total": 4, "extras": 0}, "non_striker": "G Gambhir"}}, {"2.2": {"batsman": "SR Tendulkar", "bowler": "NLTC Perera", "runs": {"batsman": 0, "total": 0, "extras": 0}, "non_striker": "G Gambhir"}}, {"2.3": {"batsman": "SR Tendulkar", "bowler": "NLTC Perera", "runs": {"batsman": 0, "total": 0, "extras": 0}, "non_striker": "G Gambhir"}}, {"2.4": {"batsman": "SR Tendulkar", "bowler": "NLTC Perera", "runs": {"batsman": 0, "total": 1, "extras": 1}, "extras": {"legbyes": 1}, "non_striker": "G Gambhir"}}, {"2.5": {"batsman": "G Gambhir", "bowler": "NLTC Perera", "runs": {"batsman": 0, "total": 0, "extras": 0}, "non_striker": "SR Tendulkar"}}, {"2.6": {"batsman": "G Gambhir", "bowler": "NLTC Perera", "runs": {"batsman": 0, "total": 0, "extras": 0}, "non_striker": "SR Tendulkar"}}, {"3.1": {"batsman": "SR Tendulkar", "bowler": "RAS Lakmal", "runs": {"batsman": 0, "total": 0, "extras": 0}, "non_striker": "G Gambhir"}}, {"3.2": {"batsman": "SR Tendulkar", "bowler": "RAS Lakmal", "runs": {"batsman": 0, "total": 0, "extras": 0}, "non_striker": "G Gambhir"}}, {"3.3": {"batsman": "SR Tendulkar", "bowler": "RAS Lakmal", "runs": {"batsman": 4, "total": 4, "extras": 0}, "non_striker": "G Gambhir"}}, {"3.4": {"batsman": "SR Tendulkar", "bowler": "RAS Lakmal", "runs": {"batsman": 0, "total": 0, "extras": 0}, "non_striker": "G Gambhir", "wicket": {"fielders": ["S Randiv"], "kind": "caught", "player_out": "SR Tendulkar"}}}, {"3.5": {"batsman": "V Kohli", "bowler": "RAS Lakmal", "runs": {"batsman": 0, "total": 5, "extras": 5}, "extras": {"wides": 5}, "non_striker": "G Gambhir"}}, {"3.6": {"batsman": "V Kohli", "bowler": "RAS Lakmal", "runs": {"batsman": 0, "total": 0, "extras": 0}, "non_striker": "G Gambhir"}}, {"3.7": {"batsman": "V Kohli", "bowler": "RAS Lakmal", "runs": {"batsman": 0, "total": 0, "extras": 0}, "non_striker": "G Gambhir"}}, {"4.1": {"batsman": "G Gambhir", "bowler": "NLTC Perera", "runs": {"batsman": 0, "total": 0, "extras": 0}, "non_striker": "V Kohli"}}, {"4.2": {"batsman": "G Gambhir", "bowler": "NLTC Perera", "runs": {"batsman": 4, "total": 4, "extras": 0}, "non_striker": "V Kohli"}}, {"4.3": {"batsman": "G Gambhir", "bowler": "NLTC Perera", "runs": {"batsman": 0, "total": 0, "extras": 0}, "non_striker": "V Kohli"}}, {"4.4": {"batsman": "G Gambhir", "bowler": "NLTC Perera", "runs": {"batsman": 0, "total": 4, "extras": 4}, "extras": {"legbyes": 4}, "non_striker": "V Kohli"}}, {"4.5": {"batsman": "G Gambhir", "bowler": "NLTC Perera", "runs": {"batsman": 1, "total": 1, "extras": 0}, "non_striker": "V Kohli"}}, {"4.6": {"batsman": "V Kohli", "bowler": "NLTC Perera", "runs": {"batsman": 0, "total": 0, "extras": 0}, "non_striker": "G Gambhir"}}, {"5.1": {"batsman": "G Gambhir", "bowler": "RAS Lakmal", "runs": {"batsman": 0, "total": 0, "extras": 0}, "non_striker": "V Kohli"}}, {"5.2": {"batsman": "G Gambhir", "bowler": "RAS Lakmal", "runs": {"batsman": 4, "total": 4, "extras": 0}, "non_striker": "V Kohli"}}, {"5.3": {"batsman": "G Gambhir", "bowler": "RAS Lakmal", "runs": {"batsman": 1, "total": 1, "extras": 0}, "non_striker": "V Kohli"}}, {"5.4": {"batsman": "V Kohli", "bowler": "RAS Lakmal", "runs": {"batsman": 4, "total": 4, "extras": 0}, "non_striker": "G Gambhir"}}, {"5.5": {"batsman": "V Kohli", "bowler": "RAS Lakmal", "runs": {"batsman": 0, "total": 0, "extras": 0}, "non_striker": "G Gambhir"}}, {"5.6": {"batsman": "V Kohli", "bowler": "RAS Lakmal", "runs": {"batsman": 0, "total": 0, "extras": 0}, "non_striker": "G Gambhir"}}, {"6.1": {"batsman": "G Gambhir", "bowler": "NLTC Perera", "runs": {"batsman": 1, "total": 1, "extras": 0}, "non_striker": "V Kohli"}}, {"6.2": {"batsman": "V Kohli", "bowler": "NLTC Perera", "runs": {"batsman": 4, "total": 4, "extras": 0}, "non_striker": "G Gambhir"}}, {"6.3": {"batsman": "V Kohli", "bowler": "NLTC Perera", "runs": {"batsman": 0, "total": 0, "extras": 0}, "non_striker": "G Gambhir"}}, {"6.4": {"batsman": "V Kohli", "bowler": "NLTC Perera", "runs": {"batsman": 0, "total": 1, "extras": 1}, "extras": {"wides": 1}, "non_striker": "G Gambhir"}}, {"6.5": {"batsman": "V Kohli", "bowler": "NLTC Perera", "runs": {"batsman": 0, "total": 0, "extras": 0}, "non_striker": "G Gambhir"}}, {"6.6": {"batsman": "V Kohli", "bowler": "NLTC Perera", "runs": {"batsman": 1, "total": 1, "extras": 0}, "non_striker": "G Gambhir"}}, {"6.7": {"batsman": "G Gambhir", "bowler": "NLTC Perera", "runs": {"batsman": 0, "total": 0, "extras": 0}, "non_striker": "V Kohli"}}, {"7.1": {"batsman": "V Kohli", "bowler": "RAS Lakmal", "runs": {"batsman": 0, "total": 0, "extras": 0}, "non_striker": "G Gambhir"}}, {"7.2": {"batsman": "V Kohli", "bowler": "RAS Lakmal", "runs": {"batsman": 0, "total": 0, "extras": 0}, "non_striker": "G Gambhir"}}, {"7.3": {"batsman": "V Kohli", "bowler": "RAS Lakmal", "runs": {"batsman": 0, "total": 0, "extras": 0}, "non_striker": "G Gambhir"}}, {"7.4": {"batsman": "V Kohli", "bowler": "RAS Lakmal", "runs": {"batsman": 0, "total": 0, "extras": 0}, "non_striker": "G Gambhir"}}, {"7.5": {"batsman": "V Kohli", "bowler": "RAS Lakmal", "runs": {"batsman": 0, "total": 0, "extras": 0}, "non_striker": "G Gambhir"}}, {"7.6": {"batsman": "V Kohli", "bowler": "RAS Lakmal", "runs": {"batsman": 1, "total": 1, "extras": 0}, "non_striker": "G Gambhir"}}, {"8.1": {"batsman": "V Kohli", "bowler": "SL Malinga", "runs": {"batsman": 0, "total": 0, "extras": 0}, "non_striker": "G Gambhir"}}, {"8.2": {"batsman": "V Kohli", "bowler": "SL Malinga", "runs": {"batsman": 0, "total": 0, "extras": 0}, "non_striker": "G Gambhir"}}, {"8.3": {"batsman": "V Kohli", "bowler": "SL Malinga", "runs": {"batsman": 4, "total": 4, "extras": 0}, "non_striker": "G Gambhir"}}, {"8.4": {"batsman": "V Kohli", "bowler": "SL Malinga", "runs": {"batsman": 4, "total": 4, "extras": 0}, "non_striker": "G Gambhir"}}, {"8.5": {"batsman": "V Kohli", "bowler": "SL Malinga", "runs": {"batsman": 4, "total": 4, "extras": 0}, "non_striker": "G Gambhir"}}, {"8.6": {"batsman": "V Kohli", "bowler": "SL Malinga", "runs": {"batsman": 4, "total": 4, "extras": 0}, "non_striker": "G Gambhir"}}, {"9.1": {"batsman": "G Gambhir", "bowler": "RAS Lakmal", "runs": {"batsman": 0, "total": 0, "extras": 0}, "non_striker": "V Kohli"}}, {"9.2": {"batsman": "G Gambhir", "bowler": "RAS Lakmal", "runs": {"batsman": 4, "total": 4, "extras": 0}, "non_striker": "V Kohli"}}, {"9.3": {"batsman": "G Gambhir", "bowler": "RAS Lakmal", "runs": {"batsman": 0, "total": 0, "extras": 0}, "non_striker": "V Kohli"}}, {"9.4": {"batsman": "G Gambhir", "bowler": "RAS Lakmal", "runs": {"batsman": 0, "total": 0, "extras": 0}, "non_striker": "V Kohli"}}, {"9.5": {"batsman": "G Gambhir", "bowler": "RAS Lakmal", "runs": {"batsman": 0, "total": 0, "extras": 0}, "non_striker": "V Kohli"}}, {"9.6": {"batsman": "G Gambhir", "bowler": "RAS Lakmal", "runs": {"batsman": 0, "total": 0, "extras": 0}, "non_striker": "V Kohli"}}, {"10.1": {"batsman": "V Kohli", "bowler": "SL Malinga", "runs": {"batsman": 1, "total": 1, "extras": 0}, "non_striker": "G Gambhir"}}, {"10.2": {"batsman": "G Gambhir", "bowler": "SL Malinga", "runs": {"batsman": 4, "total": 4, "extras": 0}, "non_striker": "V Kohli"}}, {"10.3": {"batsman": "G Gambhir", "bowler": "SL Malinga", "runs": {"batsman": 1, "total": 1, "extras": 0}, "non_striker": "V Kohli"}}, {"10.4": {"batsman": "V Kohli", "bowler": "SL Malinga", "runs": {"batsman": 0, "total": 1, "extras": 1}, "extras": {"wides": 1}, "non_striker": "G Gambhir"}}, {"10.5": {"batsman": "V Kohli", "bowler": "SL Malinga", "runs": {"batsman": 0, "total": 0, "extras": 0}, "non_striker": "G Gambhir"}}, {"10.6": {"batsman": "V Kohli", "bowler": "SL Malinga", "runs": {"batsman": 0, "total": 0, "extras": 0}, "non_striker": "G Gambhir"}}, {"10.7": {"batsman": "V Kohli", "bowler": "SL Malinga", "runs": {"batsman": 1, "total": 1, "extras": 0}, "non_striker": "G Gambhir"}}, {"11.1": {"batsman": "V Kohli", "bowler": "RAS Lakmal", "runs": {"batsman": 0, "total": 0, "extras": 0}, "non_striker": "G Gambhir"}}, {"11.2": {"batsman": "V Kohli", "bowler": "RAS Lakmal", "runs": {"batsman": 1, "total": 1, "extras": 0}, "non_striker": "G Gambhir"}}, {"11.3": {"batsman": "G Gambhir", "bowler": "RAS Lakmal", "runs": {"batsman": 1, "total": 1, "extras": 0}, "non_striker": "V Kohli"}}, {"11.4": {"batsman": "V Kohli", "bowler": "RAS Lakmal", "runs": {"batsman": 0, "total": 0, "extras": 0}, "non_striker": "G Gambhir"}}, {"11.5": {"batsman": "V Kohli", "bowler": "RAS Lakmal", "runs": {"batsman": 0, "total": 0, "extras": 0}, "non_striker": "G Gambhir"}}, {"11.6": {"batsman": "V Kohli", "bowler": "RAS Lakmal", "runs": {"batsman": 0, "total": 0, "extras": 0}, "non_striker": "G Gambhir"}}, {"12.1": {"batsman": "G Gambhir", "bowler": "SL Malinga", "runs": {"batsman": 0, "total": 0, "extras": 0}, "non_striker": "V Kohli"}}, {"12.2": {"batsman": "G Gambhir", "bowler": "SL Malinga", "runs": {"batsman": 1, "total": 1, "extras": 0}, "non_striker": "V Kohli"}}, {"12.3": {"batsman": "V Kohli", "bowler": "SL Malinga", "runs": {"batsman": 0, "total": 0, "extras": 0}, "non_striker": "G Gambhir"}}, {"12.4": {"batsman": "V Kohli", "bowler": "SL Malinga", "runs": {"batsman": 1, "total": 1, "extras": 0}, "non_striker": "G Gambhir"}}, {"12.5": {"batsman": "G Gambhir", "bowler": "SL Malinga", "runs": {"batsman": 0, "total": 0, "extras": 0}, "non_striker": "V Kohli"}}, {"12.6": {"batsman": "G Gambhir", "bowler": "SL Malinga", "runs": {"batsman": 1, "total": 1, "extras": 0}, "non_striker": "V Kohli"}}, {"13.1": {"batsman": "G Gambhir", "bowler": "RAS Lakmal", "runs": {"batsman": 1, "total": 1, "extras": 0}, "non_striker": "V Kohli"}}, {"13.2": {"batsman": "V Kohli", "bowler": "RAS Lakmal", "runs": {"batsman": 1, "total": 1, "extras": 0}, "non_striker": "G Gambhir"}}, {"13.3": {"batsman": "G Gambhir", "bowler": "RAS Lakmal", "runs": {"batsman": 1, "total": 1, "extras": 0}, "non_striker": "V Kohli"}}, {"13.4": {"batsman": "V Kohli", "bowler": "RAS Lakmal", "runs": {"batsman": 0, "total": 0, "extras": 0}, "non_striker": "G Gambhir"}}, {"13.5": {"batsman": "V Kohli", "bowler": "RAS Lakmal", "runs": {"batsman": 1, "total": 1, "extras": 0}, "non_striker": "G Gambhir"}}, {"13.6": {"batsman": "G Gambhir", "bowler": "RAS Lakmal", "runs": {"batsman": 0, "total": 0, "extras": 0}, "non_striker": "V Kohli"}}, {"14.1": {"batsman": "V Kohli", "bowler": "SL Malinga", "runs": {"batsman": 1, "total": 1, "extras": 0}, "non_striker": "G Gambhir"}}, {"14.2": {"batsman": "G Gambhir", "bowler": "SL Malinga", "runs": {"batsman": 4, "total": 4, "extras": 0}, "non_striker": "V Kohli"}}, {"14.3": {"batsman": "G Gambhir", "bowler": "SL Malinga", "runs": {"batsman": 0, "total": 0, "extras": 0}, "non_striker": "V Kohli"}}, {"14.4": {"batsman": "G Gambhir", "bowler": "SL Malinga", "runs": {"batsman": 1, "total": 1, "extras": 0}, "non_striker": "V Kohli"}}, {"14.5": {"batsman": "V Kohli", "bowler": "SL Malinga", "runs": {"batsman": 0, "total": 0, "extras": 0}, "non_striker": "G Gambhir"}}, {"14.6": {"batsman": "V Kohli", "bowler": "SL Malinga", "runs": {"batsman": 1, "total": 1, "extras": 0}, "non_striker": "G Gambhir"}}, {"15.1": {"batsman": "V Kohli", "bowler": "S Randiv", "runs": {"batsman": 1, "total": 1, "extras": 0}, "non_striker": "G Gambhir"}}, {"15.2": {"batsman": "G Gambhir", "bowler": "S Randiv", "runs": {"batsman": 1, "total": 1, "extras": 0}, "non_striker": "V Kohli"}}, {"15.3": {"batsman": "V Kohli", "bowler": "S Randiv", "runs": {"batsman": 2, "total": 2, "extras": 0}, "non_striker": "G Gambhir"}}, {"15.4": {"batsman": "V Kohli", "bowler": "S Randiv", "runs": {"batsman": 1, "total": 1, "extras": 0}, "non_striker": "G Gambhir"}}, {"15.5": {"batsman": "G Gambhir", "bowler": "S Randiv", "runs": {"batsman": 1, "total": 1, "extras": 0}, "non_striker": "V Kohli"}}, {"15.6": {"batsman": "V Kohli", "bowler": "S Randiv", "runs": {"batsman": 0, "total": 0, "extras": 0}, "non_striker": "G Gambhir"}}, {"16.1": {"batsman": "G Gambhir", "bowler": "SL Malinga", "runs": {"batsman": 1, "total": 1, "extras": 0}, "non_striker": "V Kohli"}}, {"16.2": {"batsman": "V Kohli", "bowler": "SL Malinga", "runs": {"batsman": 4, "total": 4, "extras": 0}, "non_striker": "G Gambhir"}}, {"16.3": {"batsman": "V Kohli", "bowler": "SL Malinga", "runs": {"batsman": 0, "total": 0, "extras": 0}, "non_striker": "G Gambhir"}}, {"16.4": {"batsman": "V Kohli", "bowler": "SL Malinga", "runs": {"batsman": 0, "total": 0, "extras": 0}, "non_striker": "G Gambhir"}}, {"16.5": {"batsman": "V Kohli", "bowler": "SL Malinga", "runs": {"batsman": 1, "total": 1, "extras": 0}, "non_striker": "G Gambhir"}}, {"16.6": {"batsman": "G Gambhir", "bowler": "SL Malinga", "runs": {"batsman": 1, "total": 1, "extras": 0}, "non_striker": "V Kohli"}}, {"17.1": {"batsman": "G Gambhir", "bowler": "S Randiv", "runs": {"batsman": 0, "total": 0, "extras": 0}, "non_striker": "V Kohli"}}, {"17.2": {"batsman": "G Gambhir", "bowler": "S Randiv", "runs": {"batsman": 1, "total": 1, "extras": 0}, "non_striker": "V Kohli"}}, {"17.3": {"batsman": "V Kohli", "bowler": "S Randiv", "runs": {"batsman": 1, "total": 1, "extras": 0}, "non_striker": "G Gambhir"}}, {"17.4": {"batsman": "G Gambhir", "bowler": "S Randiv", "runs": {"batsman": 2, "total": 2, "extras": 0}, "non_striker": "V Kohli"}}, {"17.5": {"batsman": "G Gambhir", "bowler": "S Randiv", "runs": {"batsman": 1, "total": 1, "extras": 0}, "non_striker": "V Kohli"}}, {"17.6": {"batsman": "V Kohli", "bowler": "S Randiv", "runs": {"batsman": 4, "total": 4, "extras": 0}, "non_striker": "G Gambhir"}}, {"18.1": {"batsman": "G Gambhir", "bowler": "ST Jayasuriya", "runs": {"batsman": 1, "total": 1, "extras": 0}, "non_striker": "V Kohli"}}, {"18.2": {"batsman": "V Kohli", "bowler": "ST Jayasuriya", "runs": {"batsman": 1, "total": 1, "extras": 0}, "non_striker": "G Gambhir"}}, {"18.3": {"batsman": "G Gambhir", "bowler": "ST Jayasuriya", "runs": {"batsman": 1, "total": 1, "extras": 0}, "non_striker": "V Kohli"}}, {"18.4": {"batsman": "V Kohli", "bowler": "ST Jayasuriya", "runs": {"batsman": 0, "total": 0, "extras": 0}, "non_striker": "G Gambhir"}}, {"18.5": {"batsman": "V Kohli", "bowler": "ST Jayasuriya", "runs": {"batsman": 1, "total": 1, "extras": 0}, "non_striker": "G Gambhir"}}, {"18.6": {"batsman": "G Gambhir", "bowler": "ST Jayasuriya", "runs": {"batsman": 1, "total": 1, "extras": 0}, "non_striker": "V Kohli"}}, {"19.1": {"batsman": "G Gambhir", "bowler": "S Randiv", "runs": {"batsman": 4, "total": 4, "extras": 0}, "non_striker": "V Kohli"}}, {"19.2": {"batsman": "G Gambhir", "bowler": "S Randiv", "runs": {"batsman": 2, "total": 2, "extras": 0}, "non_striker": "V Kohli"}}, {"19.3": {"batsman": "G Gambhir", "bowler": "S Randiv", "runs": {"batsman": 1, "total": 1, "extras": 0}, "non_striker": "V Kohli"}}, {"19.4": {"batsman": "V Kohli", "bowler": "S Randiv", "runs": {"batsman": 1, "total": 1, "extras": 0}, "non_striker": "G Gambhir"}}, {"19.5": {"batsman": "G Gambhir", "bowler": "S Randiv", "runs": {"batsman": 1, "total": 1, "extras": 0}, "non_striker": "V Kohli"}}, {"19.6": {"batsman": "V Kohli", "bowler": "S Randiv", "runs": {"batsman": 1, "total": 1, "extras": 0}, "non_striker": "G Gambhir"}}, {"20.1": {"batsman": "V Kohli", "bowler": "ST Jayasuriya", "runs": {"batsman": 0, "total": 0, "extras": 0}, "non_striker": "G Gambhir"}}, {"20.2": {"batsman": "V Kohli", "bowler": "ST Jayasuriya", "runs": {"batsman": 1, "total": 1, "extras": 0}, "non_striker": "G Gambhir"}}, {"20.3": {"batsman": "G Gambhir", "bowler": "ST Jayasuriya", "runs": {"batsman": 0, "total": 0, "extras": 0}, "non_striker": "V Kohli"}}, {"20.4": {"batsman": "G Gambhir", "bowler": "ST Jayasuriya", "runs": {"batsman": 1, "total": 1, "extras": 0}, "non_striker": "V Kohli"}}, {"20.5": {"batsman": "V Kohli", "bowler": "ST Jayasuriya", "runs": {"batsman": 0, "total": 0, "extras": 0}, "non_striker": "G Gambhir"}}, {"20.6": {"batsman": "V Kohli", "bowler": "ST Jayasuriya", "runs": {"batsman": 2, "total": 2, "extras": 0}, "non_striker": "G Gambhir"}}, {"21.1": {"batsman": "G Gambhir", "bowler": "S Randiv", "runs": {"batsman": 1, "total": 1, "extras": 0}, "non_striker": "V Kohli"}}, {"21.2": {"batsman": "V Kohli", "bowler": "S Randiv", "runs": {"batsman": 1, "total": 1, "extras": 0}, "non_striker": "G Gambhir"}}, {"21.3": {"batsman": "G Gambhir", "bowler": "S Randiv", "runs": {"batsman": 1, "total": 1, "extras": 0}, "non_striker": "V Kohli"}}, {"21.4": {"batsman": "V Kohli", "bowler": "S Randiv", "runs": {"batsman": 1, "total": 1, "extras": 0}, "non_striker": "G Gambhir"}}, {"21.5": {"batsman": "G Gambhir", "bowler": "S Randiv", "runs": {"batsman": 0, "total": 0, "extras": 0}, "non_striker": "V Kohli"}}, {"21.6": {"batsman": "G Gambhir", "bowler": "S Randiv", "runs": {"batsman": 4, "total": 4, "extras": 0}, "non_striker": "V Kohli"}}, {"22.1": {"batsman": "V Kohli", "bowler": "ST Jayasuriya", "runs": {"batsman": 1, "total": 1, "extras": 0}, "non_striker": "G Gambhir"}}, {"22.2": {"batsman": "G Gambhir", "bowler": "ST Jayasuriya", "runs": {"batsman": 0, "total": 0, "extras": 0}, "non_striker": "V Kohli"}}, {"22.3": {"batsman": "G Gambhir", "bowler": "ST Jayasuriya", "runs": {"batsman": 1, "total": 1, "extras": 0}, "non_striker": "V Kohli"}}, {"22.4": {"batsman": "V Kohli", "bowler": "ST Jayasuriya", "runs": {"batsman": 0, "total": 0, "extras": 0}, "non_striker": "G Gambhir"}}, {"22.5": {"batsman": "V Kohli", "bowler": "ST Jayasuriya", "runs": {"batsman": 0, "total": 0, "extras": 0}, "non_striker": "G Gambhir"}}, {"22.6": {"batsman": "V Kohli", "bowler": "ST Jayasuriya", "runs": {"batsman": 1, "total": 1, "extras": 0}, "non_striker": "G Gambhir"}}, {"23.1": {"batsman": "V Kohli", "bowler": "S Randiv", "runs": {"batsman": 1, "total": 1, "extras": 0}, "non_striker": "G Gambhir"}}, {"23.2": {"batsman": "G Gambhir", "bowler": "S Randiv", "runs": {"batsman": 0, "total": 0, "extras": 0}, "non_striker": "V Kohli"}}, {"23.3": {"batsman": "G Gambhir", "bowler": "S Randiv", "runs": {"batsman": 0, "total": 0, "extras": 0}, "non_striker": "V Kohli"}}, {"23.4": {"batsman": "G Gambhir", "bowler": "S Randiv", "runs": {"batsman": 0, "total": 0, "extras": 0}, "non_striker": "V Kohli"}}, {"23.5": {"batsman": "G Gambhir", "bowler": "S Randiv", "runs": {"batsman": 0, "total": 0, "extras": 0}, "non_striker": "V Kohli"}}, {"23.6": {"batsman": "G Gambhir", "bowler": "S Randiv", "runs": {"batsman": 0, "total": 0, "extras": 0}, "non_striker": "V Kohli"}}, {"24.1": {"batsman": "V Kohli", "bowler": "ST Jayasuriya", "runs": {"batsman": 1, "total": 1, "extras": 0}, "non_striker": "G Gambhir"}}, {"24.2": {"batsman": "G Gambhir", "bowler": "ST Jayasuriya", "runs": {"non_boundary": 1, "total": 4, "extras": 0, "batsman": 4}, "non_striker": "V Kohli"}}, {"24.3": {"batsman": "G Gambhir", "bowler": "ST Jayasuriya", "runs": {"batsman": 1, "total": 1, "extras": 0}, "non_striker": "V Kohli"}}, {"24.4": {"batsman": "V Kohli", "bowler": "ST Jayasuriya", "runs": {"batsman": 1, "total": 1, "extras": 0}, "non_striker": "G Gambhir"}}, {"24.5": {"batsman": "G Gambhir", "bowler": "ST Jayasuriya", "runs": {"batsman": 1, "total": 1, "extras": 0}, "non_striker": "V Kohli"}}, {"24.6": {"batsman": "V Kohli", "bowler": "ST Jayasuriya", "runs": {"batsman": 0, "total": 0, "extras": 0}, "non_striker": "G Gambhir"}}, {"25.1": {"batsman": "G Gambhir", "bowler": "S Randiv", "runs": {"batsman": 1, "total": 1, "extras": 0}, "non_striker": "V Kohli"}}, {"25.2": {"batsman": "V Kohli", "bowler": "S Randiv", "runs": {"batsman": 1, "total": 1, "extras": 0}, "non_striker": "G Gambhir"}}, {"25.3": {"batsman": "G Gambhir", "bowler": "S Randiv", "runs": {"batsman": 1, "total": 1, "extras": 0}, "non_striker": "V Kohli"}}, {"25.4": {"batsman": "V Kohli", "bowler": "S Randiv", "runs": {"batsman": 0, "total": 0, "extras": 0}, "non_striker": "G Gambhir"}}, {"25.5": {"batsman": "V Kohli", "bowler": "S Randiv", "runs": {"batsman": 0, "total": 0, "extras": 0}, "non_striker": "G Gambhir"}}, {"25.6": {"batsman": "V Kohli", "bowler": "S Randiv", "runs": {"batsman": 1, "total": 1, "extras": 0}, "non_striker": "G Gambhir"}}, {"26.1": {"batsman": "V Kohli", "bowler": "ST Jayasuriya", "runs": {"batsman": 4, "total": 4, "extras": 0}, "non_striker": "G Gambhir"}}, {"26.2": {"batsman": "V Kohli", "bowler": "ST Jayasuriya", "runs": {"batsman": 1, "total": 1, "extras": 0}, "non_striker": "G Gambhir"}}, {"26.3": {"batsman": "G Gambhir", "bowler": "ST Jayasuriya", "runs": {"batsman": 2, "total": 2, "extras": 0}, "non_striker": "V Kohli"}}, {"26.4": {"batsman": "G Gambhir", "bowler": "ST Jayasuriya", "runs": {"batsman": 0, "total": 0, "extras": 0}, "non_striker": "V Kohli"}}, {"26.5": {"batsman": "G Gambhir", "bowler": "ST Jayasuriya", "runs": {"batsman": 1, "total": 1, "extras": 0}, "non_striker": "V Kohli"}}, {"26.6": {"batsman": "V Kohli", "bowler": "ST Jayasuriya", "runs": {"batsman": 1, "total": 1, "extras": 0}, "non_striker": "G Gambhir"}}, {"27.1": {"batsman": "V Kohli", "bowler": "S Randiv", "runs": {"batsman": 0, "total": 0, "extras": 0}, "non_striker": "G Gambhir"}}, {"27.2": {"batsman": "V Kohli", "bowler": "S Randiv", "runs": {"batsman": 1, "total": 1, "extras": 0}, "non_striker": "G Gambhir"}}, {"27.3": {"batsman": "G Gambhir", "bowler": "S Randiv", "runs": {"batsman": 1, "total": 1, "extras": 0}, "non_striker": "V Kohli"}}, {"27.4": {"batsman": "V Kohli", "bowler": "S Randiv", "runs": {"batsman": 1, "total": 1, "extras": 0}, "non_striker": "G Gambhir"}}, {"27.5": {"batsman": "G Gambhir", "bowler": "S Randiv", "runs": {"batsman": 2, "total": 2, "extras": 0}, "non_striker": "V Kohli"}}, {"27.6": {"batsman": "G Gambhir", "bowler": "S Randiv", "runs": {"batsman": 0, "total": 0, "extras": 0}, "non_striker": "V Kohli"}}, {"28.1": {"batsman": "V Kohli", "bowler": "NLTC Perera", "runs": {"batsman": 2, "total": 2, "extras": 0}, "non_striker": "G Gambhir"}}, {"28.2": {"batsman": "V Kohli", "bowler": "NLTC Perera", "runs": {"batsman": 1, "total": 1, "extras": 0}, "non_striker": "G Gambhir"}}, {"28.3": {"batsman": "G Gambhir", "bowler": "NLTC Perera", "runs": {"batsman": 1, "total": 1, "extras": 0}, "non_striker": "V Kohli"}}, {"28.4": {"batsman": "V Kohli", "bowler": "NLTC Perera", "runs": {"batsman": 4, "total": 4, "extras": 0}, "non_striker": "G Gambhir"}}, {"28.5": {"batsman": "V Kohli", "bowler": "NLTC Perera", "runs": {"batsman": 1, "total": 1, "extras": 0}, "non_striker": "G Gambhir"}}, {"28.6": {"batsman": "G Gambhir", "bowler": "NLTC Perera", "runs": {"batsman": 0, "total": 0, "extras": 0}, "non_striker": "V Kohli"}}, {"29.1": {"batsman": "V Kohli", "bowler": "SL Malinga", "runs": {"batsman": 1, "total": 1, "extras": 0}, "non_striker": "G Gambhir"}}, {"29.2": {"batsman": "G Gambhir", "bowler": "SL Malinga", "runs": {"batsman": 1, "total": 1, "extras": 0}, "non_striker": "V Kohli"}}, {"29.3": {"batsman": "V Kohli", "bowler": "SL Malinga", "runs": {"batsman": 1, "total": 1, "extras": 0}, "non_striker": "G Gambhir"}}, {"29.4": {"batsman": "G Gambhir", "bowler": "SL Malinga", "runs": {"batsman": 0, "total": 0, "extras": 0}, "non_striker": "V Kohli"}}, {"29.5": {"batsman": "G Gambhir", "bowler": "SL Malinga", "runs": {"batsman": 1, "total": 1, "extras": 0}, "non_striker": "V Kohli"}}, {"29.6": {"batsman": "V Kohli", "bowler": "SL Malinga", "runs": {"batsman": 0, "total": 0, "extras": 0}, "non_striker": "G Gambhir"}}, {"30.1": {"batsman": "G Gambhir", "bowler": "NLTC Perera", "runs": {"batsman": 0, "total": 0, "extras": 0}, "non_striker": "V Kohli"}}, {"30.2": {"batsman": "G Gambhir", "bowler": "NLTC Perera", "runs": {"batsman": 1, "total": 1, "extras": 0}, "non_striker": "V Kohli"}}, {"30.3": {"batsman": "V Kohli", "bowler": "NLTC Perera", "runs": {"batsman": 0, "total": 0, "extras": 0}, "non_striker": "G Gambhir"}}, {"30.4": {"batsman": "V Kohli", "bowler": "NLTC Perera", "runs": {"batsman": 1, "total": 1, "extras": 0}, "non_striker": "G Gambhir"}}, {"30.5": {"batsman": "G Gambhir", "bowler": "NLTC Perera", "runs": {"batsman": 2, "total": 2, "extras": 0}, "non_striker": "V Kohli"}}, {"30.6": {"batsman": "G Gambhir", "bowler": "NLTC Perera", "runs": {"batsman": 2, "total": 2, "extras": 0}, "non_striker": "V Kohli"}}, {"31.1": {"batsman": "V Kohli", "bowler": "SL Malinga", "runs": {"batsman": 0, "total": 1, "extras": 1}, "extras": {"wides": 1}, "non_striker": "G Gambhir"}}, {"31.2": {"batsman": "V Kohli", "bowler": "SL Malinga", "runs": {"batsman": 0, "total": 0, "extras": 0}, "non_striker": "G Gambhir"}}, {"31.3": {"batsman": "V Kohli", "bowler": "SL Malinga", "runs": {"batsman": 1, "total": 1, "extras": 0}, "non_striker": "G Gambhir"}}, {"31.4": {"batsman": "G Gambhir", "bowler": "SL Malinga", "runs": {"batsman": 1, "total": 1, "extras": 0}, "non_striker": "V Kohli"}}, {"31.5": {"batsman": "V Kohli", "bowler": "SL Malinga", "runs": {"batsman": 1, "total": 1, "extras": 0}, "non_striker": "G Gambhir"}}, {"31.6": {"batsman": "G Gambhir", "bowler": "SL Malinga", "runs": {"batsman": 0, "total": 1, "extras": 1}, "extras": {"wides": 1}, "non_striker": "V Kohli"}}, {"31.7": {"batsman": "G Gambhir", "bowler": "SL Malinga", "runs": {"batsman": 1, "total": 1, "extras": 0}, "non_striker": "V Kohli"}}, {"31.8": {"batsman": "V Kohli", "bowler": "SL Malinga", "runs": {"batsman": 0, "total": 0, "extras": 0}, "non_striker": "G Gambhir"}}, {"32.1": {"batsman": "G Gambhir", "bowler": "NLTC Perera", "runs": {"batsman": 1, "total": 1, "extras": 0}, "non_striker": "V Kohli"}}, {"32.2": {"batsman": "V Kohli", "bowler": "NLTC Perera", "runs": {"batsman": 0, "total": 0, "extras": 0}, "non_striker": "G Gambhir"}}, {"32.3": {"batsman": "V Kohli", "bowler": "NLTC Perera", "runs": {"batsman": 0, "total": 0, "extras": 0}, "non_striker": "G Gambhir"}}, {"32.4": {"batsman": "V Kohli", "bowler": "NLTC Perera", "runs": {"batsman": 0, "total": 1, "extras": 1}, "extras": {"wides": 1}, "non_striker": "G Gambhir"}}, {"32.5": {"batsman": "V Kohli", "bowler": "NLTC Perera", "runs": {"batsman": 0, "total": 0, "extras": 0}, "non_striker": "G Gambhir"}}, {"32.6": {"batsman": "V Kohli", "bowler": "NLTC Perera", "runs": {"batsman": 2, "total": 2, "extras": 0}, "non_striker": "G Gambhir"}}, {"32.7": {"batsman": "V Kohli", "bowler": "NLTC Perera", "runs": {"batsman": 1, "total": 1, "extras": 0}, "non_striker": "G Gambhir"}}, {"33.1": {"batsman": "V Kohli", "bowler": "TM Dilshan", "runs": {"batsman": 0, "total": 0, "extras": 0}, "non_striker": "G Gambhir"}}, {"33.2": {"batsman": "V Kohli", "bowler": "TM Dilshan", "runs": {"batsman": 1, "total": 1, "extras": 0}, "non_striker": "G Gambhir"}}, {"33.3": {"batsman": "G Gambhir", "bowler": "TM Dilshan", "runs": {"batsman": 1, "total": 1, "extras": 0}, "non_striker": "V Kohli"}}, {"33.4": {"batsman": "V Kohli", "bowler": "TM Dilshan", "runs": {"batsman": 1, "total": 1, "extras": 0}, "non_striker": "G Gambhir"}}, {"33.5": {"batsman": "G Gambhir", "bowler": "TM Dilshan", "runs": {"batsman": 1, "total": 1, "extras": 0}, "non_striker": "V Kohli"}}, {"33.6": {"batsman": "V Kohli", "bowler": "TM Dilshan", "runs": {"batsman": 0, "total": 0, "extras": 0}, "non_striker": "G Gambhir"}}, {"34.1": {"batsman": "G Gambhir", "bowler": "ST Jayasuriya", "runs": {"batsman": 1, "total": 1, "extras": 0}, "non_striker": "V Kohli"}}, {"34.2": {"batsman": "V Kohli", "bowler": "ST Jayasuriya", "runs": {"batsman": 4, "total": 4, "extras": 0}, "non_striker": "G Gambhir"}}, {"34.3": {"batsman": "V Kohli", "bowler": "ST Jayasuriya", "runs": {"batsman": 0, "total": 0, "extras": 0}, "non_striker": "G Gambhir"}}, {"34.4": {"batsman": "V Kohli", "bowler": "ST Jayasuriya", "runs": {"batsman": 1, "total": 1, "extras": 0}, "non_striker": "G Gambhir"}}, {"34.5": {"batsman": "G Gambhir", "bowler": "ST Jayasuriya", "runs": {"batsman": 0, "total": 0, "extras": 0}, "non_striker": "V Kohli"}}, {"34.6": {"batsman": "G Gambhir", "bowler": "ST Jayasuriya", "runs": {"batsman": 1, "total": 1, "extras": 0}, "non_striker": "V Kohli"}}, {"35.1": {"batsman": "G Gambhir", "bowler": "TM Dilshan", "runs": {"batsman": 2, "total": 2, "extras": 0}, "non_striker": "V Kohli"}}, {"35.2": {"batsman": "G Gambhir", "bowler": "TM Dilshan", "runs": {"batsman": 0, "total": 0, "extras": 0}, "non_striker": "V Kohli"}}, {"35.3": {"batsman": "G Gambhir", "bowler": "TM Dilshan", "runs": {"batsman": 0, "total": 0, "extras": 0}, "non_striker": "V Kohli"}}, {"35.4": {"batsman": "G Gambhir", "bowler": "TM Dilshan", "runs": {"batsman": 4, "total": 4, "extras": 0}, "non_striker": "V Kohli"}}, {"35.5": {"batsman": "G Gambhir", "bowler": "TM Dilshan", "runs": {"batsman": 1, "total": 1, "extras": 0}, "non_striker": "V Kohli"}}, {"35.6": {"batsman": "V Kohli", "bowler": "TM Dilshan", "runs": {"batsman": 1, "total": 1, "extras": 0}, "non_striker": "G Gambhir"}}, {"36.1": {"batsman": "V Kohli", "bowler": "ST Jayasuriya", "runs": {"batsman": 1, "total": 1, "extras": 0}, "non_striker": "G Gambhir"}}, {"36.2": {"batsman": "G Gambhir", "bowler": "ST Jayasuriya", "runs": {"batsman": 2, "total": 2, "extras": 0}, "non_striker": "V Kohli"}}, {"36.3": {"batsman": "G Gambhir", "bowler": "ST Jayasuriya", "runs": {"batsman": 1, "total": 1, "extras": 0}, "non_striker": "V Kohli"}}, {"36.4": {"batsman": "V Kohli", "bowler": "ST Jayasuriya", "runs": {"batsman": 0, "total": 0, "extras": 0}, "non_striker": "G Gambhir"}}, {"36.5": {"batsman": "V Kohli", "bowler": "ST Jayasuriya", "runs": {"batsman": 1, "total": 1, "extras": 0}, "non_striker": "G Gambhir"}}, {"36.6": {"batsman": "G Gambhir", "bowler": "ST Jayasuriya", "runs": {"batsman": 1, "total": 1, "extras": 0}, "non_striker": "V Kohli"}}, {"37.1": {"batsman": "G Gambhir", "bowler": "TM Dilshan", "runs": {"batsman": 1, "total": 1, "extras": 0}, "non_striker": "V Kohli"}}, {"37.2": {"batsman": "V Kohli", "bowler": "TM Dilshan", "runs": {"batsman": 0, "total": 0, "extras": 0}, "non_striker": "G Gambhir"}}, {"37.3": {"batsman": "V Kohli", "bowler": "TM Dilshan", "runs": {"batsman": 1, "total": 1, "extras": 0}, "non_striker": "G Gambhir"}}, {"37.4": {"batsman": "G Gambhir", "bowler": "TM Dilshan", "runs": {"batsman": 1, "total": 1, "extras": 0}, "non_striker": "V Kohli"}}, {"37.5": {"batsman": "V Kohli", "bowler": "TM Dilshan", "runs": {"batsman": 1, "total": 1, "extras": 0}, "non_striker": "G Gambhir"}}, {"37.6": {"batsman": "G Gambhir", "bowler": "TM Dilshan", "runs": {"batsman": 1, "total": 1, "extras": 0}, "non_striker": "V Kohli"}}, {"38.1": {"batsman": "G Gambhir", "bowler": "NLTC Perera", "runs": {"batsman": 0, "total": 0, "extras": 0}, "non_striker": "V Kohli"}}, {"38.2": {"batsman": "G Gambhir", "bowler": "NLTC Perera", "runs": {"batsman": 1, "total": 1, "extras": 0}, "non_striker": "V Kohli"}}, {"38.3": {"batsman": "V Kohli", "bowler": "NLTC Perera", "runs": {"batsman": 0, "total": 0, "extras": 0}, "non_striker": "G Gambhir"}}, {"38.4": {"batsman": "V Kohli", "bowler": "NLTC Perera", "runs": {"batsman": 1, "total": 1, "extras": 0}, "non_striker": "G Gambhir"}}, {"38.5": {"batsman": "G Gambhir", "bowler": "NLTC Perera", "runs": {"batsman": 1, "total": 1, "extras": 0}, "non_striker": "V Kohli"}}, {"38.6": {"batsman": "V Kohli", "bowler": "NLTC Perera", "runs": {"batsman": 6, "total": 6, "extras": 0}, "non_striker": "G Gambhir"}}, {"39.1": {"batsman": "G Gambhir", "bowler": "S Randiv", "runs": {"batsman": 1, "total": 1, "extras": 0}, "non_striker": "V Kohli"}}, {"39.2": {"batsman": "V Kohli", "bowler": "S Randiv", "runs": {"batsman": 0, "total": 0, "extras": 0}, "non_striker": "G Gambhir", "wicket": {"fielders": ["M Pushpakumara (sub)"], "kind": "caught", "player_out": "V Kohli"}}}, {"39.3": {"batsman": "KD Karthik", "bowler": "S Randiv", "runs": {"batsman": 1, "total": 1, "extras": 0}, "non_striker": "G Gambhir"}}, {"39.4": {"batsman": "G Gambhir", "bowler": "S Randiv", "runs": {"batsman": 1, "total": 1, "extras": 0}, "non_striker": "KD Karthik"}}, {"39.5": {"batsman": "KD Karthik", "bowler": "S Randiv", "runs": {"batsman": 1, "total": 1, "extras": 0}, "non_striker": "G Gambhir"}}, {"39.6": {"batsman": "G Gambhir", "bowler": "S Randiv", "runs": {"batsman": 1, "total": 1, "extras": 0}, "non_striker": "KD Karthik"}}, {"40.1": {"batsman": "G Gambhir", "bowler": "NLTC Perera", "runs": {"batsman": 4, "total": 4, "extras": 0}, "non_striker": "KD Karthik"}}, {"40.2": {"batsman": "G Gambhir", "bowler": "NLTC Perera", "runs": {"batsman": 0, "total": 0, "extras": 0}, "non_striker": "KD Karthik"}}, {"40.3": {"batsman": "G Gambhir", "bowler": "NLTC Perera", "runs": {"batsman": 4, "total": 4, "extras": 0}, "non_striker": "KD Karthik"}}, {"40.4": {"batsman": "G Gambhir", "bowler": "NLTC Perera", "runs": {"batsman": 0, "total": 0, "extras": 0}, "non_striker": "KD Karthik"}}, {"40.5": {"batsman": "G Gambhir", "bowler": "NLTC Perera", "runs": {"batsman": 1, "total": 1, "extras": 0}, "non_striker": "KD Karthik"}}, {"40.6": {"batsman": "KD Karthik", "bowler": "NLTC Perera", "runs": {"batsman": 0, "total": 0, "extras": 0}, "non_striker": "G Gambhir"}}, {"41.1": {"batsman": "G Gambhir", "bowler": "S Randiv", "runs": {"batsman": 1, "total": 1, "extras": 0}, "non_striker": "KD Karthik"}}, {"41.2": {"batsman": "KD Karthik", "bowler": "S Randiv", "runs": {"batsman": 0, "total": 0, "extras": 0}, "non_striker": "G Gambhir"}}, {"41.3": {"batsman": "KD Karthik", "bowler": "S Randiv", "runs": {"batsman": 1, "total": 1, "extras": 0}, "non_striker": "G Gambhir"}}, {"41.4": {"batsman": "G Gambhir", "bowler": "S Randiv", "runs": {"batsman": 1, "total": 1, "extras": 0}, "non_striker": "KD Karthik"}}, {"41.5": {"batsman": "KD Karthik", "bowler": "S Randiv", "runs": {"batsman": 1, "total": 1, "extras": 0}, "non_striker": "G Gambhir"}}, {"41.6": {"batsman": "G Gambhir", "bowler": "S Randiv", "runs": {"batsman": 1, "total": 1, "extras": 0}, "non_striker": "KD Karthik"}}, {"42.1": {"batsman": "G Gambhir", "bowler": "RAS Lakmal", "runs": {"batsman": 4, "total": 4, "extras": 0}, "non_striker": "KD Karthik"}}, {"42.2": {"batsman": "G Gambhir", "bowler": "RAS Lakmal", "runs": {"batsman": 1, "total": 1, "extras": 0}, "non_striker": "KD Karthik"}}, {"42.3": {"batsman": "KD Karthik", "bowler": "RAS Lakmal", "runs": {"batsman": 1, "total": 1, "extras": 0}, "non_striker": "G Gambhir"}}, {"42.4": {"batsman": "G Gambhir", "bowler": "RAS Lakmal", "runs": {"batsman": 4, "total": 4, "extras": 0}, "non_striker": "KD Karthik"}}, {"42.5": {"batsman": "G Gambhir", "bowler": "RAS Lakmal", "runs": {"batsman": 0, "total": 0, "extras": 0}, "non_striker": "KD Karthik"}}, {"42.6": {"batsman": "G Gambhir", "bowler": "RAS Lakmal", "runs": {"batsman": 1, "total": 1, "extras": 0}, "non_striker": "KD Karthik"}}, {"43.1": {"batsman": "G Gambhir", "bowler": "S Randiv", "runs": {"batsman": 0, "total": 0, "extras": 0}, "non_striker": "KD Karthik"}}, {"43.2": {"batsman": "G Gambhir", "bowler": "S Randiv", "runs": {"batsman": 0, "total": 1, "extras": 1}, "extras": {"wides": 1}, "non_striker": "KD Karthik"}}, {"43.3": {"batsman": "G Gambhir", "bowler": "S Randiv", "runs": {"batsman": 0, "total": 0, "extras": 0}, "non_striker": "KD Karthik"}}, {"43.4": {"batsman": "G Gambhir", "bowler": "S Randiv", "runs": {"batsman": 1, "total": 1, "extras": 0}, "non_striker": "KD Karthik"}}, {"43.5": {"batsman": "KD Karthik", "bowler": "S Randiv", "runs": {"batsman": 0, "total": 0, "extras": 0}, "non_striker": "G Gambhir"}}, {"43.6": {"batsman": "KD Karthik", "bowler": "S Randiv", "runs": {"batsman": 1, "total": 1, "extras": 0}, "non_striker": "G Gambhir"}}, {"43.7": {"batsman": "G Gambhir", "bowler": "S Randiv", "runs": {"batsman": 1, "total": 1, "extras": 0}, "non_striker": "KD Karthik"}}, {"44.1": {"batsman": "G Gambhir", "bowler": "SL Malinga", "runs": {"batsman": 1, "total": 2, "extras": 1}, "extras": {"noballs": 1}, "non_striker": "KD Karthik"}}, {"44.2": {"batsman": "KD Karthik", "bowler": "SL Malinga", "runs": {"batsman": 2, "total": 2, "extras": 0}, "non_striker": "G Gambhir"}}, {"44.3": {"batsman": "KD Karthik", "bowler": "SL Malinga", "runs": {"batsman": 2, "total": 2, "extras": 0}, "non_striker": "G Gambhir"}}, {"44.4": {"batsman": "KD Karthik", "bowler": "SL Malinga", "runs": {"batsman": 1, "total": 1, "extras": 0}, "non_striker": "G Gambhir"}}, {"44.5": {"batsman": "G Gambhir", "bowler": "SL Malinga", "runs": {"batsman": 0, "total": 0, "extras": 0}, "non_striker": "KD Karthik"}}, {"44.6": {"batsman": "G Gambhir", "bowler": "SL Malinga", "runs": {"batsman": 0, "total": 1, "extras": 1}, "extras": {"wides": 1}, "non_striker": "KD Karthik"}}, {"44.7": {"batsman": "G Gambhir", "bowler": "SL Malinga", "runs": {"batsman": 4, "total": 4, "extras": 0}, "non_striker": "KD Karthik"}}, {"44.8": {"batsman": "G Gambhir", "bowler": "SL Malinga", "runs": {"batsman": 1, "total": 1, "extras": 0}, "non_striker": "KD Karthik"}}, {"45.1": {"batsman": "G Gambhir", "bowler": "RAS Lakmal", "runs": {"batsman": 1, "total": 1, "extras": 0}, "non_striker": "KD Karthik"}}, {"45.2": {"batsman": "KD Karthik", "bowler": "RAS Lakmal", "runs": {"batsman": 0, "total": 0, "extras": 0}, "non_striker": "G Gambhir"}}, {"45.3": {"batsman": "KD Karthik", "bowler": "RAS Lakmal", "runs": {"batsman": 0, "total": 0, "extras": 0}, "non_striker": "G Gambhir"}}, {"45.4": {"batsman": "KD Karthik", "bowler": "RAS Lakmal", "runs": {"batsman": 0, "total": 0, "extras": 0}, "non_striker": "G Gambhir"}}, {"45.5": {"batsman": "KD Karthik", "bowler": "RAS Lakmal", "runs": {"batsman": 0, "total": 1, "extras": 1}, "extras": {"wides": 1}, "non_striker": "G Gambhir"}}, {"45.6": {"batsman": "KD Karthik", "bowler": "RAS Lakmal", "runs": {"batsman": 1, "total": 1, "extras": 0}, "non_striker": "G Gambhir"}}, {"45.7": {"batsman": "G Gambhir", "bowler": "RAS Lakmal", "runs": {"batsman": 1, "total": 1, "extras": 0}, "non_striker": "KD Karthik"}}, {"46.1": {"batsman": "G Gambhir", "bowler": "SL Malinga", "runs": {"batsman": 2, "total": 2, "extras": 0}, "non_striker": "KD Karthik"}}, {"46.2": {"batsman": "G Gambhir", "bowler": "SL Malinga", "runs": {"batsman": 1, "total": 1, "extras": 0}, "non_striker": "KD Karthik"}}, {"46.3": {"batsman": "KD Karthik", "bowler": "SL Malinga", "runs": {"batsman": 1, "total": 1, "extras": 0}, "non_striker": "G Gambhir"}}, {"46.4": {"batsman": "G Gambhir", "bowler": "SL Malinga", "runs": {"batsman": 1, "total": 1, "extras": 0}, "non_striker": "KD Karthik"}}, {"46.5": {"batsman": "KD Karthik", "bowler": "SL Malinga", "runs": {"batsman": 1, "total": 1, "extras": 0}, "non_striker": "G Gambhir"}}, {"46.6": {"batsman": "G Gambhir", "bowler": "SL Malinga", "runs": {"batsman": 1, "total": 1, "extras": 0}, "non_striker": "KD Karthik"}}, {"47.1": {"batsman": "G Gambhir", "bowler": "RAS Lakmal", "runs": {"batsman": 3, "total": 3, "extras": 0}, "non_striker": "KD Karthik"}}, {"47.2": {"batsman": "KD Karthik", "bowler": "RAS Lakmal", "runs": {"batsman": 0, "total": 0, "extras": 0}, "non_striker": "G Gambhir"}}, {"47.3": {"batsman": "KD Karthik", "bowler": "RAS Lakmal", "runs": {"batsman": 1, "total": 1, "extras": 0}, "non_striker": "G Gambhir"}}, {"47.4": {"batsman": "G Gambhir", "bowler": "RAS Lakmal", "runs": {"batsman": 1, "total": 1, "extras": 0}, "non_striker": "KD Karthik"}}, {"47.5": {"batsman": "KD Karthik", "bowler": "RAS Lakmal", "runs": {"batsman": 4, "total": 4, "extras": 0}, "non_striker": "G Gambhir"}}, {"47.6": {"batsman": "KD Karthik", "bowler": "RAS Lakmal", "runs": {"batsman": 0, "total": 0, "extras": 0}, "non_striker": "G Gambhir"}}, {"48.1": {"batsman": "G Gambhir", "bowler": "SL Malinga", "runs": {"batsman": 4, "total": 4, "extras": 0}, "non_striker": "KD Karthik"}}], "team": "India"}}], "meta": {"data_version": 0.6, "created": {"month": 1, "day": 1, "year": 2010}, "revision": 1}}