{"info": {"city": "Bloemfontein", "dates": [{"month": 10, "day": 15, "year": 2010}], "match_type": "ODI", "toss": {"decision": "bat", "winner": "South Africa"}, "venue": "OUTsurance Oval", "teams": ["South Africa", "Zimbabwe"], "umpires": ["Enamul Haque", "M Erasmus"], "player_of_match": ["CA Ingram"], "outcome": {"winner": "South Africa", "by": {"runs": 64}}, "overs": 50}, "innings": [{"1st innings": {"deliveries": [{"0.1": {"batsman": "HM Amla", "bowler": "CB Mpofu", "runs": {"batsman": 0, "total": 1, "extras": 1}, "extras": {"wides": 1}, "non_striker": "GC Smith"}}, {"0.2": {"batsman": "HM Amla", "bowler": "CB Mpofu", "runs": {"batsman": 0, "total": 0, "extras": 0}, "non_striker": "GC Smith"}}, {"0.3": {"batsman": "HM Amla", "bowler": "CB Mpofu", "runs": {"batsman": 0, "total": 0, "extras": 0}, "non_striker": "GC Smith"}}, {"0.4": {"batsman": "HM Amla", "bowler": "CB Mpofu", "runs": {"batsman": 0, "total": 0, "extras": 0}, "non_striker": "GC Smith"}}, {"0.5": {"batsman": "HM Amla", "bowler": "CB Mpofu", "runs": {"batsman": 4, "total": 4, "extras": 0}, "non_striker": "GC Smith"}}, {"0.6": {"batsman": "HM Amla", "bowler": "CB Mpofu", "runs": {"batsman": 4, "total": 4, "extras": 0}, "non_striker": "GC Smith"}}, {"0.7": {"batsman": "HM Amla", "bowler": "CB Mpofu", "runs": {"batsman": 0, "total": 0, "extras": 0}, "non_striker": "GC Smith"}}, {"1.1": {"batsman": "GC Smith", "bowler": "SW Masakadza", "runs": {"batsman": 0, "total": 0, "extras": 0}, "non_striker": "HM Amla"}}, {"1.2": {"batsman": "GC Smith", "bowler": "SW Masakadza", "runs": {"batsman": 0, "total": 0, "extras": 0}, "non_striker": "HM Amla"}}, {"1.3": {"batsman": "GC Smith", "bowler": "SW Masakadza", "runs": {"batsman": 1, "total": 1, "extras": 0}, "non_striker": "HM Amla"}}, {"1.4": {"batsman": "HM Amla", "bowler": "SW Masakadza", "runs": {"batsman": 2, "total": 2, "extras": 0}, "non_striker": "GC Smith"}}, {"1.5": {"batsman": "HM Amla", "bowler": "SW Masakadza", "runs": {"batsman": 4, "total": 4, "extras": 0}, "non_striker": "GC Smith"}}, {"1.6": {"batsman": "HM Amla", "bowler": "SW Masakadza", "runs": {"batsman": 0, "total": 0, "extras": 0}, "non_striker": "GC Smith"}}, {"2.1": {"batsman": "GC Smith", "bowler": "CB Mpofu", "runs": {"batsman": 4, "total": 4, "extras": 0}, "non_striker": "HM Amla"}}, {"2.2": {"batsman": "GC Smith", "bowler": "CB Mpofu", "runs": {"batsman": 0, "total": 0, "extras": 0}, "non_striker": "HM Amla"}}, {"2.3": {"batsman": "GC Smith", "bowler": "CB Mpofu", "runs": {"batsman": 0, "total": 0, "extras": 0}, "non_striker": "HM Amla"}}, {"2.4": {"batsman": "GC Smith", "bowler": "CB Mpofu", "runs": {"batsman": 0, "total": 1, "extras": 1}, "extras": {"wides": 1}, "non_striker": "HM Amla"}}, {"2.5": {"batsman": "GC Smith", "bowler": "CB Mpofu", "runs": {"batsman": 0, "total": 0, "extras": 0}, "non_striker": "HM Amla"}}, {"2.6": {"batsman": "GC Smith", "bowler": "CB Mpofu", "runs": {"batsman": 0, "total": 0, "extras": 0}, "non_striker": "HM Amla"}}, {"2.7": {"batsman": "GC Smith", "bowler": "CB Mpofu", "runs": {"batsman": 4, "total": 4, "extras": 0}, "non_striker": "HM Amla"}}, {"3.1": {"batsman": "HM Amla", "bowler": "SW Masakadza", "runs": {"batsman": 0, "total": 0, "extras": 0}, "non_striker": "GC Smith"}}, {"3.2": {"batsman": "HM Amla", "bowler": "SW Masakadza", "runs": {"batsman": 4, "total": 4, "extras": 0}, "non_striker": "GC Smith"}}, {"3.3": {"batsman": "HM Amla", "bowler": "SW Masakadza", "runs": {"batsman": 0, "total": 0, "extras": 0}, "non_striker": "GC Smith"}}, {"3.4": {"batsman": "HM Amla", "bowler": "SW Masakadza", "runs": {"batsman": 2, "total": 2, "extras": 0}, "non_striker": "GC Smith"}}, {"3.5": {"batsman": "HM Amla", "bowler": "SW Masakadza", "runs": {"batsman": 4, "total": 4, "extras": 0}, "non_striker": "GC Smith"}}, {"3.6": {"batsman": "HM Amla", "bowler": "SW Masakadza", "runs": {"batsman": 1, "total": 1, "extras": 0}, "non_striker": "GC Smith"}}, {"4.1": {"batsman": "HM Amla", "bowler": "CB Mpofu", "runs": {"batsman": 0, "total": 1, "extras": 1}, "extras": {"wides": 1}, "non_striker": "GC Smith"}}, {"4.2": {"batsman": "HM Amla", "bowler": "CB Mpofu", "runs": {"batsman": 1, "total": 1, "extras": 0}, "non_striker": "GC Smith"}}, {"4.3": {"batsman": "GC Smith", "bowler": "CB Mpofu", "runs": {"batsman": 0, "total": 0, "extras": 0}, "non_striker": "HM Amla"}}, {"4.4": {"batsman": "GC Smith", "bowler": "CB Mpofu", "runs": {"batsman": 1, "total": 1, "extras": 0}, "non_striker": "HM Amla"}}, {"4.5": {"batsman": "HM Amla", "bowler": "CB Mpofu", "runs": {"batsman": 0, "total": 0, "extras": 0}, "non_striker": "GC Smith"}}, {"4.6": {"batsman": "HM Amla", "bowler": "CB Mpofu", "runs": {"batsman": 0, "total": 0, "extras": 0}, "non_striker": "GC Smith"}}, {"4.7": {"batsman": "HM Amla", "bowler": "CB Mpofu", "runs": {"batsman": 4, "total": 4, "extras": 0}, "non_striker": "GC Smith"}}, {"5.1": {"batsman": "GC Smith", "bowler": "SW Masakadza", "runs": {"batsman": 0, "total": 0, "extras": 0}, "non_striker": "HM Amla"}}, {"5.2": {"batsman": "GC Smith", "bowler": "SW Masakadza", "runs": {"batsman": 0, "total": 0, "extras": 0}, "non_striker": "HM Amla"}}, {"5.3": {"batsman": "GC Smith", "bowler": "SW Masakadza", "runs": {"batsman": 1, "total": 1, "extras": 0}, "non_striker": "HM Amla"}}, {"5.4": {"batsman": "HM Amla", "bowler": "SW Masakadza", "runs": {"batsman": 0, "total": 0, "extras": 0}, "non_striker": "GC Smith"}}, {"5.5": {"batsman": "HM Amla", "bowler": "SW Masakadza", "runs": {"batsman": 0, "total": 0, "extras": 0}, "non_striker": "GC Smith"}}, {"5.6": {"batsman": "HM Amla", "bowler": "SW Masakadza", "runs": {"batsman": 0, "total": 0, "extras": 0}, "non_striker": "GC Smith"}}, {"6.1": {"batsman": "GC Smith", "bowler": "CB Mpofu", "runs": {"batsman": 0, "total": 0, "extras": 0}, "non_striker": "HM Amla"}}, {"6.2": {"batsman": "GC Smith", "bowler": "CB Mpofu", "runs": {"batsman": 1, "total": 1, "extras": 0}, "non_striker": "HM Amla"}}, {"6.3": {"batsman": "HM Amla", "bowler": "CB Mpofu", "runs": {"batsman": 0, "total": 0, "extras": 0}, "non_striker": "GC Smith"}}, {"6.4": {"batsman": "HM Amla", "bowler": "CB Mpofu", "runs": {"batsman": 1, "total": 1, "extras": 0}, "non_striker": "GC Smith"}}, {"6.5": {"batsman": "GC Smith", "bowler": "CB Mpofu", "runs": {"batsman": 3, "total": 3, "extras": 0}, "non_striker": "HM Amla"}}, {"6.6": {"batsman": "HM Amla", "bowler": "CB Mpofu", "runs": {"batsman": 0, "total": 1, "extras": 1}, "extras": {"wides": 1}, "non_striker": "GC Smith"}}, {"6.7": {"batsman": "HM Amla", "bowler": "CB Mpofu", "runs": {"batsman": 4, "total": 4, "extras": 0}, "non_striker": "GC Smith"}}, {"7.1": {"batsman": "GC Smith", "bowler": "SW Masakadza", "runs": {"batsman": 4, "total": 4, "extras": 0}, "non_striker": "HM Amla"}}, {"7.2": {"batsman": "GC Smith", "bowler": "SW Masakadza", "runs": {"batsman": 0, "total": 1, "extras": 1}, "extras": {"legbyes": 1}, "non_striker": "HM Amla"}}, {"7.3": {"batsman": "HM Amla", "bowler": "SW Masakadza", "runs": {"batsman": 4, "total": 4, "extras": 0}, "non_striker": "GC Smith"}}, {"7.4": {"batsman": "HM Amla", "bowler": "SW Masakadza", "runs": {"batsman": 1, "total": 1, "extras": 0}, "non_striker": "GC Smith"}}, {"7.5": {"batsman": "GC Smith", "bowler": "SW Masakadza", "runs": {"batsman": 0, "total": 0, "extras": 0}, "non_striker": "HM Amla", "wicket": {"fielders": ["BRM Taylor"], "kind": "caught", "player_out": "GC Smith"}}}, {"7.6": {"batsman": "CA Ingram", "bowler": "SW Masakadza", "runs": {"batsman": 0, "total": 0, "extras": 0}, "non_striker": "HM Amla"}}, {"8.1": {"batsman": "HM Amla", "bowler": "E Chigumbura", "runs": {"batsman": 4, "total": 4, "extras": 0}, "non_striker": "CA Ingram"}}, {"8.2": {"batsman": "HM Amla", "bowler": "E Chigumbura", "runs": {"batsman": 1, "total": 1, "extras": 0}, "non_striker": "CA Ingram"}}, {"8.3": {"batsman": "CA Ingram", "bowler": "E Chigumbura", "runs": {"batsman": 0, "total": 0, "extras": 0}, "non_striker": "HM Amla"}}, {"8.4": {"batsman": "CA Ingram", "bowler": "E Chigumbura", "runs": {"batsman": 0, "total": 0, "extras": 0}, "non_striker": "HM Amla"}}, {"8.5": {"batsman": "CA Ingram", "bowler": "E Chigumbura", "runs": {"batsman": 0, "total": 0, "extras": 0}, "non_striker": "HM Amla"}}, {"8.6": {"batsman": "CA Ingram", "bowler": "E Chigumbura", "runs": {"batsman": 1, "total": 1, "extras": 0}, "non_striker": "HM Amla"}}, {"9.1": {"batsman": "CA Ingram", "bowler": "SW Masakadza", "runs": {"batsman": 0, "total": 0, "extras": 0}, "non_striker": "HM Amla"}}, {"9.2": {"batsman": "CA Ingram", "bowler": "SW Masakadza", "runs": {"batsman": 1, "total": 1, "extras": 0}, "non_striker": "HM Amla"}}, {"9.3": {"batsman": "HM Amla", "bowler": "SW Masakadza", "runs": {"batsman": 1, "total": 1, "extras": 0}, "non_striker": "CA Ingram"}}, {"9.4": {"batsman": "CA Ingram", "bowler": "SW Masakadza", "runs": {"batsman": 4, "total": 4, "extras": 0}, "non_striker": "HM Amla"}}, {"9.5": {"batsman": "CA Ingram", "bowler": "SW Masakadza", "runs": {"batsman": 0, "total": 0, "extras": 0}, "non_striker": "HM Amla"}}, {"9.6": {"batsman": "CA Ingram", "bowler": "SW Masakadza", "runs": {"batsman": 1, "total": 1, "extras": 0}, "non_striker": "HM Amla"}}, {"10.1": {"batsman": "CA Ingram", "bowler": "E Chigumbura", "runs": {"batsman": 0, "total": 1, "extras": 1}, "extras": {"wides": 1}, "non_striker": "HM Amla"}}, {"10.2": {"batsman": "CA Ingram", "bowler": "E Chigumbura", "runs": {"batsman": 0, "total": 0, "extras": 0}, "non_striker": "HM Amla"}}, {"10.3": {"batsman": "CA Ingram", "bowler": "E Chigumbura", "runs": {"batsman": 2, "total": 2, "extras": 0}, "non_striker": "HM Amla"}}, {"10.4": {"batsman": "CA Ingram", "bowler": "E Chigumbura", "runs": {"batsman": 1, "total": 1, "extras": 0}, "non_striker": "HM Amla"}}, {"10.5": {"batsman": "HM Amla", "bowler": "E Chigumbura", "runs": {"batsman": 2, "total": 2, "extras": 0}, "non_striker": "CA Ingram"}}, {"10.6": {"batsman": "HM Amla", "bowler": "E Chigumbura", "runs": {"batsman": 4, "total": 4, "extras": 0}, "non_striker": "CA Ingram"}}, {"10.7": {"batsman": "HM Amla", "bowler": "E Chigumbura", "runs": {"batsman": 0, "total": 0, "extras": 0}, "non_striker": "CA Ingram"}}, {"11.1": {"batsman": "CA Ingram", "bowler": "SW Masakadza", "runs": {"batsman": 0, "total": 0, "extras": 0}, "non_striker": "HM Amla"}}, {"11.2": {"batsman": "CA Ingram", "bowler": "SW Masakadza", "runs": {"batsman": 1, "total": 1, "extras": 0}, "non_striker": "HM Amla"}}, {"11.3": {"batsman": "HM Amla", "bowler": "SW Masakadza", "runs": {"batsman": 1, "total": 1, "extras": 0}, "non_striker": "CA Ingram"}}, {"11.4": {"batsman": "CA Ingram", "bowler": "SW Masakadza", "runs": {"batsman": 0, "total": 0, "extras": 0}, "non_striker": "HM Amla"}}, {"11.5": {"batsman": "CA Ingram", "bowler": "SW Masakadza", "runs": {"batsman": 0, "total": 0, "extras": 0}, "non_striker": "HM Amla"}}, {"11.6": {"batsman": "CA Ingram", "bowler": "SW Masakadza", "runs": {"batsman": 0, "total": 0, "extras": 0}, "non_striker": "HM Amla"}}, {"12.1": {"batsman": "HM Amla", "bowler": "E Chigumbura", "runs": {"batsman": 0, "total": 0, "extras": 0}, "non_striker": "CA Ingram"}}, {"12.2": {"batsman": "HM Amla", "bowler": "E Chigumbura", "runs": {"batsman": 4, "total": 4, "extras": 0}, "non_striker": "CA Ingram"}}, {"12.3": {"batsman": "HM Amla", "bowler": "E Chigumbura", "runs": {"batsman": 1, "total": 1, "extras": 0}, "non_striker": "CA Ingram"}}, {"12.4": {"batsman": "CA Ingram", "bowler": "E Chigumbura", "runs": {"batsman": 0, "total": 0, "extras": 0}, "non_striker": "HM Amla"}}, {"12.5": {"batsman": "CA Ingram", "bowler": "E Chigumbura", "runs": {"batsman": 1, "total": 1, "extras": 0}, "non_striker": "HM Amla"}}, {"12.6": {"batsman": "HM Amla", "bowler": "E Chigumbura", "runs": {"batsman": 1, "total": 1, "extras": 0}, "non_striker": "CA Ingram"}}, {"13.1": {"batsman": "HM Amla", "bowler": "P Utseya", "runs": {"batsman": 1, "total": 1, "extras": 0}, "non_striker": "CA Ingram"}}, {"13.2": {"batsman": "CA Ingram", "bowler": "P Utseya", "runs": {"batsman": 0, "total": 0, "extras": 0}, "non_striker": "HM Amla"}}, {"13.3": {"batsman": "CA Ingram", "bowler": "P Utseya", "runs": {"batsman": 1, "total": 1, "extras": 0}, "non_striker": "HM Amla"}}, {"13.4": {"batsman": "HM Amla", "bowler": "P Utseya", "runs": {"batsman": 1, "total": 1, "extras": 0}, "non_striker": "CA Ingram"}}, {"13.5": {"batsman": "CA Ingram", "bowler": "P Utseya", "runs": {"batsman": 0, "total": 0, "extras": 0}, "non_striker": "HM Amla"}}, {"13.6": {"batsman": "CA Ingram", "bowler": "P Utseya", "runs": {"batsman": 1, "total": 1, "extras": 0}, "non_striker": "HM Amla"}}, {"14.1": {"batsman": "CA Ingram", "bowler": "E Chigumbura", "runs": {"batsman": 0, "total": 1, "extras": 1}, "extras": {"wides": 1}, "non_striker": "HM Amla"}}, {"14.2": {"batsman": "CA Ingram", "bowler": "E Chigumbura", "runs": {"batsman": 1, "total": 1, "extras": 0}, "non_striker": "HM Amla"}}, {"14.3": {"batsman": "HM Amla", "bowler": "E Chigumbura", "runs": {"batsman": 1, "total": 1, "extras": 0}, "non_striker": "CA Ingram"}}, {"14.4": {"batsman": "CA Ingram", "bowler": "E Chigumbura", "runs": {"batsman": 0, "total": 1, "extras": 1}, "extras": {"wides": 1}, "non_striker": "HM Amla"}}, {"14.5": {"batsman": "CA Ingram", "bowler": "E Chigumbura", "runs": {"batsman": 0, "total": 0, "extras": 0}, "non_striker": "HM Amla"}}, {"14.6": {"batsman": "CA Ingram", "bowler": "E Chigumbura", "runs": {"batsman": 0, "total": 0, "extras": 0}, "non_striker": "HM Amla"}}, {"14.7": {"batsman": "CA Ingram", "bowler": "E Chigumbura", "runs": {"batsman": 1, "total": 1, "extras": 0}, "non_striker": "HM Amla"}}, {"14.8": {"batsman": "HM Amla", "bowler": "E Chigumbura", "runs": {"batsman": 1, "total": 1, "extras": 0}, "non_striker": "CA Ingram"}}, {"15.1": {"batsman": "HM Amla", "bowler": "P Utseya", "runs": {"batsman": 0, "total": 0, "extras": 0}, "non_striker": "CA Ingram"}}, {"15.2": {"batsman": "HM Amla", "bowler": "P Utseya", "runs": {"batsman": 1, "total": 1, "extras": 0}, "non_striker": "CA Ingram"}}, {"15.3": {"batsman": "CA Ingram", "bowler": "P Utseya", "runs": {"batsman": 4, "total": 4, "extras": 0}, "non_striker": "HM Amla"}}, {"15.4": {"batsman": "CA Ingram", "bowler": "P Utseya", "runs": {"batsman": 0, "total": 0, "extras": 0}, "non_striker": "HM Amla"}}, {"15.5": {"batsman": "CA Ingram", "bowler": "P Utseya", "runs": {"batsman": 0, "total": 1, "extras": 1}, "extras": {"legbyes": 1}, "non_striker": "HM Amla"}}, {"15.6": {"batsman": "HM Amla", "bowler": "P Utseya", "runs": {"batsman": 1, "total": 1, "extras": 0}, "non_striker": "CA Ingram"}}, {"16.1": {"batsman": "HM Amla", "bowler": "AG Cremer", "runs": {"batsman": 0, "total": 0, "extras": 0}, "non_striker": "CA Ingram"}}, {"16.2": {"batsman": "HM Amla", "bowler": "AG Cremer", "runs": {"batsman": 0, "total": 0, "extras": 0}, "non_striker": "CA Ingram"}}, {"16.3": {"batsman": "HM Amla", "bowler": "AG Cremer", "runs": {"batsman": 0, "total": 0, "extras": 0}, "non_striker": "CA Ingram"}}, {"16.4": {"batsman": "HM Amla", "bowler": "AG Cremer", "runs": {"batsman": 1, "total": 1, "extras": 0}, "non_striker": "CA Ingram"}}, {"16.5": {"batsman": "CA Ingram", "bowler": "AG Cremer", "runs": {"batsman": 1, "total": 1, "extras": 0}, "non_striker": "HM Amla"}}, {"16.6": {"batsman": "HM Amla", "bowler": "AG Cremer", "runs": {"batsman": 1, "total": 1, "extras": 0}, "non_striker": "CA Ingram"}}, {"17.1": {"batsman": "HM Amla", "bowler": "P Utseya", "runs": {"batsman": 0, "total": 0, "extras": 0}, "non_striker": "CA Ingram"}}, {"17.2": {"batsman": "HM Amla", "bowler": "P Utseya", "runs": {"batsman": 1, "total": 1, "extras": 0}, "non_striker": "CA Ingram"}}, {"17.3": {"batsman": "CA Ingram", "bowler": "P Utseya", "runs": {"batsman": 1, "total": 1, "extras": 0}, "non_striker": "HM Amla"}}, {"17.4": {"batsman": "HM Amla", "bowler": "P Utseya", "runs": {"batsman": 1, "total": 1, "extras": 0}, "non_striker": "CA Ingram"}}, {"17.5": {"batsman": "CA Ingram", "bowler": "P Utseya", "runs": {"batsman": 1, "total": 1, "extras": 0}, "non_striker": "HM Amla"}}, {"17.6": {"batsman": "HM Amla", "bowler": "P Utseya", "runs": {"batsman": 1, "total": 1, "extras": 0}, "non_striker": "CA Ingram"}}, {"18.1": {"batsman": "HM Amla", "bowler": "AG Cremer", "runs": {"batsman": 0, "total": 0, "extras": 0}, "non_striker": "CA Ingram"}}, {"18.2": {"batsman": "HM Amla", "bowler": "AG Cremer", "runs": {"batsman": 1, "total": 1, "extras": 0}, "non_striker": "CA Ingram"}}, {"18.3": {"batsman": "CA Ingram", "bowler": "AG Cremer", "runs": {"batsman": 1, "total": 1, "extras": 0}, "non_striker": "HM Amla"}}, {"18.4": {"batsman": "HM Amla", "bowler": "AG Cremer", "runs": {"batsman": 2, "total": 2, "extras": 0}, "non_striker": "CA Ingram"}}, {"18.5": {"batsman": "HM Amla", "bowler": "AG Cremer", "runs": {"batsman": 1, "total": 1, "extras": 0}, "non_striker": "CA Ingram"}}, {"18.6": {"batsman": "CA Ingram", "bowler": "AG Cremer", "runs": {"batsman": 1, "total": 1, "extras": 0}, "non_striker": "HM Amla"}}, {"19.1": {"batsman": "CA Ingram", "bowler": "P Utseya", "runs": {"batsman": 2, "total": 2, "extras": 0}, "non_striker": "HM Amla"}}, {"19.2": {"batsman": "CA Ingram", "bowler": "P Utseya", "runs": {"batsman": 0, "total": 0, "extras": 0}, "non_striker": "HM Amla"}}, {"19.3": {"batsman": "CA Ingram", "bowler": "P Utseya", "runs": {"batsman": 0, "total": 1, "extras": 1}, "extras": {"wides": 1}, "non_striker": "HM Amla"}}, {"19.4": {"batsman": "CA Ingram", "bowler": "P Utseya", "runs": {"batsman": 1, "total": 1, "extras": 0}, "non_striker": "HM Amla"}}, {"19.5": {"batsman": "HM Amla", "bowler": "P Utseya", "runs": {"batsman": 1, "total": 1, "extras": 0}, "non_striker": "CA Ingram"}}, {"19.6": {"batsman": "CA Ingram", "bowler": "P Utseya", "runs": {"batsman": 0, "total": 0, "extras": 0}, "non_striker": "HM Amla"}}, {"19.7": {"batsman": "CA Ingram", "bowler": "P Utseya", "runs": {"batsman": 1, "total": 1, "extras": 0}, "non_striker": "HM Amla"}}, {"20.1": {"batsman": "CA Ingram", "bowler": "AG Cremer", "runs": {"batsman": 2, "total": 2, "extras": 0}, "non_striker": "HM Amla"}}, {"20.2": {"batsman": "CA Ingram", "bowler": "AG Cremer", "runs": {"batsman": 0, "total": 0, "extras": 0}, "non_striker": "HM Amla"}}, {"20.3": {"batsman": "CA Ingram", "bowler": "AG Cremer", "runs": {"batsman": 1, "total": 1, "extras": 0}, "non_striker": "HM Amla"}}, {"20.4": {"batsman": "HM Amla", "bowler": "AG Cremer", "runs": {"batsman": 0, "total": 0, "extras": 0}, "non_striker": "CA Ingram"}}, {"20.5": {"batsman": "HM Amla", "bowler": "AG Cremer", "runs": {"batsman": 0, "total": 0, "extras": 0}, "non_striker": "CA Ingram"}}, {"20.6": {"batsman": "HM Amla", "bowler": "AG Cremer", "runs": {"batsman": 4, "total": 4, "extras": 0}, "non_striker": "CA Ingram"}}, {"21.1": {"batsman": "CA Ingram", "bowler": "P Utseya", "runs": {"batsman": 1, "total": 1, "extras": 0}, "non_striker": "HM Amla"}}, {"21.2": {"batsman": "HM Amla", "bowler": "P Utseya", "runs": {"batsman": 4, "total": 4, "extras": 0}, "non_striker": "CA Ingram"}}, {"21.3": {"batsman": "HM Amla", "bowler": "P Utseya", "runs": {"batsman": 1, "total": 1, "extras": 0}, "non_striker": "CA Ingram"}}, {"21.4": {"batsman": "CA Ingram", "bowler": "P Utseya", "runs": {"batsman": 1, "total": 1, "extras": 0}, "non_striker": "HM Amla"}}, {"21.5": {"batsman": "HM Amla", "bowler": "P Utseya", "runs": {"batsman": 1, "total": 1, "extras": 0}, "non_striker": "CA Ingram"}}, {"21.6": {"batsman": "CA Ingram", "bowler": "P Utseya", "runs": {"batsman": 0, "total": 0, "extras": 0}, "non_striker": "HM Amla"}}, {"22.1": {"batsman": "HM Amla", "bowler": "AG Cremer", "runs": {"batsman": 1, "total": 1, "extras": 0}, "non_striker": "CA Ingram"}}, {"22.2": {"batsman": "CA Ingram", "bowler": "AG Cremer", "runs": {"batsman": 2, "total": 2, "extras": 0}, "non_striker": "HM Amla"}}, {"22.3": {"batsman": "CA Ingram", "bowler": "AG Cremer", "runs": {"batsman": 0, "total": 1, "extras": 1}, "extras": {"legbyes": 1}, "non_striker": "HM Amla"}}, {"22.4": {"batsman": "HM Amla", "bowler": "AG Cremer", "runs": {"batsman": 0, "total": 0, "extras": 0}, "non_striker": "CA Ingram"}}, {"22.5": {"batsman": "HM Amla", "bowler": "AG Cremer", "runs": {"batsman": 1, "total": 1, "extras": 0}, "non_striker": "CA Ingram"}}, {"22.6": {"batsman": "CA Ingram", "bowler": "AG Cremer", "runs": {"batsman": 0, "total": 0, "extras": 0}, "non_striker": "HM Amla"}}, {"23.1": {"batsman": "HM Amla", "bowler": "GW Flower", "runs": {"batsman": 2, "total": 2, "extras": 0}, "non_striker": "CA Ingram"}}, {"23.2": {"batsman": "HM Amla", "bowler": "GW Flower", "runs": {"batsman": 0, "total": 0, "extras": 0}, "non_striker": "CA Ingram"}}, {"23.3": {"batsman": "HM Amla", "bowler": "GW Flower", "runs": {"batsman": 1, "total": 1, "extras": 0}, "non_striker": "CA Ingram"}}, {"23.4": {"batsman": "CA Ingram", "bowler": "GW Flower", "runs": {"batsman": 1, "total": 1, "extras": 0}, "non_striker": "HM Amla"}}, {"23.5": {"batsman": "HM Amla", "bowler": "GW Flower", "runs": {"batsman": 1, "total": 1, "extras": 0}, "non_striker": "CA Ingram"}}, {"23.6": {"batsman": "CA Ingram", "bowler": "GW Flower", "runs": {"batsman": 0, "total": 0, "extras": 0}, "non_striker": "HM Amla"}}, {"24.1": {"batsman": "HM Amla", "bowler": "AG Cremer", "runs": {"batsman": 1, "total": 1, "extras": 0}, "non_striker": "CA Ingram"}}, {"24.2": {"batsman": "CA Ingram", "bowler": "AG Cremer", "runs": {"batsman": 3, "total": 3, "extras": 0}, "non_striker": "HM Amla"}}, {"24.3": {"batsman": "HM Amla", "bowler": "AG Cremer", "runs": {"batsman": 0, "total": 0, "extras": 0}, "non_striker": "CA Ingram"}}, {"24.4": {"batsman": "HM Amla", "bowler": "AG Cremer", "runs": {"batsman": 0, "total": 0, "extras": 0}, "non_striker": "CA Ingram"}}, {"24.5": {"batsman": "HM Amla", "bowler": "AG Cremer", "runs": {"batsman": 1, "total": 1, "extras": 0}, "non_striker": "CA Ingram"}}, {"24.6": {"batsman": "CA Ingram", "bowler": "AG Cremer", "runs": {"batsman": 1, "total": 1, "extras": 0}, "non_striker": "HM Amla"}}, {"25.1": {"batsman": "CA Ingram", "bowler": "GW Flower", "runs": {"batsman": 1, "total": 1, "extras": 0}, "non_striker": "HM Amla"}}, {"25.2": {"batsman": "HM Amla", "bowler": "GW Flower", "runs": {"batsman": 1, "total": 1, "extras": 0}, "non_striker": "CA Ingram"}}, {"25.3": {"batsman": "CA Ingram", "bowler": "GW Flower", "runs": {"batsman": 1, "total": 1, "extras": 0}, "non_striker": "HM Amla"}}, {"25.4": {"batsman": "HM Amla", "bowler": "GW Flower", "runs": {"batsman": 0, "total": 0, "extras": 0}, "non_striker": "CA Ingram"}}, {"25.5": {"batsman": "HM Amla", "bowler": "GW Flower", "runs": {"batsman": 1, "total": 1, "extras": 0}, "non_striker": "CA Ingram"}}, {"25.6": {"batsman": "CA Ingram", "bowler": "GW Flower", "runs": {"batsman": 1, "total": 1, "extras": 0}, "non_striker": "HM Amla"}}, {"26.1": {"batsman": "CA Ingram", "bowler": "AG Cremer", "runs": {"batsman": 0, "total": 0, "extras": 0}, "non_striker": "HM Amla"}}, {"26.2": {"batsman": "CA Ingram", "bowler": "AG Cremer", "runs": {"batsman": 1, "total": 1, "extras": 0}, "non_striker": "HM Amla"}}, {"26.3": {"batsman": "HM Amla", "bowler": "AG Cremer", "runs": {"batsman": 1, "total": 1, "extras": 0}, "non_striker": "CA Ingram"}}, {"26.4": {"batsman": "CA Ingram", "bowler": "AG Cremer", "runs": {"batsman": 1, "total": 1, "extras": 0}, "non_striker": "HM Amla"}}, {"26.5": {"batsman": "HM Amla", "bowler": "AG Cremer", "runs": {"batsman": 0, "total": 0, "extras": 0}, "non_striker": "CA Ingram"}}, {"26.6": {"batsman": "HM Amla", "bowler": "AG Cremer", "runs": {"batsman": 0, "total": 0, "extras": 0}, "non_striker": "CA Ingram"}}, {"27.1": {"batsman": "CA Ingram", "bowler": "GW Flower", "runs": {"batsman": 1, "total": 1, "extras": 0}, "non_striker": "HM Amla"}}, {"27.2": {"batsman": "HM Amla", "bowler": "GW Flower", "runs": {"batsman": 2, "total": 2, "extras": 0}, "non_striker": "CA Ingram"}}, {"27.3": {"batsman": "HM Amla", "bowler": "GW Flower", "runs": {"batsman": 1, "total": 1, "extras": 0}, "non_striker": "CA Ingram"}}, {"27.4": {"batsman": "CA Ingram", "bowler": "GW Flower", "runs": {"batsman": 1, "total": 1, "extras": 0}, "non_striker": "HM Amla"}}, {"27.5": {"batsman": "HM Amla", "bowler": "GW Flower", "runs": {"batsman": 0, "total": 0, "extras": 0}, "non_striker": "CA Ingram"}}, {"27.6": {"batsman": "HM Amla", "bowler": "GW Flower", "runs": {"batsman": 0, "total": 0, "extras": 0}, "non_striker": "CA Ingram"}}, {"28.1": {"batsman": "CA Ingram", "bowler": "AG Cremer", "runs": {"batsman": 0, "total": 0, "extras": 0}, "non_striker": "HM Amla"}}, {"28.2": {"batsman": "CA Ingram", "bowler": "AG Cremer", "runs": {"batsman": 1, "total": 1, "extras": 0}, "non_striker": "HM Amla"}}, {"28.3": {"batsman": "HM Amla", "bowler": "AG Cremer", "runs": {"batsman": 4, "total": 4, "extras": 0}, "non_striker": "CA Ingram"}}, {"28.4": {"batsman": "HM Amla", "bowler": "AG Cremer", "runs": {"batsman": 1, "total": 1, "extras": 0}, "non_striker": "CA Ingram"}}, {"28.5": {"batsman": "CA Ingram", "bowler": "AG Cremer", "runs": {"batsman": 1, "total": 1, "extras": 0}, "non_striker": "HM Amla"}}, {"28.6": {"batsman": "HM Amla", "bowler": "AG Cremer", "runs": {"batsman": 1, "total": 1, "extras": 0}, "non_striker": "CA Ingram"}}, {"29.1": {"batsman": "HM Amla", "bowler": "GW Flower", "runs": {"batsman": 1, "total": 1, "extras": 0}, "non_striker": "CA Ingram"}}, {"29.2": {"batsman": "CA Ingram", "bowler": "GW Flower", "runs": {"batsman": 1, "total": 1, "extras": 0}, "non_striker": "HM Amla"}}, {"29.3": {"batsman": "HM Amla", "bowler": "GW Flower", "runs": {"batsman": 0, "total": 0, "extras": 0}, "non_striker": "CA Ingram"}}, {"29.4": {"batsman": "HM Amla", "bowler": "GW Flower", "runs": {"batsman": 1, "total": 1, "extras": 0}, "non_striker": "CA Ingram"}}, {"29.5": {"batsman": "CA Ingram", "bowler": "GW Flower", "runs": {"batsman": 4, "total": 4, "extras": 0}, "non_striker": "HM Amla"}}, {"29.6": {"batsman": "CA Ingram", "bowler": "GW Flower", "runs": {"batsman": 1, "total": 1, "extras": 0}, "non_striker": "HM Amla"}}, {"30.1": {"batsman": "CA Ingram", "bowler": "CB Mpofu", "runs": {"batsman": 1, "total": 1, "extras": 0}, "non_striker": "HM Amla"}}, {"30.2": {"batsman": "HM Amla", "bowler": "CB Mpofu", "runs": {"batsman": 0, "total": 0, "extras": 0}, "non_striker": "CA Ingram"}}, {"30.3": {"batsman": "HM Amla", "bowler": "CB Mpofu", "runs": {"batsman": 1, "total": 1, "extras": 0}, "non_striker": "CA Ingram"}}, {"30.4": {"batsman": "CA Ingram", "bowler": "CB Mpofu", "runs": {"batsman": 0, "total": 0, "extras": 0}, "non_striker": "HM Amla"}}, {"30.5": {"batsman": "CA Ingram", "bowler": "CB Mpofu", "runs": {"batsman": 0, "total": 0, "extras": 0}, "non_striker": "HM Amla"}}, {"30.6": {"batsman": "CA Ingram", "bowler": "CB Mpofu", "runs": {"batsman": 1, "total": 1, "extras": 0}, "non_striker": "HM Amla"}}, {"31.1": {"batsman": "CA Ingram", "bowler": "SC Williams", "runs": {"batsman": 1, "total": 1, "extras": 0}, "non_striker": "HM Amla"}}, {"31.2": {"batsman": "HM Amla", "bowler": "SC Williams", "runs": {"batsman": 2, "total": 2, "extras": 0}, "non_striker": "CA Ingram"}}, {"31.3": {"batsman": "HM Amla", "bowler": "SC Williams", "runs": {"batsman": 0, "total": 1, "extras": 1}, "extras": {"wides": 1}, "non_striker": "CA Ingram"}}, {"31.4": {"batsman": "HM Amla", "bowler": "SC Williams", "runs": {"batsman": 0, "total": 0, "extras": 0}, "non_striker": "CA Ingram", "wicket": {"fielders": ["P Utseya", "SC Williams"], "kind": "run out", "player_out": "HM Amla"}}}, {"31.5": {"batsman": "CA Ingram", "bowler": "SC Williams", "runs": {"batsman": 0, "total": 0, "extras": 0}, "non_striker": "AB de Villiers"}}, {"31.6": {"batsman": "CA Ingram", "bowler": "SC Williams", "runs": {"batsman": 0, "total": 0, "extras": 0}, "non_striker": "AB de Villiers"}}, {"31.7": {"batsman": "CA Ingram", "bowler": "SC Williams", "runs": {"batsman": 1, "total": 1, "extras": 0}, "non_striker": "AB de Villiers"}}, {"32.1": {"batsman": "CA Ingram", "bowler": "CB Mpofu", "runs": {"batsman": 4, "total": 4, "extras": 0}, "non_striker": "AB de Villiers"}}, {"32.2": {"batsman": "CA Ingram", "bowler": "CB Mpofu", "runs": {"batsman": 1, "total": 1, "extras": 0}, "non_striker": "AB de Villiers"}}, {"32.3": {"batsman": "AB de Villiers", "bowler": "CB Mpofu", "runs": {"batsman": 1, "total": 1, "extras": 0}, "non_striker": "CA Ingram"}}, {"32.4": {"batsman": "CA Ingram", "bowler": "CB Mpofu", "runs": {"batsman": 0, "total": 0, "extras": 0}, "non_striker": "AB de Villiers"}}, {"32.5": {"batsman": "CA Ingram", "bowler": "CB Mpofu", "runs": {"batsman": 0, "total": 0, "extras": 0}, "non_striker": "AB de Villiers"}}, {"32.6": {"batsman": "CA Ingram", "bowler": "CB Mpofu", "runs": {"batsman": 1, "total": 1, "extras": 0}, "non_striker": "AB de Villiers"}}, {"33.1": {"batsman": "CA Ingram", "bowler": "SC Williams", "runs": {"batsman": 2, "total": 2, "extras": 0}, "non_striker": "AB de Villiers"}}, {"33.2": {"batsman": "CA Ingram", "bowler": "SC Williams", "runs": {"batsman": 1, "total": 1, "extras": 0}, "non_striker": "AB de Villiers"}}, {"33.3": {"batsman": "AB de Villiers", "bowler": "SC Williams", "runs": {"batsman": 1, "total": 1, "extras": 0}, "non_striker": "CA Ingram"}}, {"33.4": {"batsman": "CA Ingram", "bowler": "SC Williams", "runs": {"batsman": 0, "total": 0, "extras": 0}, "non_striker": "AB de Villiers"}}, {"33.5": {"batsman": "CA Ingram", "bowler": "SC Williams", "runs": {"batsman": 1, "total": 1, "extras": 0}, "non_striker": "AB de Villiers"}}, {"33.6": {"batsman": "AB de Villiers", "bowler": "SC Williams", "runs": {"batsman": 4, "total": 4, "extras": 0}, "non_striker": "CA Ingram"}}, {"34.1": {"batsman": "CA Ingram", "bowler": "P Utseya", "runs": {"batsman": 1, "total": 1, "extras": 0}, "non_striker": "AB de Villiers"}}, {"34.2": {"batsman": "AB de Villiers", "bowler": "P Utseya", "runs": {"batsman": 0, "total": 0, "extras": 0}, "non_striker": "CA Ingram"}}, {"34.3": {"batsman": "AB de Villiers", "bowler": "P Utseya", "runs": {"batsman": 1, "total": 1, "extras": 0}, "non_striker": "CA Ingram"}}, {"34.4": {"batsman": "CA Ingram", "bowler": "P Utseya", "runs": {"batsman": 0, "total": 0, "extras": 0}, "non_striker": "AB de Villiers"}}, {"34.5": {"batsman": "CA Ingram", "bowler": "P Utseya", "runs": {"batsman": 1, "total": 1, "extras": 0}, "non_striker": "AB de Villiers"}}, {"34.6": {"batsman": "AB de Villiers", "bowler": "P Utseya", "runs": {"batsman": 1, "total": 1, "extras": 0}, "non_striker": "CA Ingram"}}, {"35.1": {"batsman": "AB de Villiers", "bowler": "AG Cremer", "runs": {"batsman": 1, "total": 1, "extras": 0}, "non_striker": "CA Ingram"}}, {"35.2": {"batsman": "CA Ingram", "bowler": "AG Cremer", "runs": {"batsman": 1, "total": 1, "extras": 0}, "non_striker": "AB de Villiers"}}, {"35.3": {"batsman": "AB de Villiers", "bowler": "AG Cremer", "runs": {"batsman": 0, "total": 0, "extras": 0}, "non_striker": "CA Ingram"}}, {"35.4": {"batsman": "AB de Villiers", "bowler": "AG Cremer", "runs": {"batsman": 2, "total": 2, "extras": 0}, "non_striker": "CA Ingram"}}, {"35.5": {"batsman": "AB de Villiers", "bowler": "AG Cremer", "runs": {"batsman": 3, "total": 3, "extras": 0}, "non_striker": "CA Ingram"}}, {"35.6": {"batsman": "CA Ingram", "bowler": "AG Cremer", "runs": {"batsman": 1, "total": 1, "extras": 0}, "non_striker": "AB de Villiers"}}, {"36.1": {"batsman": "CA Ingram", "bowler": "P Utseya", "runs": {"batsman": 0, "total": 0, "extras": 0}, "non_striker": "AB de Villiers"}}, {"36.2": {"batsman": "CA Ingram", "bowler": "P Utseya", "runs": {"batsman": 1, "total": 1, "extras": 0}, "non_striker": "AB de Villiers"}}, {"36.3": {"batsman": "AB de Villiers", "bowler": "P Utseya", "runs": {"batsman": 4, "total": 4, "extras": 0}, "non_striker": "CA Ingram"}}, {"36.4": {"batsman": "AB de Villiers", "bowler": "P Utseya", "runs": {"batsman": 0, "total": 0, "extras": 0}, "non_striker": "CA Ingram"}}, {"36.5": {"batsman": "AB de Villiers", "bowler": "P Utseya", "runs": {"batsman": 1, "total": 1, "extras": 0}, "non_striker": "CA Ingram"}}, {"36.6": {"batsman": "CA Ingram", "bowler": "P Utseya", "runs": {"batsman": 0, "total": 0, "extras": 0}, "non_striker": "AB de Villiers"}}, {"37.1": {"batsman": "AB de Villiers", "bowler": "AG Cremer", "runs": {"batsman": 1, "total": 1, "extras": 0}, "non_striker": "CA Ingram"}}, {"37.2": {"batsman": "CA Ingram", "bowler": "AG Cremer", "runs": {"batsman": 0, "total": 0, "extras": 0}, "non_striker": "AB de Villiers"}}, {"37.3": {"batsman": "CA Ingram", "bowler": "AG Cremer", "runs": {"batsman": 1, "total": 1, "extras": 0}, "non_striker": "AB de Villiers"}}, {"37.4": {"batsman": "AB de Villiers", "bowler": "AG Cremer", "runs": {"batsman": 0, "total": 1, "extras": 1}, "extras": {"wides": 1}, "non_striker": "CA Ingram"}}, {"37.5": {"batsman": "AB de Villiers", "bowler": "AG Cremer", "runs": {"batsman": 0, "total": 0, "extras": 0}, "non_striker": "CA Ingram"}}, {"37.6": {"batsman": "AB de Villiers", "bowler": "AG Cremer", "runs": {"batsman": 1, "total": 1, "extras": 0}, "non_striker": "CA Ingram"}}, {"37.7": {"batsman": "CA Ingram", "bowler": "AG Cremer", "runs": {"batsman": 1, "total": 1, "extras": 0}, "non_striker": "AB de Villiers"}}, {"38.1": {"batsman": "CA Ingram", "bowler": "P Utseya", "runs": {"batsman": 0, "total": 0, "extras": 0}, "non_striker": "AB de Villiers"}}, {"38.2": {"batsman": "CA Ingram", "bowler": "P Utseya", "runs": {"batsman": 0, "total": 0, "extras": 0}, "non_striker": "AB de Villiers", "wicket": {"fielders": ["AG Cremer"], "kind": "run out", "player_out": "AB de Villiers"}}}, {"38.3": {"batsman": "JA Morkel", "bowler": "P Utseya", "runs": {"batsman": 0, "total": 0, "extras": 0}, "non_striker": "CA Ingram"}}, {"38.4": {"batsman": "JA Morkel", "bowler": "P Utseya", "runs": {"batsman": 1, "total": 1, "extras": 0}, "non_striker": "CA Ingram"}}, {"38.5": {"batsman": "CA Ingram", "bowler": "P Utseya", "runs": {"batsman": 1, "total": 1, "extras": 0}, "non_striker": "JA Morkel"}}, {"38.6": {"batsman": "JA Morkel", "bowler": "P Utseya", "runs": {"batsman": 0, "total": 0, "extras": 0}, "non_striker": "CA Ingram"}}, {"39.1": {"batsman": "CA Ingram", "bowler": "SW Masakadza", "runs": {"batsman": 4, "total": 4, "extras": 0}, "non_striker": "JA Morkel"}}, {"39.2": {"batsman": "CA Ingram", "bowler": "SW Masakadza", "runs": {"batsman": 0, "total": 0, "extras": 0}, "non_striker": "JA Morkel"}}, {"39.3": {"batsman": "CA Ingram", "bowler": "SW Masakadza", "runs": {"batsman": 2, "total": 2, "extras": 0}, "non_striker": "JA Morkel"}}, {"39.4": {"batsman": "CA Ingram", "bowler": "SW Masakadza", "runs": {"batsman": 6, "total": 6, "extras": 0}, "non_striker": "JA Morkel"}}, {"39.5": {"batsman": "CA Ingram", "bowler": "SW Masakadza", "runs": {"batsman": 1, "total": 1, "extras": 0}, "non_striker": "JA Morkel"}}, {"39.6": {"batsman": "JA Morkel", "bowler": "SW Masakadza", "runs": {"batsman": 0, "total": 0, "extras": 0}, "non_striker": "CA Ingram", "wicket": {"fielders": ["P Utseya"], "kind": "caught", "player_out": "JA Morkel"}}}, {"40.1": {"batsman": "CA Ingram", "bowler": "P Utseya", "runs": {"batsman": 0, "total": 0, "extras": 0}, "non_striker": "DA Miller"}}, {"40.2": {"batsman": "CA Ingram", "bowler": "P Utseya", "runs": {"batsman": 1, "total": 1, "extras": 0}, "non_striker": "DA Miller"}}, {"40.3": {"batsman": "DA Miller", "bowler": "P Utseya", "runs": {"batsman": 0, "total": 0, "extras": 0}, "non_striker": "CA Ingram"}}, {"40.4": {"batsman": "DA Miller", "bowler": "P Utseya", "runs": {"batsman": 0, "total": 0, "extras": 0}, "non_striker": "CA Ingram"}}, {"40.5": {"batsman": "DA Miller", "bowler": "P Utseya", "runs": {"batsman": 1, "total": 1, "extras": 0}, "non_striker": "CA Ingram"}}, {"40.6": {"batsman": "CA Ingram", "bowler": "P Utseya", "runs": {"batsman": 4, "total": 4, "extras": 0}, "non_striker": "DA Miller"}}, {"41.1": {"batsman": "DA Miller", "bowler": "SW Masakadza", "runs": {"batsman": 4, "total": 4, "extras": 0}, "non_striker": "CA Ingram"}}, {"41.2": {"batsman": "DA Miller", "bowler": "SW Masakadza", "runs": {"batsman": 4, "total": 4, "extras": 0}, "non_striker": "CA Ingram"}}, {"41.3": {"batsman": "DA Miller", "bowler": "SW Masakadza", "runs": {"batsman": 0, "total": 0, "extras": 0}, "non_striker": "CA Ingram"}}, {"41.4": {"batsman": "DA Miller", "bowler": "SW Masakadza", "runs": {"batsman": 1, "total": 1, "extras": 0}, "non_striker": "CA Ingram"}}, {"41.5": {"batsman": "CA Ingram", "bowler": "SW Masakadza", "runs": {"batsman": 3, "total": 3, "extras": 0}, "non_striker": "DA Miller"}}, {"41.6": {"batsman": "DA Miller", "bowler": "SW Masakadza", "runs": {"batsman": 1, "total": 1, "extras": 0}, "non_striker": "CA Ingram"}}, {"42.1": {"batsman": "DA Miller", "bowler": "CB Mpofu", "runs": {"batsman": 0, "total": 0, "extras": 0}, "non_striker": "CA Ingram"}}, {"42.2": {"batsman": "DA Miller", "bowler": "CB Mpofu", "runs": {"batsman": 1, "total": 1, "extras": 0}, "non_striker": "CA Ingram"}}, {"42.3": {"batsman": "CA Ingram", "bowler": "CB Mpofu", "runs": {"batsman": 0, "total": 0, "extras": 0}, "non_striker": "DA Miller"}}, {"42.4": {"batsman": "CA Ingram", "bowler": "CB Mpofu", "runs": {"batsman": 1, "total": 1, "extras": 0}, "non_striker": "DA Miller"}}, {"42.5": {"batsman": "DA Miller", "bowler": "CB Mpofu", "runs": {"batsman": 1, "total": 1, "extras": 0}, "non_striker": "CA Ingram"}}, {"42.6": {"batsman": "CA Ingram", "bowler": "CB Mpofu", "runs": {"batsman": 2, "total": 2, "extras": 0}, "non_striker": "DA Miller"}}, {"43.1": {"batsman": "DA Miller", "bowler": "P Utseya", "runs": {"batsman": 0, "total": 0, "extras": 0}, "non_striker": "CA Ingram"}}, {"43.2": {"batsman": "DA Miller", "bowler": "P Utseya", "runs": {"batsman": 0, "total": 0, "extras": 0}, "non_striker": "CA Ingram"}}, {"43.3": {"batsman": "DA Miller", "bowler": "P Utseya", "runs": {"batsman": 1, "total": 1, "extras": 0}, "non_striker": "CA Ingram"}}, {"43.4": {"batsman": "CA Ingram", "bowler": "P Utseya", "runs": {"batsman": 0, "total": 0, "extras": 0}, "non_striker": "DA Miller"}}, {"43.5": {"batsman": "CA Ingram", "bowler": "P Utseya", "runs": {"batsman": 0, "total": 0, "extras": 0}, "non_striker": "DA Miller"}}, {"43.6": {"batsman": "CA Ingram", "bowler": "P Utseya", "runs": {"batsman": 0, "total": 1, "extras": 1}, "extras": {"legbyes": 1}, "non_striker": "DA Miller"}}, {"44.1": {"batsman": "CA Ingram", "bowler": "BRM Taylor", "runs": {"batsman": 2, "total": 2, "extras": 0}, "non_striker": "DA Miller"}}, {"44.2": {"batsman": "CA Ingram", "bowler": "BRM Taylor", "runs": {"batsman": 0, "total": 0, "extras": 0}, "non_striker": "DA Miller"}}, {"44.3": {"batsman": "CA Ingram", "bowler": "BRM Taylor", "runs": {"batsman": 2, "total": 2, "extras": 0}, "non_striker": "DA Miller"}}, {"44.4": {"batsman": "CA Ingram", "bowler": "BRM Taylor", "runs": {"batsman": 0, "total": 1, "extras": 1}, "extras": {"legbyes": 1}, "non_striker": "DA Miller"}}, {"44.5": {"batsman": "DA Miller", "bowler": "BRM Taylor", "runs": {"batsman": 1, "total": 1, "extras": 0}, "non_striker": "CA Ingram"}}, {"44.6": {"batsman": "CA Ingram", "bowler": "BRM Taylor", "runs": {"batsman": 4, "total": 4, "extras": 0}, "non_striker": "DA Miller"}}, {"45.1": {"batsman": "DA Miller", "bowler": "AG Cremer", "runs": {"batsman": 6, "total": 6, "extras": 0}, "non_striker": "CA Ingram"}}, {"45.2": {"batsman": "DA Miller", "bowler": "AG Cremer", "runs": {"batsman": 0, "total": 0, "extras": 0}, "non_striker": "CA Ingram"}}, {"45.3": {"batsman": "DA Miller", "bowler": "AG Cremer", "runs": {"batsman": 6, "total": 6, "extras": 0}, "non_striker": "CA Ingram"}}, {"45.4": {"batsman": "DA Miller", "bowler": "AG Cremer", "runs": {"batsman": 1, "total": 1, "extras": 0}, "non_striker": "CA Ingram"}}, {"45.5": {"batsman": "CA Ingram", "bowler": "AG Cremer", "runs": {"batsman": 1, "total": 1, "extras": 0}, "non_striker": "DA Miller"}}, {"45.6": {"batsman": "DA Miller", "bowler": "AG Cremer", "runs": {"batsman": 0, "total": 0, "extras": 0}, "non_striker": "CA Ingram"}}, {"46.1": {"batsman": "CA Ingram", "bowler": "E Chigumbura", "runs": {"batsman": 0, "total": 0, "extras": 0}, "non_striker": "DA Miller"}}, {"46.2": {"batsman": "CA Ingram", "bowler": "E Chigumbura", "runs": {"batsman": 1, "total": 1, "extras": 0}, "non_striker": "DA Miller"}}, {"46.3": {"batsman": "DA Miller", "bowler": "E Chigumbura", "runs": {"batsman": 0, "total": 1, "extras": 1}, "extras": {"wides": 1}, "non_striker": "CA Ingram"}}, {"46.4": {"batsman": "DA Miller", "bowler": "E Chigumbura", "runs": {"batsman": 2, "total": 2, "extras": 0}, "non_striker": "CA Ingram"}}, {"46.5": {"batsman": "DA Miller", "bowler": "E Chigumbura", "runs": {"batsman": 2, "total": 2, "extras": 0}, "non_striker": "CA Ingram"}}, {"46.6": {"batsman": "DA Miller", "bowler": "E Chigumbura", "runs": {"batsman": 4, "total": 4, "extras": 0}, "non_striker": "CA Ingram"}}, {"46.7": {"batsman": "DA Miller", "bowler": "E Chigumbura", "runs": {"batsman": 4, "total": 4, "extras": 0}, "non_striker": "CA Ingram"}}, {"47.1": {"batsman": "CA Ingram", "bowler": "SW Masakadza", "runs": {"batsman": 4, "total": 4, "extras": 0}, "non_striker": "DA Miller"}}, {"47.2": {"batsman": "CA Ingram", "bowler": "SW Masakadza", "runs": {"batsman": 6, "total": 6, "extras": 0}, "non_striker": "DA Miller"}}, {"47.3": {"batsman": "CA Ingram", "bowler": "SW Masakadza", "runs": {"batsman": 2, "total": 2, "extras": 0}, "non_striker": "DA Miller"}}, {"47.4": {"batsman": "CA Ingram", "bowler": "SW Masakadza", "runs": {"batsman": 0, "total": 0, "extras": 0}, "non_striker": "DA Miller", "wicket": {"kind": "bowled", "player_out": "CA Ingram"}}}, {"47.5": {"batsman": "JP Duminy", "bowler": "SW Masakadza", "runs": {"batsman": 1, "total": 1, "extras": 0}, "non_striker": "DA Miller"}}, {"47.6": {"batsman": "DA Miller", "bowler": "SW Masakadza", "runs": {"batsman": 1, "total": 1, "extras": 0}, "non_striker": "JP Duminy"}}, {"48.1": {"batsman": "DA Miller", "bowler": "CB Mpofu", "runs": {"batsman": 2, "total": 2, "extras": 0}, "non_striker": "JP Duminy"}}, {"48.2": {"batsman": "DA Miller", "bowler": "CB Mpofu", "runs": {"batsman": 2, "total": 2, "extras": 0}, "non_striker": "JP Duminy"}}, {"48.3": {"batsman": "DA Miller", "bowler": "CB Mpofu", "runs": {"batsman": 1, "total": 1, "extras": 0}, "non_striker": "JP Duminy"}}, {"48.4": {"batsman": "JP Duminy", "bowler": "CB Mpofu", "runs": {"batsman": 1, "total": 1, "extras": 0}, "non_striker": "DA Miller"}}, {"48.5": {"batsman": "DA Miller", "bowler": "CB Mpofu", "runs": {"batsman": 1, "total": 1, "extras": 0}, "non_striker": "JP Duminy"}}, {"48.6": {"batsman": "JP Duminy", "bowler": "CB Mpofu", "runs": {"batsman": 2, "total": 2, "extras": 0}, "non_striker": "DA Miller"}}, {"49.1": {"batsman": "DA Miller", "bowler": "SW Masakadza", "runs": {"batsman": 4, "total": 4, "extras": 0}, "non_striker": "JP Duminy"}}, {"49.2": {"batsman": "DA Miller", "bowler": "SW Masakadza", "runs": {"batsman": 0, "total": 0, "extras": 0}, "non_striker": "JP Duminy", "wicket": {"kind": "bowled", "player_out": "DA Miller"}}}, {"49.3": {"batsman": "J Botha", "bowler": "SW Masakadza", "runs": {"batsman": 0, "total": 0, "extras": 0}, "non_striker": "JP Duminy"}}, {"49.4": {"batsman": "J Botha", "bowler": "SW Masakadza", "runs": {"batsman": 2, "total": 2, "extras": 0}, "non_striker": "JP Duminy"}}, {"49.5": {"batsman": "J Botha", "bowler": "SW Masakadza", "runs": {"batsman": 1, "total": 1, "extras": 0}, "non_striker": "JP Duminy"}}, {"49.6": {"batsman": "JP Duminy", "bowler": "SW Masakadza", "runs": {"batsman": 2, "total": 2, "extras": 0}, "non_striker": "J Botha"}}], "team": "South Africa"}}, {"2nd innings": {"deliveries": [{"0.1": {"batsman": "H Masakadza", "bowler": "JA Morkel", "runs": {"batsman": 0, "total": 0, "extras": 0}, "non_striker": "BRM Taylor"}}, {"0.2": {"batsman": "H Masakadza", "bowler": "JA Morkel", "runs": {"batsman": 0, "total": 0, "extras": 0}, "non_striker": "BRM Taylor"}}, {"0.3": {"batsman": "H Masakadza", "bowler": "JA Morkel", "runs": {"batsman": 0, "total": 0, "extras": 0}, "non_striker": "BRM Taylor"}}, {"0.4": {"batsman": "H Masakadza", "bowler": "JA Morkel", "runs": {"batsman": 0, "total": 0, "extras": 0}, "non_striker": "BRM Taylor"}}, {"0.5": {"batsman": "H Masakadza", "bowler": "JA Morkel", "runs": {"batsman": 0, "total": 0, "extras": 0}, "non_striker": "BRM Taylor"}}, {"0.6": {"batsman": "H Masakadza", "bowler": "JA Morkel", "runs": {"batsman": 0, "total": 0, "extras": 0}, "non_striker": "BRM Taylor"}}, {"1.1": {"batsman": "BRM Taylor", "bowler": "WD Parnell", "runs": {"batsman": 4, "total": 4, "extras": 0}, "non_striker": "H Masakadza"}}, {"1.2": {"batsman": "BRM Taylor", "bowler": "WD Parnell", "runs": {"batsman": 0, "total": 0, "extras": 0}, "non_striker": "H Masakadza"}}, {"1.3": {"batsman": "BRM Taylor", "bowler": "WD Parnell", "runs": {"batsman": 0, "total": 0, "extras": 0}, "non_striker": "H Masakadza"}}, {"1.4": {"batsman": "BRM Taylor", "bowler": "WD Parnell", "runs": {"batsman": 0, "total": 0, "extras": 0}, "non_striker": "H Masakadza"}}, {"1.5": {"batsman": "BRM Taylor", "bowler": "WD Parnell", "runs": {"batsman": 0, "total": 1, "extras": 1}, "extras": {"legbyes": 1}, "non_striker": "H Masakadza"}}, {"1.6": {"batsman": "H Masakadza", "bowler": "WD Parnell", "runs": {"batsman": 0, "total": 0, "extras": 0}, "non_striker": "BRM Taylor"}}, {"2.1": {"batsman": "BRM Taylor", "bowler": "JA Morkel", "runs": {"batsman": 0, "total": 0, "extras": 0}, "non_striker": "H Masakadza"}}, {"2.2": {"batsman": "BRM Taylor", "bowler": "JA Morkel", "runs": {"batsman": 1, "total": 1, "extras": 0}, "non_striker": "H Masakadza"}}, {"2.3": {"batsman": "H Masakadza", "bowler": "JA Morkel", "runs": {"batsman": 1, "total": 1, "extras": 0}, "non_striker": "BRM Taylor"}}, {"2.4": {"batsman": "BRM Taylor", "bowler": "JA Morkel", "runs": {"batsman": 0, "total": 0, "extras": 0}, "non_striker": "H Masakadza"}}, {"2.5": {"batsman": "BRM Taylor", "bowler": "JA Morkel", "runs": {"batsman": 1, "total": 1, "extras": 0}, "non_striker": "H Masakadza"}}, {"2.6": {"batsman": "H Masakadza", "bowler": "JA Morkel", "runs": {"batsman": 4, "total": 4, "extras": 0}, "non_striker": "BRM Taylor"}}, {"3.1": {"batsman": "BRM Taylor", "bowler": "WD Parnell", "runs": {"batsman": 0, "total": 0, "extras": 0}, "non_striker": "H Masakadza"}}, {"3.2": {"batsman": "BRM Taylor", "bowler": "WD Parnell", "runs": {"batsman": 4, "total": 4, "extras": 0}, "non_striker": "H Masakadza"}}, {"3.3": {"batsman": "BRM Taylor", "bowler": "WD Parnell", "runs": {"batsman": 1, "total": 1, "extras": 0}, "non_striker": "H Masakadza"}}, {"3.4": {"batsman": "H Masakadza", "bowler": "WD Parnell", "runs": {"batsman": 4, "total": 4, "extras": 0}, "non_striker": "BRM Taylor"}}, {"3.5": {"batsman": "H Masakadza", "bowler": "WD Parnell", "runs": {"batsman": 0, "total": 0, "extras": 0}, "non_striker": "BRM Taylor"}}, {"3.6": {"batsman": "H Masakadza", "bowler": "WD Parnell", "runs": {"batsman": 0, "total": 0, "extras": 0}, "non_striker": "BRM Taylor"}}, {"4.1": {"batsman": "BRM Taylor", "bowler": "JA Morkel", "runs": {"batsman": 1, "total": 1, "extras": 0}, "non_striker": "H Masakadza"}}, {"4.2": {"batsman": "H Masakadza", "bowler": "JA Morkel", "runs": {"batsman": 0, "total": 1, "extras": 1}, "extras": {"legbyes": 1}, "non_striker": "BRM Taylor"}}, {"4.3": {"batsman": "BRM Taylor", "bowler": "JA Morkel", "runs": {"batsman": 1, "total": 1, "extras": 0}, "non_striker": "H Masakadza"}}, {"4.4": {"batsman": "H Masakadza", "bowler": "JA Morkel", "runs": {"batsman": 0, "total": 0, "extras": 0}, "non_striker": "BRM Taylor"}}, {"4.5": {"batsman": "H Masakadza", "bowler": "JA Morkel", "runs": {"batsman": 4, "total": 4, "extras": 0}, "non_striker": "BRM Taylor"}}, {"4.6": {"batsman": "H Masakadza", "bowler": "JA Morkel", "runs": {"batsman": 4, "total": 4, "extras": 0}, "non_striker": "BRM Taylor"}}, {"5.1": {"batsman": "BRM Taylor", "bowler": "CK Langeveldt", "runs": {"batsman": 0, "total": 0, "extras": 0}, "non_striker": "H Masakadza"}}, {"5.2": {"batsman": "BRM Taylor", "bowler": "CK Langeveldt", "runs": {"batsman": 0, "total": 0, "extras": 0}, "non_striker": "H Masakadza"}}, {"5.3": {"batsman": "BRM Taylor", "bowler": "CK Langeveldt", "runs": {"batsman": 4, "total": 4, "extras": 0}, "non_striker": "H Masakadza"}}, {"5.4": {"batsman": "BRM Taylor", "bowler": "CK Langeveldt", "runs": {"batsman": 1, "total": 1, "extras": 0}, "non_striker": "H Masakadza"}}, {"5.5": {"batsman": "H Masakadza", "bowler": "CK Langeveldt", "runs": {"batsman": 0, "total": 0, "extras": 0}, "non_striker": "BRM Taylor"}}, {"5.6": {"batsman": "H Masakadza", "bowler": "CK Langeveldt", "runs": {"batsman": 1, "total": 1, "extras": 0}, "non_striker": "BRM Taylor"}}, {"6.1": {"batsman": "H Masakadza", "bowler": "JA Morkel", "runs": {"batsman": 0, "total": 0, "extras": 0}, "non_striker": "BRM Taylor"}}, {"6.2": {"batsman": "H Masakadza", "bowler": "JA Morkel", "runs": {"batsman": 1, "total": 1, "extras": 0}, "non_striker": "BRM Taylor"}}, {"6.3": {"batsman": "BRM Taylor", "bowler": "JA Morkel", "runs": {"batsman": 1, "total": 1, "extras": 0}, "non_striker": "H Masakadza"}}, {"6.4": {"batsman": "H Masakadza", "bowler": "JA Morkel", "runs": {"batsman": 0, "total": 0, "extras": 0}, "non_striker": "BRM Taylor"}}, {"6.5": {"batsman": "H Masakadza", "bowler": "JA Morkel", "runs": {"batsman": 0, "total": 0, "extras": 0}, "non_striker": "BRM Taylor"}}, {"6.6": {"batsman": "H Masakadza", "bowler": "JA Morkel", "runs": {"batsman": 0, "total": 0, "extras": 0}, "non_striker": "BRM Taylor"}}, {"7.1": {"batsman": "BRM Taylor", "bowler": "CK Langeveldt", "runs": {"batsman": 0, "total": 0, "extras": 0}, "non_striker": "H Masakadza"}}, {"7.2": {"batsman": "BRM Taylor", "bowler": "CK Langeveldt", "runs": {"batsman": 4, "total": 4, "extras": 0}, "non_striker": "H Masakadza"}}, {"7.3": {"batsman": "BRM Taylor", "bowler": "CK Langeveldt", "runs": {"batsman": 2, "total": 2, "extras": 0}, "non_striker": "H Masakadza"}}, {"7.4": {"batsman": "BRM Taylor", "bowler": "CK Langeveldt", "runs": {"batsman": 1, "total": 1, "extras": 0}, "non_striker": "H Masakadza"}}, {"7.5": {"batsman": "H Masakadza", "bowler": "CK Langeveldt", "runs": {"batsman": 4, "total": 4, "extras": 0}, "non_striker": "BRM Taylor"}}, {"7.6": {"batsman": "H Masakadza", "bowler": "CK Langeveldt", "runs": {"batsman": 1, "total": 1, "extras": 0}, "non_striker": "BRM Taylor"}}, {"8.1": {"batsman": "H Masakadza", "bowler": "J Theron", "runs": {"batsman": 0, "total": 0, "extras": 0}, "non_striker": "BRM Taylor"}}, {"8.2": {"batsman": "H Masakadza", "bowler": "J Theron", "runs": {"batsman": 0, "total": 0, "extras": 0}, "non_striker": "BRM Taylor"}}, {"8.3": {"batsman": "H Masakadza", "bowler": "J Theron", "runs": {"batsman": 1, "total": 1, "extras": 0}, "non_striker": "BRM Taylor"}}, {"8.4": {"batsman": "BRM Taylor", "bowler": "J Theron", "runs": {"batsman": 1, "total": 1, "extras": 0}, "non_striker": "H Masakadza"}}, {"8.5": {"batsman": "H Masakadza", "bowler": "J Theron", "runs": {"batsman": 0, "total": 0, "extras": 0}, "non_striker": "BRM Taylor"}}, {"8.6": {"batsman": "H Masakadza", "bowler": "J Theron", "runs": {"batsman": 0, "total": 0, "extras": 0}, "non_striker": "BRM Taylor"}}, {"9.1": {"batsman": "BRM Taylor", "bowler": "CK Langeveldt", "runs": {"batsman": 0, "total": 0, "extras": 0}, "non_striker": "H Masakadza"}}, {"9.2": {"batsman": "BRM Taylor", "bowler": "CK Langeveldt", "runs": {"batsman": 0, "total": 0, "extras": 0}, "non_striker": "H Masakadza"}}, {"9.3": {"batsman": "BRM Taylor", "bowler": "CK Langeveldt", "runs": {"batsman": 1, "total": 1, "extras": 0}, "non_striker": "H Masakadza"}}, {"9.4": {"batsman": "H Masakadza", "bowler": "CK Langeveldt", "runs": {"batsman": 1, "total": 1, "extras": 0}, "non_striker": "BRM Taylor"}}, {"9.5": {"batsman": "BRM Taylor", "bowler": "CK Langeveldt", "runs": {"batsman": 1, "total": 1, "extras": 0}, "non_striker": "H Masakadza"}}, {"9.6": {"batsman": "H Masakadza", "bowler": "CK Langeveldt", "runs": {"batsman": 0, "total": 1, "extras": 1}, "extras": {"legbyes": 1}, "non_striker": "BRM Taylor"}}, {"10.1": {"batsman": "H Masakadza", "bowler": "J Theron", "runs": {"batsman": 1, "total": 1, "extras": 0}, "non_striker": "BRM Taylor"}}, {"10.2": {"batsman": "BRM Taylor", "bowler": "J Theron", "runs": {"batsman": 4, "total": 4, "extras": 0}, "non_striker": "H Masakadza"}}, {"10.3": {"batsman": "BRM Taylor", "bowler": "J Theron", "runs": {"batsman": 1, "total": 1, "extras": 0}, "non_striker": "H Masakadza"}}, {"10.4": {"batsman": "H Masakadza", "bowler": "J Theron", "runs": {"batsman": 0, "total": 0, "extras": 0}, "non_striker": "BRM Taylor"}}, {"10.5": {"batsman": "H Masakadza", "bowler": "J Theron", "runs": {"batsman": 0, "total": 0, "extras": 0}, "non_striker": "BRM Taylor"}}, {"10.6": {"batsman": "H Masakadza", "bowler": "J Theron", "runs": {"batsman": 1, "total": 1, "extras": 0}, "non_striker": "BRM Taylor"}}, {"11.1": {"batsman": "H Masakadza", "bowler": "CK Langeveldt", "runs": {"batsman": 0, "total": 0, "extras": 0}, "non_striker": "BRM Taylor"}}, {"11.2": {"batsman": "H Masakadza", "bowler": "CK Langeveldt", "runs": {"batsman": 2, "total": 2, "extras": 0}, "non_striker": "BRM Taylor"}}, {"11.3": {"batsman": "H Masakadza", "bowler": "CK Langeveldt", "runs": {"batsman": 0, "total": 0, "extras": 0}, "non_striker": "BRM Taylor"}}, {"11.4": {"batsman": "H Masakadza", "bowler": "CK Langeveldt", "runs": {"batsman": 0, "total": 1, "extras": 1}, "extras": {"legbyes": 1}, "non_striker": "BRM Taylor"}}, {"11.5": {"batsman": "BRM Taylor", "bowler": "CK Langeveldt", "runs": {"batsman": 0, "total": 0, "extras": 0}, "non_striker": "H Masakadza"}}, {"11.6": {"batsman": "BRM Taylor", "bowler": "CK Langeveldt", "runs": {"batsman": 1, "total": 1, "extras": 0}, "non_striker": "H Masakadza"}}, {"12.1": {"batsman": "BRM Taylor", "bowler": "J Theron", "runs": {"batsman": 1, "total": 1, "extras": 0}, "non_striker": "H Masakadza"}}, {"12.2": {"batsman": "H Masakadza", "bowler": "J Theron", "runs": {"batsman": 0, "total": 0, "extras": 0}, "non_striker": "BRM Taylor", "wicket": {"fielders": ["J Botha"], "kind": "caught", "player_out": "H Masakadza"}}}, {"12.3": {"batsman": "BRM Taylor", "bowler": "J Theron", "runs": {"batsman": 1, "total": 1, "extras": 0}, "non_striker": "CJ Chibhabha"}}, {"12.4": {"batsman": "CJ Chibhabha", "bowler": "J Theron", "runs": {"batsman": 0, "total": 0, "extras": 0}, "non_striker": "BRM Taylor"}}, {"12.5": {"batsman": "CJ Chibhabha", "bowler": "J Theron", "runs": {"batsman": 1, "total": 1, "extras": 0}, "non_striker": "BRM Taylor"}}, {"12.6": {"batsman": "BRM Taylor", "bowler": "J Theron", "runs": {"batsman": 1, "total": 1, "extras": 0}, "non_striker": "CJ Chibhabha"}}, {"13.1": {"batsman": "BRM Taylor", "bowler": "CK Langeveldt", "runs": {"batsman": 1, "total": 1, "extras": 0}, "non_striker": "CJ Chibhabha"}}, {"13.2": {"batsman": "CJ Chibhabha", "bowler": "CK Langeveldt", "runs": {"batsman": 1, "total": 1, "extras": 0}, "non_striker": "BRM Taylor"}}, {"13.3": {"batsman": "BRM Taylor", "bowler": "CK Langeveldt", "runs": {"batsman": 0, "total": 0, "extras": 0}, "non_striker": "CJ Chibhabha"}}, {"13.4": {"batsman": "BRM Taylor", "bowler": "CK Langeveldt", "runs": {"batsman": 2, "total": 2, "extras": 0}, "non_striker": "CJ Chibhabha"}}, {"13.5": {"batsman": "BRM Taylor", "bowler": "CK Langeveldt", "runs": {"batsman": 0, "total": 0, "extras": 0}, "non_striker": "CJ Chibhabha"}}, {"13.6": {"batsman": "BRM Taylor", "bowler": "CK Langeveldt", "runs": {"batsman": 2, "total": 2, "extras": 0}, "non_striker": "CJ Chibhabha"}}, {"14.1": {"batsman": "CJ Chibhabha", "bowler": "J Theron", "runs": {"batsman": 4, "total": 4, "extras": 0}, "non_striker": "BRM Taylor"}}, {"14.2": {"batsman": "CJ Chibhabha", "bowler": "J Theron", "runs": {"batsman": 0, "total": 0, "extras": 0}, "non_striker": "BRM Taylor"}}, {"14.3": {"batsman": "CJ Chibhabha", "bowler": "J Theron", "runs": {"batsman": 0, "total": 0, "extras": 0}, "non_striker": "BRM Taylor"}}, {"14.4": {"batsman": "CJ Chibhabha", "bowler": "J Theron", "runs": {"batsman": 1, "total": 1, "extras": 0}, "non_striker": "BRM Taylor"}}, {"14.5": {"batsman": "BRM Taylor", "bowler": "J Theron", "runs": {"batsman": 1, "total": 1, "extras": 0}, "non_striker": "CJ Chibhabha"}}, {"14.6": {"batsman": "CJ Chibhabha", "bowler": "J Theron", "runs": {"batsman": 2, "total": 2, "extras": 0}, "non_striker": "BRM Taylor"}}, {"15.1": {"batsman": "BRM Taylor", "bowler": "WD Parnell", "runs": {"batsman": 1, "total": 1, "extras": 0}, "non_striker": "CJ Chibhabha"}}, {"15.2": {"batsman": "CJ Chibhabha", "bowler": "WD Parnell", "runs": {"batsman": 1, "total": 1, "extras": 0}, "non_striker": "BRM Taylor"}}, {"15.3": {"batsman": "BRM Taylor", "bowler": "WD Parnell", "runs": {"batsman": 1, "total": 1, "extras": 0}, "non_striker": "CJ Chibhabha"}}, {"15.4": {"batsman": "CJ Chibhabha", "bowler": "WD Parnell", "runs": {"batsman": 0, "total": 0, "extras": 0}, "non_striker": "BRM Taylor", "wicket": {"fielders": ["AB de Villiers"], "kind": "caught", "player_out": "CJ Chibhabha"}}}, {"15.5": {"batsman": "SC Williams", "bowler": "WD Parnell", "runs": {"batsman": 2, "total": 2, "extras": 0}, "non_striker": "BRM Taylor"}}, {"15.6": {"batsman": "SC Williams", "bowler": "WD Parnell", "runs": {"batsman": 0, "total": 0, "extras": 0}, "non_striker": "BRM Taylor"}}, {"16.1": {"batsman": "BRM Taylor", "bowler": "J Botha", "runs": {"batsman": 2, "total": 2, "extras": 0}, "non_striker": "SC Williams"}}, {"16.2": {"batsman": "BRM Taylor", "bowler": "J Botha", "runs": {"batsman": 0, "total": 0, "extras": 0}, "non_striker": "SC Williams"}}, {"16.3": {"batsman": "BRM Taylor", "bowler": "J Botha", "runs": {"batsman": 0, "total": 0, "extras": 0}, "non_striker": "SC Williams"}}, {"16.4": {"batsman": "BRM Taylor", "bowler": "J Botha", "runs": {"batsman": 2, "total": 2, "extras": 0}, "non_striker": "SC Williams"}}, {"16.5": {"batsman": "BRM Taylor", "bowler": "J Botha", "runs": {"batsman": 1, "total": 1, "extras": 0}, "non_striker": "SC Williams"}}, {"16.6": {"batsman": "SC Williams", "bowler": "J Botha", "runs": {"batsman": 0, "total": 0, "extras": 0}, "non_striker": "BRM Taylor"}}, {"17.1": {"batsman": "BRM Taylor", "bowler": "WD Parnell", "runs": {"batsman": 2, "total": 2, "extras": 0}, "non_striker": "SC Williams"}}, {"17.2": {"batsman": "BRM Taylor", "bowler": "WD Parnell", "runs": {"batsman": 4, "total": 4, "extras": 0}, "non_striker": "SC Williams"}}, {"17.3": {"batsman": "BRM Taylor", "bowler": "WD Parnell", "runs": {"batsman": 1, "total": 1, "extras": 0}, "non_striker": "SC Williams"}}, {"17.4": {"batsman": "SC Williams", "bowler": "WD Parnell", "runs": {"batsman": 0, "total": 0, "extras": 0}, "non_striker": "BRM Taylor"}}, {"17.5": {"batsman": "SC Williams", "bowler": "WD Parnell", "runs": {"batsman": 0, "total": 0, "extras": 0}, "non_striker": "BRM Taylor"}}, {"17.6": {"batsman": "SC Williams", "bowler": "WD Parnell", "runs": {"batsman": 0, "total": 0, "extras": 0}, "non_striker": "BRM Taylor"}}, {"18.1": {"batsman": "BRM Taylor", "bowler": "J Botha", "runs": {"batsman": 0, "total": 0, "extras": 0}, "non_striker": "SC Williams"}}, {"18.2": {"batsman": "BRM Taylor", "bowler": "J Botha", "runs": {"batsman": 1, "total": 1, "extras": 0}, "non_striker": "SC Williams"}}, {"18.3": {"batsman": "SC Williams", "bowler": "J Botha", "runs": {"batsman": 0, "total": 0, "extras": 0}, "non_striker": "BRM Taylor"}}, {"18.4": {"batsman": "SC Williams", "bowler": "J Botha", "runs": {"batsman": 0, "total": 0, "extras": 0}, "non_striker": "BRM Taylor"}}, {"18.5": {"batsman": "SC Williams", "bowler": "J Botha", "runs": {"batsman": 1, "total": 1, "extras": 0}, "non_striker": "BRM Taylor"}}, {"18.6": {"batsman": "BRM Taylor", "bowler": "J Botha", "runs": {"batsman": 0, "total": 1, "extras": 1}, "extras": {"wides": 1}, "non_striker": "SC Williams"}}, {"18.7": {"batsman": "BRM Taylor", "bowler": "J Botha", "runs": {"batsman": 1, "total": 1, "extras": 0}, "non_striker": "SC Williams"}}, {"19.1": {"batsman": "BRM Taylor", "bowler": "WD Parnell", "runs": {"batsman": 1, "total": 1, "extras": 0}, "non_striker": "SC Williams"}}, {"19.2": {"batsman": "SC Williams", "bowler": "WD Parnell", "runs": {"batsman": 0, "total": 0, "extras": 0}, "non_striker": "BRM Taylor"}}, {"19.3": {"batsman": "SC Williams", "bowler": "WD Parnell", "runs": {"batsman": 0, "total": 0, "extras": 0}, "non_striker": "BRM Taylor"}}, {"19.4": {"batsman": "SC Williams", "bowler": "WD Parnell", "runs": {"batsman": 1, "total": 1, "extras": 0}, "non_striker": "BRM Taylor"}}, {"19.5": {"batsman": "BRM Taylor", "bowler": "WD Parnell", "runs": {"batsman": 1, "total": 1, "extras": 0}, "non_striker": "SC Williams"}}, {"19.6": {"batsman": "SC Williams", "bowler": "WD Parnell", "runs": {"batsman": 0, "total": 0, "extras": 0}, "non_striker": "BRM Taylor"}}, {"20.1": {"batsman": "BRM Taylor", "bowler": "J Botha", "runs": {"batsman": 1, "total": 1, "extras": 0}, "non_striker": "SC Williams"}}, {"20.2": {"batsman": "SC Williams", "bowler": "J Botha", "runs": {"batsman": 0, "total": 1, "extras": 1}, "extras": {"legbyes": 1}, "non_striker": "BRM Taylor"}}, {"20.3": {"batsman": "BRM Taylor", "bowler": "J Botha", "runs": {"batsman": 1, "total": 1, "extras": 0}, "non_striker": "SC Williams"}}, {"20.4": {"batsman": "SC Williams", "bowler": "J Botha", "runs": {"batsman": 1, "total": 1, "extras": 0}, "non_striker": "BRM Taylor"}}, {"20.5": {"batsman": "BRM Taylor", "bowler": "J Botha", "runs": {"batsman": 1, "total": 1, "extras": 0}, "non_striker": "SC Williams"}}, {"20.6": {"batsman": "SC Williams", "bowler": "J Botha", "runs": {"batsman": 1, "total": 1, "extras": 0}, "non_striker": "BRM Taylor"}}, {"21.1": {"batsman": "SC Williams", "bowler": "JA Morkel", "runs": {"batsman": 1, "total": 1, "extras": 0}, "non_striker": "BRM Taylor"}}, {"21.2": {"batsman": "BRM Taylor", "bowler": "JA Morkel", "runs": {"batsman": 0, "total": 1, "extras": 1}, "extras": {"legbyes": 1}, "non_striker": "SC Williams"}}, {"21.3": {"batsman": "SC Williams", "bowler": "JA Morkel", "runs": {"batsman": 2, "total": 2, "extras": 0}, "non_striker": "BRM Taylor"}}, {"21.4": {"batsman": "SC Williams", "bowler": "JA Morkel", "runs": {"batsman": 0, "total": 0, "extras": 0}, "non_striker": "BRM Taylor"}}, {"21.5": {"batsman": "SC Williams", "bowler": "JA Morkel", "runs": {"batsman": 0, "total": 0, "extras": 0}, "non_striker": "BRM Taylor"}}, {"21.6": {"batsman": "SC Williams", "bowler": "JA Morkel", "runs": {"batsman": 1, "total": 1, "extras": 0}, "non_striker": "BRM Taylor"}}, {"22.1": {"batsman": "SC Williams", "bowler": "J Botha", "runs": {"batsman": 0, "total": 0, "extras": 0}, "non_striker": "BRM Taylor"}}, {"22.2": {"batsman": "SC Williams", "bowler": "J Botha", "runs": {"batsman": 0, "total": 0, "extras": 0}, "non_striker": "BRM Taylor"}}, {"22.3": {"batsman": "SC Williams", "bowler": "J Botha", "runs": {"batsman": 0, "total": 0, "extras": 0}, "non_striker": "BRM Taylor"}}, {"22.4": {"batsman": "SC Williams", "bowler": "J Botha", "runs": {"batsman": 0, "total": 0, "extras": 0}, "non_striker": "BRM Taylor", "wicket": {"fielders": ["J Theron"], "kind": "caught", "player_out": "SC Williams"}}}, {"22.5": {"batsman": "BRM Taylor", "bowler": "J Botha", "runs": {"batsman": 1, "total": 1, "extras": 0}, "non_striker": "GW Flower"}}, {"22.6": {"batsman": "GW Flower", "bowler": "J Botha", "runs": {"batsman": 0, "total": 0, "extras": 0}, "non_striker": "BRM Taylor"}}, {"23.1": {"batsman": "BRM Taylor", "bowler": "JA Morkel", "runs": {"batsman": 0, "total": 0, "extras": 0}, "non_striker": "GW Flower"}}, {"23.2": {"batsman": "BRM Taylor", "bowler": "JA Morkel", "runs": {"batsman": 1, "total": 1, "extras": 0}, "non_striker": "GW Flower"}}, {"23.3": {"batsman": "GW Flower", "bowler": "JA Morkel", "runs": {"batsman": 0, "total": 0, "extras": 0}, "non_striker": "BRM Taylor"}}, {"23.4": {"batsman": "GW Flower", "bowler": "JA Morkel", "runs": {"batsman": 0, "total": 2, "extras": 2}, "extras": {"legbyes": 2}, "non_striker": "BRM Taylor"}}, {"23.5": {"batsman": "GW Flower", "bowler": "JA Morkel", "runs": {"batsman": 0, "total": 0, "extras": 0}, "non_striker": "BRM Taylor"}}, {"23.6": {"batsman": "GW Flower", "bowler": "JA Morkel", "runs": {"batsman": 1, "total": 1, "extras": 0}, "non_striker": "BRM Taylor"}}, {"24.1": {"batsman": "GW Flower", "bowler": "J Botha", "runs": {"batsman": 0, "total": 0, "extras": 0}, "non_striker": "BRM Taylor"}}, {"24.2": {"batsman": "GW Flower", "bowler": "J Botha", "runs": {"batsman": 0, "total": 0, "extras": 0}, "non_striker": "BRM Taylor"}}, {"24.3": {"batsman": "GW Flower", "bowler": "J Botha", "runs": {"batsman": 0, "total": 0, "extras": 0}, "non_striker": "BRM Taylor"}}, {"24.4": {"batsman": "GW Flower", "bowler": "J Botha", "runs": {"batsman": 0, "total": 0, "extras": 0}, "non_striker": "BRM Taylor"}}, {"24.5": {"batsman": "GW Flower", "bowler": "J Botha", "runs": {"batsman": 1, "total": 1, "extras": 0}, "non_striker": "BRM Taylor"}}, {"24.6": {"batsman": "BRM Taylor", "bowler": "J Botha", "runs": {"batsman": 0, "total": 0, "extras": 0}, "non_striker": "GW Flower"}}, {"25.1": {"batsman": "GW Flower", "bowler": "JA Morkel", "runs": {"batsman": 1, "total": 1, "extras": 0}, "non_striker": "BRM Taylor"}}, {"25.2": {"batsman": "BRM Taylor", "bowler": "JA Morkel", "runs": {"batsman": 0, "total": 0, "extras": 0}, "non_striker": "GW Flower"}}, {"25.3": {"batsman": "BRM Taylor", "bowler": "JA Morkel", "runs": {"batsman": 1, "total": 1, "extras": 0}, "non_striker": "GW Flower"}}, {"25.4": {"batsman": "GW Flower", "bowler": "JA Morkel", "runs": {"batsman": 0, "total": 0, "extras": 0}, "non_striker": "BRM Taylor"}}, {"25.5": {"batsman": "GW Flower", "bowler": "JA Morkel", "runs": {"batsman": 1, "total": 1, "extras": 0}, "non_striker": "BRM Taylor"}}, {"25.6": {"batsman": "BRM Taylor", "bowler": "JA Morkel", "runs": {"batsman": 1, "total": 1, "extras": 0}, "non_striker": "GW Flower"}}, {"26.1": {"batsman": "BRM Taylor", "bowler": "J Botha", "runs": {"batsman": 1, "total": 1, "extras": 0}, "non_striker": "GW Flower"}}, {"26.2": {"batsman": "GW Flower", "bowler": "J Botha", "runs": {"batsman": 2, "total": 2, "extras": 0}, "non_striker": "BRM Taylor"}}, {"26.3": {"batsman": "GW Flower", "bowler": "J Botha", "runs": {"batsman": 1, "total": 1, "extras": 0}, "non_striker": "BRM Taylor"}}, {"26.4": {"batsman": "BRM Taylor", "bowler": "J Botha", "runs": {"batsman": 1, "total": 1, "extras": 0}, "non_striker": "GW Flower"}}, {"26.5": {"batsman": "GW Flower", "bowler": "J Botha", "runs": {"batsman": 1, "total": 1, "extras": 0}, "non_striker": "BRM Taylor"}}, {"26.6": {"batsman": "BRM Taylor", "bowler": "J Botha", "runs": {"batsman": 1, "total": 1, "extras": 0}, "non_striker": "GW Flower"}}, {"27.1": {"batsman": "BRM Taylor", "bowler": "J Theron", "runs": {"batsman": 1, "total": 1, "extras": 0}, "non_striker": "GW Flower"}}, {"27.2": {"batsman": "GW Flower", "bowler": "J Theron", "runs": {"batsman": 0, "total": 1, "extras": 1}, "extras": {"legbyes": 1}, "non_striker": "BRM Taylor"}}, {"27.3": {"batsman": "BRM Taylor", "bowler": "J Theron", "runs": {"batsman": 0, "total": 0, "extras": 0}, "non_striker": "GW Flower"}}, {"27.4": {"batsman": "BRM Taylor", "bowler": "J Theron", "runs": {"batsman": 1, "total": 1, "extras": 0}, "non_striker": "GW Flower"}}, {"27.5": {"batsman": "GW Flower", "bowler": "J Theron", "runs": {"batsman": 1, "total": 1, "extras": 0}, "non_striker": "BRM Taylor"}}, {"27.6": {"batsman": "BRM Taylor", "bowler": "J Theron", "runs": {"batsman": 4, "total": 4, "extras": 0}, "non_striker": "GW Flower"}}, {"28.1": {"batsman": "GW Flower", "bowler": "J Botha", "runs": {"batsman": 1, "total": 1, "extras": 0}, "non_striker": "BRM Taylor"}}, {"28.2": {"batsman": "BRM Taylor", "bowler": "J Botha", "runs": {"batsman": 1, "total": 1, "extras": 0}, "non_striker": "GW Flower"}}, {"28.3": {"batsman": "GW Flower", "bowler": "J Botha", "runs": {"batsman": 1, "total": 1, "extras": 0}, "non_striker": "BRM Taylor"}}, {"28.4": {"batsman": "BRM Taylor", "bowler": "J Botha", "runs": {"batsman": 0, "total": 0, "extras": 0}, "non_striker": "GW Flower"}}, {"28.5": {"batsman": "BRM Taylor", "bowler": "J Botha", "runs": {"batsman": 1, "total": 1, "extras": 0}, "non_striker": "GW Flower"}}, {"28.6": {"batsman": "GW Flower", "bowler": "J Botha", "runs": {"batsman": 2, "total": 2, "extras": 0}, "non_striker": "BRM Taylor"}}, {"29.1": {"batsman": "BRM Taylor", "bowler": "J Theron", "runs": {"batsman": 1, "total": 1, "extras": 0}, "non_striker": "GW Flower"}}, {"29.2": {"batsman": "GW Flower", "bowler": "J Theron", "runs": {"batsman": 0, "total": 0, "extras": 0}, "non_striker": "BRM Taylor"}}, {"29.3": {"batsman": "GW Flower", "bowler": "J Theron", "runs": {"batsman": 0, "total": 3, "extras": 3}, "extras": {"legbyes": 3}, "non_striker": "BRM Taylor"}}, {"29.4": {"batsman": "BRM Taylor", "bowler": "J Theron", "runs": {"batsman": 1, "total": 1, "extras": 0}, "non_striker": "GW Flower"}}, {"29.5": {"batsman": "GW Flower", "bowler": "J Theron", "runs": {"batsman": 0, "total": 0, "extras": 0}, "non_striker": "BRM Taylor", "wicket": {"fielders": ["GC Smith"], "kind": "caught", "player_out": "GW Flower"}}}, {"29.6": {"batsman": "T Taibu", "bowler": "J Theron", "runs": {"batsman": 1, "total": 1, "extras": 0}, "non_striker": "BRM Taylor"}}, {"30.1": {"batsman": "T Taibu", "bowler": "J Botha", "runs": {"batsman": 1, "total": 1, "extras": 0}, "non_striker": "BRM Taylor"}}, {"30.2": {"batsman": "BRM Taylor", "bowler": "J Botha", "runs": {"batsman": 1, "total": 1, "extras": 0}, "non_striker": "T Taibu"}}, {"30.3": {"batsman": "T Taibu", "bowler": "J Botha", "runs": {"batsman": 0, "total": 0, "extras": 0}, "non_striker": "BRM Taylor"}}, {"30.4": {"batsman": "T Taibu", "bowler": "J Botha", "runs": {"batsman": 4, "total": 4, "extras": 0}, "non_striker": "BRM Taylor"}}, {"30.5": {"batsman": "T Taibu", "bowler": "J Botha", "runs": {"batsman": 0, "total": 0, "extras": 0}, "non_striker": "BRM Taylor"}}, {"30.6": {"batsman": "T Taibu", "bowler": "J Botha", "runs": {"batsman": 0, "total": 0, "extras": 0}, "non_striker": "BRM Taylor"}}, {"31.1": {"batsman": "BRM Taylor", "bowler": "WD Parnell", "runs": {"batsman": 0, "total": 1, "extras": 1}, "extras": {"legbyes": 1}, "non_striker": "T Taibu"}}, {"31.2": {"batsman": "T Taibu", "bowler": "WD Parnell", "runs": {"batsman": 0, "total": 0, "extras": 0}, "non_striker": "BRM Taylor"}}, {"31.3": {"batsman": "T Taibu", "bowler": "WD Parnell", "runs": {"batsman": 1, "total": 1, "extras": 0}, "non_striker": "BRM Taylor"}}, {"31.4": {"batsman": "BRM Taylor", "bowler": "WD Parnell", "runs": {"batsman": 0, "total": 1, "extras": 1}, "extras": {"wides": 1}, "non_striker": "T Taibu"}}, {"31.5": {"batsman": "BRM Taylor", "bowler": "WD Parnell", "runs": {"batsman": 0, "total": 0, "extras": 0}, "non_striker": "T Taibu"}}, {"31.6": {"batsman": "BRM Taylor", "bowler": "WD Parnell", "runs": {"batsman": 0, "total": 1, "extras": 1}, "extras": {"wides": 1}, "non_striker": "T Taibu"}}, {"31.7": {"batsman": "BRM Taylor", "bowler": "WD Parnell", "runs": {"batsman": 1, "total": 1, "extras": 0}, "non_striker": "T Taibu"}}, {"31.8": {"batsman": "T Taibu", "bowler": "WD Parnell", "runs": {"batsman": 1, "total": 1, "extras": 0}, "non_striker": "BRM Taylor"}}, {"32.1": {"batsman": "T Taibu", "bowler": "J Botha", "runs": {"batsman": 0, "total": 1, "extras": 1}, "extras": {"legbyes": 1}, "non_striker": "BRM Taylor"}}, {"32.2": {"batsman": "BRM Taylor", "bowler": "J Botha", "runs": {"batsman": 0, "total": 0, "extras": 0}, "non_striker": "T Taibu"}}, {"32.3": {"batsman": "BRM Taylor", "bowler": "J Botha", "runs": {"batsman": 1, "total": 1, "extras": 0}, "non_striker": "T Taibu"}}, {"32.4": {"batsman": "T Taibu", "bowler": "J Botha", "runs": {"batsman": 0, "total": 0, "extras": 0}, "non_striker": "BRM Taylor"}}, {"32.5": {"batsman": "T Taibu", "bowler": "J Botha", "runs": {"batsman": 1, "total": 1, "extras": 0}, "non_striker": "BRM Taylor"}}, {"32.6": {"batsman": "BRM Taylor", "bowler": "J Botha", "runs": {"batsman": 0, "total": 0, "extras": 0}, "non_striker": "T Taibu"}}, {"33.1": {"batsman": "T Taibu", "bowler": "WD Parnell", "runs": {"batsman": 1, "total": 1, "extras": 0}, "non_striker": "BRM Taylor"}}, {"33.2": {"batsman": "BRM Taylor", "bowler": "WD Parnell", "runs": {"batsman": 1, "total": 1, "extras": 0}, "non_striker": "T Taibu"}}, {"33.3": {"batsman": "T Taibu", "bowler": "WD Parnell", "runs": {"batsman": 0, "total": 0, "extras": 0}, "non_striker": "BRM Taylor"}}, {"33.4": {"batsman": "T Taibu", "bowler": "WD Parnell", "runs": {"batsman": 1, "total": 1, "extras": 0}, "non_striker": "BRM Taylor"}}, {"33.5": {"batsman": "BRM Taylor", "bowler": "WD Parnell", "runs": {"batsman": 0, "total": 0, "extras": 0}, "non_striker": "T Taibu"}}, {"33.6": {"batsman": "BRM Taylor", "bowler": "WD Parnell", "runs": {"batsman": 0, "total": 0, "extras": 0}, "non_striker": "T Taibu"}}, {"34.1": {"batsman": "T Taibu", "bowler": "J Botha", "runs": {"batsman": 0, "total": 0, "extras": 0}, "non_striker": "BRM Taylor"}}, {"34.2": {"batsman": "T Taibu", "bowler": "J Botha", "runs": {"batsman": 2, "total": 2, "extras": 0}, "non_striker": "BRM Taylor"}}, {"34.3": {"batsman": "T Taibu", "bowler": "J Botha", "runs": {"batsman": 0, "total": 0, "extras": 0}, "non_striker": "BRM Taylor", "wicket": {"fielders": ["HM Amla"], "kind": "caught", "player_out": "T Taibu"}}}, {"34.4": {"batsman": "BRM Taylor", "bowler": "J Botha", "runs": {"batsman": 1, "total": 1, "extras": 0}, "non_striker": "E Chigumbura"}}, {"34.5": {"batsman": "E Chigumbura", "bowler": "J Botha", "runs": {"batsman": 0, "total": 0, "extras": 0}, "non_striker": "BRM Taylor"}}, {"34.6": {"batsman": "E Chigumbura", "bowler": "J Botha", "runs": {"batsman": 1, "total": 1, "extras": 0}, "non_striker": "BRM Taylor"}}, {"35.1": {"batsman": "E Chigumbura", "bowler": "WD Parnell", "runs": {"batsman": 1, "total": 1, "extras": 0}, "non_striker": "BRM Taylor"}}, {"35.2": {"batsman": "BRM Taylor", "bowler": "WD Parnell", "runs": {"batsman": 0, "total": 0, "extras": 0}, "non_striker": "E Chigumbura"}}, {"35.3": {"batsman": "BRM Taylor", "bowler": "WD Parnell", "runs": {"batsman": 1, "total": 1, "extras": 0}, "non_striker": "E Chigumbura"}}, {"35.4": {"batsman": "E Chigumbura", "bowler": "WD Parnell", "runs": {"batsman": 0, "total": 0, "extras": 0}, "non_striker": "BRM Taylor"}}, {"35.5": {"batsman": "E Chigumbura", "bowler": "WD Parnell", "runs": {"batsman": 1, "total": 1, "extras": 0}, "non_striker": "BRM Taylor"}}, {"35.6": {"batsman": "BRM Taylor", "bowler": "WD Parnell", "runs": {"batsman": 0, "total": 0, "extras": 0}, "non_striker": "E Chigumbura"}}, {"36.1": {"batsman": "E Chigumbura", "bowler": "JA Morkel", "runs": {"batsman": 0, "total": 0, "extras": 0}, "non_striker": "BRM Taylor"}}, {"36.2": {"batsman": "E Chigumbura", "bowler": "JA Morkel", "runs": {"batsman": 0, "total": 0, "extras": 0}, "non_striker": "BRM Taylor"}}, {"36.3": {"batsman": "E Chigumbura", "bowler": "JA Morkel", "runs": {"batsman": 1, "total": 1, "extras": 0}, "non_striker": "BRM Taylor"}}, {"36.4": {"batsman": "BRM Taylor", "bowler": "JA Morkel", "runs": {"batsman": 1, "total": 1, "extras": 0}, "non_striker": "E Chigumbura"}}, {"36.5": {"batsman": "E Chigumbura", "bowler": "JA Morkel", "runs": {"batsman": 0, "total": 0, "extras": 0}, "non_striker": "BRM Taylor"}}, {"36.6": {"batsman": "E Chigumbura", "bowler": "JA Morkel", "runs": {"batsman": 4, "total": 4, "extras": 0}, "non_striker": "BRM Taylor"}}, {"37.1": {"batsman": "BRM Taylor", "bowler": "CK Langeveldt", "runs": {"batsman": 2, "total": 2, "extras": 0}, "non_striker": "E Chigumbura"}}, {"37.2": {"batsman": "BRM Taylor", "bowler": "CK Langeveldt", "runs": {"batsman": 1, "total": 1, "extras": 0}, "non_striker": "E Chigumbura"}}, {"37.3": {"batsman": "E Chigumbura", "bowler": "CK Langeveldt", "runs": {"batsman": 0, "total": 0, "extras": 0}, "non_striker": "BRM Taylor"}}, {"37.4": {"batsman": "E Chigumbura", "bowler": "CK Langeveldt", "runs": {"batsman": 1, "total": 1, "extras": 0}, "non_striker": "BRM Taylor"}}, {"37.5": {"batsman": "BRM Taylor", "bowler": "CK Langeveldt", "runs": {"batsman": 1, "total": 1, "extras": 0}, "non_striker": "E Chigumbura"}}, {"37.6": {"batsman": "E Chigumbura", "bowler": "CK Langeveldt", "runs": {"batsman": 0, "total": 0, "extras": 0}, "non_striker": "BRM Taylor"}}, {"38.1": {"batsman": "BRM Taylor", "bowler": "JA Morkel", "runs": {"batsman": 2, "total": 2, "extras": 0}, "non_striker": "E Chigumbura"}}, {"38.2": {"batsman": "BRM Taylor", "bowler": "JA Morkel", "runs": {"batsman": 1, "total": 1, "extras": 0}, "non_striker": "E Chigumbura"}}, {"38.3": {"batsman": "E Chigumbura", "bowler": "JA Morkel", "runs": {"batsman": 1, "total": 1, "extras": 0}, "non_striker": "BRM Taylor"}}, {"38.4": {"batsman": "BRM Taylor", "bowler": "JA Morkel", "runs": {"batsman": 0, "total": 0, "extras": 0}, "non_striker": "E Chigumbura"}}, {"38.5": {"batsman": "BRM Taylor", "bowler": "JA Morkel", "runs": {"batsman": 2, "total": 2, "extras": 0}, "non_striker": "E Chigumbura"}}, {"38.6": {"batsman": "BRM Taylor", "bowler": "JA Morkel", "runs": {"batsman": 1, "total": 1, "extras": 0}, "non_striker": "E Chigumbura"}}, {"39.1": {"batsman": "BRM Taylor", "bowler": "CK Langeveldt", "runs": {"batsman": 0, "total": 1, "extras": 1}, "extras": {"legbyes": 1}, "non_striker": "E Chigumbura"}}, {"39.2": {"batsman": "E Chigumbura", "bowler": "CK Langeveldt", "runs": {"batsman": 0, "total": 1, "extras": 1}, "extras": {"wides": 1}, "non_striker": "BRM Taylor"}}, {"39.3": {"batsman": "E Chigumbura", "bowler": "CK Langeveldt", "runs": {"batsman": 0, "total": 0, "extras": 0}, "non_striker": "BRM Taylor"}}, {"39.4": {"batsman": "E Chigumbura", "bowler": "CK Langeveldt", "runs": {"batsman": 1, "total": 1, "extras": 0}, "non_striker": "BRM Taylor"}}, {"39.5": {"batsman": "BRM Taylor", "bowler": "CK Langeveldt", "runs": {"batsman": 0, "total": 0, "extras": 0}, "non_striker": "E Chigumbura"}}, {"39.6": {"batsman": "BRM Taylor", "bowler": "CK Langeveldt", "runs": {"batsman": 0, "total": 1, "extras": 1}, "extras": {"wides": 1}, "non_striker": "E Chigumbura"}}, {"39.7": {"batsman": "BRM Taylor", "bowler": "CK Langeveldt", "runs": {"batsman": 0, "total": 1, "extras": 1}, "extras": {"wides": 1}, "non_striker": "E Chigumbura"}}, {"39.8": {"batsman": "BRM Taylor", "bowler": "CK Langeveldt", "runs": {"batsman": 1, "total": 1, "extras": 0}, "non_striker": "E Chigumbura"}}, {"39.9": {"batsman": "E Chigumbura", "bowler": "CK Langeveldt", "runs": {"batsman": 0, "total": 0, "extras": 0}, "non_striker": "BRM Taylor"}}, {"40.1": {"batsman": "BRM Taylor", "bowler": "J Theron", "runs": {"batsman": 0, "total": 0, "extras": 0}, "non_striker": "E Chigumbura"}}, {"40.2": {"batsman": "BRM Taylor", "bowler": "J Theron", "runs": {"batsman": 1, "total": 1, "extras": 0}, "non_striker": "E Chigumbura"}}, {"40.3": {"batsman": "BRM Taylor", "bowler": "J Theron", "runs": {"batsman": 4, "total": 4, "extras": 0}, "non_striker": "E Chigumbura"}}, {"40.4": {"batsman": "BRM Taylor", "bowler": "J Theron", "runs": {"batsman": 0, "total": 0, "extras": 0}, "non_striker": "E Chigumbura"}}, {"40.5": {"batsman": "BRM Taylor", "bowler": "J Theron", "runs": {"batsman": 1, "total": 1, "extras": 0}, "non_striker": "E Chigumbura"}}, {"40.6": {"batsman": "E Chigumbura", "bowler": "J Theron", "runs": {"batsman": 0, "total": 0, "extras": 0}, "non_striker": "BRM Taylor"}}, {"41.1": {"batsman": "BRM Taylor", "bowler": "CK Langeveldt", "runs": {"batsman": 4, "total": 4, "extras": 0}, "non_striker": "E Chigumbura"}}, {"41.2": {"batsman": "BRM Taylor", "bowler": "CK Langeveldt", "runs": {"batsman": 1, "total": 1, "extras": 0}, "non_striker": "E Chigumbura"}}, {"41.3": {"batsman": "E Chigumbura", "bowler": "CK Langeveldt", "runs": {"batsman": 0, "total": 0, "extras": 0}, "non_striker": "BRM Taylor"}}, {"41.4": {"batsman": "E Chigumbura", "bowler": "CK Langeveldt", "runs": {"batsman": 1, "total": 1, "extras": 0}, "non_striker": "BRM Taylor"}}, {"41.5": {"batsman": "BRM Taylor", "bowler": "CK Langeveldt", "runs": {"batsman": 2, "total": 2, "extras": 0}, "non_striker": "E Chigumbura"}}, {"41.6": {"batsman": "BRM Taylor", "bowler": "CK Langeveldt", "runs": {"batsman": 2, "total": 2, "extras": 0}, "non_striker": "E Chigumbura"}}, {"42.1": {"batsman": "E Chigumbura", "bowler": "J Theron", "runs": {"batsman": 1, "total": 1, "extras": 0}, "non_striker": "BRM Taylor"}}, {"42.2": {"batsman": "BRM Taylor", "bowler": "J Theron", "runs": {"batsman": 2, "total": 2, "extras": 0}, "non_striker": "E Chigumbura"}}, {"42.3": {"batsman": "BRM Taylor", "bowler": "J Theron", "runs": {"batsman": 1, "total": 1, "extras": 0}, "non_striker": "E Chigumbura"}}, {"42.4": {"batsman": "E Chigumbura", "bowler": "J Theron", "runs": {"batsman": 1, "total": 1, "extras": 0}, "non_striker": "BRM Taylor"}}, {"42.5": {"batsman": "BRM Taylor", "bowler": "J Theron", "runs": {"batsman": 4, "total": 4, "extras": 0}, "non_striker": "E Chigumbura"}}, {"42.6": {"batsman": "BRM Taylor", "bowler": "J Theron", "runs": {"batsman": 1, "total": 1, "extras": 0}, "non_striker": "E Chigumbura"}}, {"43.1": {"batsman": "BRM Taylor", "bowler": "WD Parnell", "runs": {"batsman": 0, "total": 0, "extras": 0}, "non_striker": "E Chigumbura"}}, {"43.2": {"batsman": "BRM Taylor", "bowler": "WD Parnell", "runs": {"batsman": 2, "total": 2, "extras": 0}, "non_striker": "E Chigumbura"}}, {"43.3": {"batsman": "BRM Taylor", "bowler": "WD Parnell", "runs": {"batsman": 0, "total": 0, "extras": 0}, "non_striker": "E Chigumbura"}}, {"43.4": {"batsman": "BRM Taylor", "bowler": "WD Parnell", "runs": {"batsman": 1, "total": 1, "extras": 0}, "non_striker": "E Chigumbura"}}, {"43.5": {"batsman": "E Chigumbura", "bowler": "WD Parnell", "runs": {"batsman": 4, "total": 4, "extras": 0}, "non_striker": "BRM Taylor"}}, {"43.6": {"batsman": "E Chigumbura", "bowler": "WD Parnell", "runs": {"batsman": 1, "total": 1, "extras": 0}, "non_striker": "BRM Taylor"}}, {"44.1": {"batsman": "E Chigumbura", "bowler": "J Theron", "runs": {"batsman": 4, "total": 4, "extras": 0}, "non_striker": "BRM Taylor"}}, {"44.2": {"batsman": "E Chigumbura", "bowler": "J Theron", "runs": {"batsman": 0, "total": 0, "extras": 0}, "non_striker": "BRM Taylor", "wicket": {"fielders": ["JA Morkel"], "kind": "caught", "player_out": "E Chigumbura"}}}, {"44.3": {"batsman": "P Utseya", "bowler": "J Theron", "runs": {"batsman": 1, "total": 1, "extras": 0}, "non_striker": "BRM Taylor"}}, {"44.4": {"batsman": "BRM Taylor", "bowler": "J Theron", "runs": {"batsman": 1, "total": 1, "extras": 0}, "non_striker": "P Utseya"}}, {"44.5": {"batsman": "P Utseya", "bowler": "J Theron", "runs": {"batsman": 0, "total": 0, "extras": 0}, "non_striker": "BRM Taylor"}}, {"44.6": {"batsman": "P Utseya", "bowler": "J Theron", "runs": {"batsman": 0, "total": 0, "extras": 0}, "non_striker": "BRM Taylor"}}, {"45.1": {"batsman": "BRM Taylor", "bowler": "WD Parnell", "runs": {"batsman": 1, "total": 1, "extras": 0}, "non_striker": "P Utseya"}}, {"45.2": {"batsman": "P Utseya", "bowler": "WD Parnell", "runs": {"batsman": 1, "total": 1, "extras": 0}, "non_striker": "BRM Taylor"}}, {"45.3": {"batsman": "BRM Taylor", "bowler": "WD Parnell", "runs": {"batsman": 4, "total": 4, "extras": 0}, "non_striker": "P Utseya"}}, {"45.4": {"batsman": "BRM Taylor", "bowler": "WD Parnell", "runs": {"batsman": 1, "total": 1, "extras": 0}, "non_striker": "P Utseya"}}, {"45.5": {"batsman": "P Utseya", "bowler": "WD Parnell", "runs": {"batsman": 1, "total": 1, "extras": 0}, "non_striker": "BRM Taylor"}}, {"45.6": {"batsman": "BRM Taylor", "bowler": "WD Parnell", "runs": {"batsman": 4, "total": 4, "extras": 0}, "non_striker": "P Utseya"}}, {"46.1": {"batsman": "P Utseya", "bowler": "J Theron", "runs": {"batsman": 1, "total": 1, "extras": 0}, "non_striker": "BRM Taylor"}}, {"46.2": {"batsman": "BRM Taylor", "bowler": "J Theron", "runs": {"batsman": 2, "total": 2, "extras": 0}, "non_striker": "P Utseya"}}, {"46.3": {"batsman": "BRM Taylor", "bowler": "J Theron", "runs": {"batsman": 1, "total": 1, "extras": 0}, "non_striker": "P Utseya"}}, {"46.4": {"batsman": "P Utseya", "bowler": "J Theron", "runs": {"batsman": 0, "total": 0, "extras": 0}, "non_striker": "BRM Taylor"}}, {"46.5": {"batsman": "P Utseya", "bowler": "J Theron", "runs": {"batsman": 4, "total": 4, "extras": 0}, "non_striker": "BRM Taylor"}}, {"46.6": {"batsman": "P Utseya", "bowler": "J Theron", "runs": {"batsman": 1, "total": 1, "extras": 0}, "non_striker": "BRM Taylor"}}, {"47.1": {"batsman": "P Utseya", "bowler": "CK Langeveldt", "runs": {"batsman": 4, "total": 4, "extras": 0}, "non_striker": "BRM Taylor"}}, {"47.2": {"batsman": "P Utseya", "bowler": "CK Langeveldt", "runs": {"batsman": 0, "total": 0, "extras": 0}, "non_striker": "BRM Taylor"}}, {"47.3": {"batsman": "P Utseya", "bowler": "CK Langeveldt", "runs": {"batsman": 0, "total": 0, "extras": 0}, "non_striker": "BRM Taylor"}}, {"47.4": {"batsman": "P Utseya", "bowler": "CK Langeveldt", "runs": {"batsman": 4, "total": 4, "extras": 0}, "non_striker": "BRM Taylor"}}, {"47.5": {"batsman": "P Utseya", "bowler": "CK Langeveldt", "runs": {"batsman": 0, "total": 0, "extras": 0}, "non_striker": "BRM Taylor"}}, {"47.6": {"batsman": "P Utseya", "bowler": "CK Langeveldt", "runs": {"batsman": 1, "total": 1, "extras": 0}, "non_striker": "BRM Taylor"}}, {"48.1": {"batsman": "P Utseya", "bowler": "JA Morkel", "runs": {"batsman": 1, "total": 1, "extras": 0}, "non_striker": "BRM Taylor"}}, {"48.2": {"batsman": "BRM Taylor", "bowler": "JA Morkel", "runs": {"batsman": 0, "total": 0, "extras": 0}, "non_striker": "P Utseya"}}, {"48.3": {"batsman": "BRM Taylor", "bowler": "JA Morkel", "runs": {"batsman": 2, "total": 2, "extras": 0}, "non_striker": "P Utseya"}}, {"48.4": {"batsman": "BRM Taylor", "bowler": "JA Morkel", "runs": {"batsman": 0, "total": 0, "extras": 0}, "non_striker": "P Utseya"}}, {"48.5": {"batsman": "BRM Taylor", "bowler": "JA Morkel", "runs": {"batsman": 1, "total": 1, "extras": 0}, "non_striker": "P Utseya"}}, {"48.6": {"batsman": "P Utseya", "bowler": "JA Morkel", "runs": {"batsman": 1, "total": 1, "extras": 0}, "non_striker": "BRM Taylor"}}, {"49.1": {"batsman": "P Utseya", "bowler": "CK Langeveldt", "runs": {"batsman": 0, "total": 0, "extras": 0}, "non_striker": "BRM Taylor"}}, {"49.2": {"batsman": "P Utseya", "bowler": "CK Langeveldt", "runs": {"batsman": 1, "total": 1, "extras": 0}, "non_striker": "BRM Taylor"}}, {"49.3": {"batsman": "BRM Taylor", "bowler": "CK Langeveldt", "runs": {"batsman": 1, "total": 1, "extras": 0}, "non_striker": "P Utseya"}}, {"49.4": {"batsman": "P Utseya", "bowler": "CK Langeveldt", "runs": {"batsman": 1, "total": 1, "extras": 0}, "non_striker": "BRM Taylor"}}, {"49.5": {"batsman": "BRM Taylor", "bowler": "CK Langeveldt", "runs": {"batsman": 0, "total": 0, "extras": 0}, "non_striker": "P Utseya"}}, {"49.6": {"batsman": "BRM Taylor", "bowler": "CK Langeveldt", "runs": {"batsman": 1, "total": 1, "extras": 0}, "non_striker": "P Utseya"}}], "team": "Zimbabwe"}}], "meta": {"data_version": 0.6, "created": {"month": 11, "day": 16, "year": 2010}, "revision": 1}}